Workbook

Sheet Team Info
A1: Team Number: | B1: 1
D2: Emphasis Company: | K2: Compare Company:
A3: Team Member Name: | B3: Email:
A4: Joel Applegate | B4: jaa9436@uncw.edu
A5: Joey Bridgham | B5: jjb3229@uncw.edu
A6: Owen Bieler | B6: orb1456@uncw.edu
A7: Taylor Chapman | B7: tlc3246@uncw.edu
A8: Colin Waltsak | B8: cpw9627@uncw.edu

Sheet D1_Balance Sheet
A1: Line Items | B1: Year(t=0) | C1: Year(t=-1) | D1: Year(t=-2) | E1: Year(t=-3) | F1: Year(t=-4) | G1: Year(t=-5) | J1: MEAN | K1: STD | L1: MIN | M1: MEDIAN | N1: MAX
B2: 2025 | C2: 2024 | D2: 2023 | E2: 2022 | F2: 2021 | G2: 2020
A3: Current Assets
A4: Cash and Cash Equivalents | B4: 23356 | C4: 22935 | D4: 24862 | E4: 25134 | F4: 20540 | G4: 25243 | J4: =AVERAGE(B4:G4) -> 23678.333 | K4: =STDEV(B4:G4) -> 1815.147 | L4: =MIN(B4:G4) -> 20540 | M4: =MEDIAN(B4:G4) -> 24109 | N4: =MAX(B4:G4) -> 25243
A5: Marketable Securities | B5: 15131 | C5: 15413 | D5: 15309 | E5: 18936 | F5: 29053 | G5: 24718 | J5: =AVERAGE(B5:G5) -> 19760 | K5: =STDEV(B5:G5) -> 5860.9904 | L5: =MIN(B5:G5) -> 15131 | M5: =MEDIAN(B5:G5) -> 17174.5 | N5: =MAX(B5:G5) -> 29053
A6: Trade and Other Receivables | B6: 15398 | C6: 14723 | D6: 15601 | E6: 15729 | F6: 11370 | G6: 9993 | J6: =AVERAGE(B6:G6) -> 13802.333 | K6: =STDEV(B6:G6) -> 2480.6568 | L6: =MIN(B6:G6) -> 9993 | M6: =MEDIAN(B6:G6) -> 15060.5 | N6: =MAX(B6:G6) -> 15729
A7: Inventories | B7: 15285 | C7: 14951 | D7: 15651 | E7: 14080 | F7: 12065 | G7: 10808 | J7: =AVERAGE(B7:G7) -> 13806.667 | K7: =STDEV(B7:G7) -> 1949.187 | L7: =MIN(B7:G7) -> 10808 | M7: =MEDIAN(B7:G7) -> 14515.5 | N7: =MAX(B7:G7) -> 15651
A8: Financial Services Finance Receivables, Net | B8: 49130 | C8: 51850 | D8: 46425 | E8: 38720 | F8: 32543 | G8: 42401 | J8: =AVERAGE(B8:G8) -> 43511.5 | K8: =STDEV(B8:G8) -> 7128.6223 | L8: =MIN(B8:G8) -> 32543 | M8: =MEDIAN(B8:G8) -> 44413 | N8: =MAX(B8:G8) -> 51850
A9: Asset Held for Sale | F9: 9 | J9: =AVERAGE(B9:G9) -> 9 | K9: =STDEV(B9:G9) -> #DIV/0! | L9: =MIN(B9:G9) -> 9 | M9: =MEDIAN(B9:G9) -> 9 | N9: =MAX(B9:G9) -> 9
A10: Other Current Assets | B10: 5187 | C10: 4602 | D10: 3633 | E10: 3877 | F10: 3416 | G10: 3581 | J10: =AVERAGE(B10:G10) -> 4049.3333 | K10: =STDEV(B10:G10) -> 696.16167 | L10: =MIN(B10:G10) -> 3416 | M10: =MEDIAN(B10:G10) -> 3755 | N10: =MAX(B10:G10) -> 5187
A11: Total Current Assets | B11: 123487 | C11: 124474 | D11: 121481 | E11: 116476 | F11: 108996 | G11: 116744 | J11: =AVERAGE(B11:G11) -> 118609.67 | K11: =STDEV(B11:G11) -> 5777.1822 | L11: =MIN(B11:G11) -> 108996 | M11: =MEDIAN(B11:G11) -> 119112.5 | N11: =MAX(B11:G11) -> 124474
A12: Noncurrent Assets
A13: Net Property | B13: 37288 | C13: 41928 | D13: 40821 | E13: 37265 | F13: 37139 | G13: 37083 | J13: =AVERAGE(B13:G13) -> 38587.333 | K13: =STDEV(B13:G13) -> 2188.4625 | L13: =MIN(B13:G13) -> 37083 | M13: =MEDIAN(B13:G13) -> 37276.5 | N13: =MAX(B13:G13) -> 41928
A14: Net Investment in Operating Leases | B14: 28540 | C14: 22947 | D14: 21384 | E14: 22772 | F14: 26361 | G14: 27951 | J14: =AVERAGE(B14:G14) -> 24992.5 | K14: =STDEV(B14:G14) -> 3011.519 | L14: =MIN(B14:G14) -> 21384 | M14: =MEDIAN(B14:G14) -> 24654 | N14: =MAX(B14:G14) -> 28540
A15: Equity in Net Assets of Affiliated Companies | B15: 2753 | C15: 6821 | D15: 5548 | E15: 2798 | F15: 4545 | G15: 4901 | J15: =AVERAGE(B15:G15) -> 4561 | K15: =STDEV(B15:G15) -> 1585.8536 | L15: =MIN(B15:G15) -> 2753 | M15: =MEDIAN(B15:G15) -> 4723 | N15: =MAX(B15:G15) -> 6821
A16: Deferred Income Taxes | B16: 21953 | C16: 16375 | D16: 16985 | E16: 15552 | F16: 13796 | G16: 12423 | J16: =AVERAGE(B16:G16) -> 16180.667 | K16: =STDEV(B16:G16) -> 3292.6119 | L16: =MIN(B16:G16) -> 12423 | M16: =MEDIAN(B16:G16) -> 15963.5 | N16: =MAX(B16:G16) -> 21953
A17: Ford Credit Finance Receivables, Net | B17: 61449 | C17: 59786 | D17: 55650 | E17: 49903 | F17: 51256 | G17: 55277 | J17: =AVERAGE(B17:G17) -> 55553.5 | K17: =STDEV(B17:G17) -> 4542.1008 | L17: =MIN(B17:G17) -> 49903 | M17: =MEDIAN(B17:G17) -> 55463.5 | N17: =MAX(B17:G17) -> 61449
A18: Other Assets | B18: 13690 | C18: 12865 | D18: 11441 | E18: 11118 | F18: 14942 | G18: 12882 | J18: =AVERAGE(B18:G18) -> 12823 | K18: =STDEV(B18:G18) -> 1418.7349 | L18: =MIN(B18:G18) -> 11118 | M18: =MEDIAN(B18:G18) -> 12873.5 | N18: =MAX(B18:G18) -> 14942
A19: Total Assets | B19: 289160 | C19: 285196 | D19: 273310 | E19: 255884 | F19: 257035 | G19: 267261 | J19: =AVERAGE(B19:G19) -> 271307.67 | K19: =STDEV(B19:G19) -> 13954.031 | L19: =MIN(B19:G19) -> 255884 | M19: =MEDIAN(B19:G19) -> 270285.5 | N19: =MAX(B19:G19) -> 289160
A20: Current Liabilities
A21: Company Excluding Ford Credit | B21: 5550 | C21: 1756 | D21: 477 | E21: 730 | F21: 3175 | G21: 1374 | J21: =AVERAGE(B21:G21) -> 2177 | K21: =STDEV(B21:G21) -> 1906.777 | L21: =MIN(B21:G21) -> 477 | M21: =MEDIAN(B21:G21) -> 1565 | N21: =MAX(B21:G21) -> 5550
A22: Ford Credit | J22: =AVERAGE(B22:G22) -> #DIV/0! | K22: =STDEV(B22:G22) -> #DIV/0! | L22: =MIN(B22:G22) -> 0 | M22: =MEDIAN(B22:G22) -> #NUM! | N22: =MAX(B22:G22) -> 0
A23: Ford Credit Debt Payable within One Year | B23: 51752 | C23: 53193 | D23: 49192 | E23: 49434 | F23: 46517 | G23: 49969 | J23: =AVERAGE(B23:G23) -> 50009.5 | K23: =STDEV(B23:G23) -> 2296.5052 | L23: =MIN(B23:G23) -> 46517 | M23: =MEDIAN(B23:G23) -> 49701.5 | N23: =MAX(B23:G23) -> 53193
A24: Payables | B24: 25809 | C24: 24128 | D24: 25992 | E24: 25605 | F24: 22349 | G24: 22204 | J24: =AVERAGE(B24:G24) -> 24347.833 | K24: =STDEV(B24:G24) -> 1735.4217 | L24: =MIN(B24:G24) -> 22204 | M24: =MEDIAN(B24:G24) -> 24866.5 | N24: =MAX(B24:G24) -> 25992
A25: Other Liabilities and Deferred Revenue | B25: 31779 | C25: 27782 | D25: 25870 | E25: 21097 | F25: 18686 | G25: 23645 | J25: =AVERAGE(B25:G25) -> 24809.833 | K25: =STDEV(B25:G25) -> 4715.3009 | L25: =MIN(B25:G25) -> 18686 | M25: =MEDIAN(B25:G25) -> 24757.5 | N25: =MAX(B25:G25) -> 31779
A26: Total Current Liabilities | B26: 114890 | C26: 106859 | D26: 101531 | E26: 96866 | F26: 90727 | G26: 97192 | J26: =AVERAGE(B26:G26) -> 101344.17 | K26: =STDEV(B26:G26) -> 8531.7828 | L26: =MIN(B26:G26) -> 90727 | M26: =MEDIAN(B26:G26) -> 99361.5 | N26: =MAX(B26:G26) -> 114890
A27: Noncurrent Liabilities
A28: Company Excluding Ford Credit | B28: 16369 | C28: 18898 | D28: 19467 | E28: 19200 | F28: 17200 | G28: 22633 | J28: =AVERAGE(B28:G28) -> 18961.167 | K28: =STDEV(B28:G28) -> 2173.49 | L28: =MIN(B28:G28) -> 16369 | M28: =MEDIAN(B28:G28) -> 19049 | N28: =MAX(B28:G28) -> 22633
A29: Deferred Income Taxes | B29: 1354 | C29: 1074 | D29: 1005 | E29: 1549 | F29: 1581 | G29: 538 | J29: =AVERAGE(B29:G29) -> 1183.5 | K29: =STDEV(B29:G29) -> 395.2694 | L29: =MIN(B29:G29) -> 538 | M29: =MEDIAN(B29:G29) -> 1214 | N29: =MAX(B29:G29) -> 1581
A30: Minority Interest | B30: 28 | C30: 23 | D30: 25 | E30: -75 | F30: 103 | G30: 121 | J30: =AVERAGE(B30:G30) -> 37.5 | K30: =STDEV(B30:G30) -> 69.821916 | L30: =MIN(B30:G30) -> -75 | M30: =MEDIAN(B30:G30) -> 26.5 | N30: =MAX(B30:G30) -> 121
A31: Ford Credit | J31: =AVERAGE(B31:G31) -> #DIV/0! | K31: =STDEV(B31:G31) -> #DIV/0! | L31: =MIN(B31:G31) -> 0 | M31: =MEDIAN(B31:G31) -> #NUM! | N31: =MAX(B31:G31) -> 0
A32: Ford Credit Long- Term Debt | B32: 89665 | C32: 84675 | D32: 80095 | E32: 69605 | F32: 71200 | G32: 87708 | J32: =AVERAGE(B32:G32) -> 80491.333 | K32: =STDEV(B32:G32) -> 8470.3921 | L32: =MIN(B32:G32) -> 69605 | M32: =MEDIAN(B32:G32) -> 82385 | N32: =MAX(B32:G32) -> 89665
A33: Other Liabilities and Deferred Revenue | B33: 30902 | C33: 28832 | D33: 28414 | E33: 25497 | F33: 27705 | G33: 28379 | J33: =AVERAGE(B33:G33) -> 28288.167 | K33: =STDEV(B33:G33) -> 1748.294 | L33: =MIN(B33:G33) -> 25497 | M33: =MEDIAN(B33:G33) -> 28396.5 | N33: =MAX(B33:G33) -> 30902
A34: Shareholders' Equity
A35: Common Stock - Par Value | B35: 1 | C35: 1 | D35: 1 | E35: 1 | F35: 1 | G35: 1 | J35: =AVERAGE(B35:G35) -> 1 | K35: =STDEV(B35:G35) -> 0 | L35: =MIN(B35:G35) -> 1 | M35: =MEDIAN(B35:G35) -> 1 | N35: =MAX(B35:G35) -> 1
A36: Common Stock - Par Value | B36: 41 | C36: 41 | D36: 41 | E36: 41 | F36: 40 | G36: 40 | J36: =AVERAGE(B36:G36) -> 40.666667 | K36: =STDEV(B36:G36) -> 0.51639778 | L36: =MIN(B36:G36) -> 40 | M36: =MEDIAN(B36:G36) -> 41 | N36: =MAX(B36:G36) -> 41
A37: Additional Paid in Capital | B37: 23922 | C37: 23502 | D37: 23128 | E37: 22832 | F37: 22611 | G37: 22290 | J37: =AVERAGE(B37:G37) -> 23047.5 | K37: =STDEV(B37:G37) -> 598.09355 | L37: =MIN(B37:G37) -> 22290 | M37: =MEDIAN(B37:G37) -> 22980 | N37: =MAX(B37:G37) -> 23922
A38: Treasury Stock - Common | B38: -2810 | C38: -2810 | D38: -2384 | E38: -2047 | F38: -1563 | G38: -1590 | J38: =AVERAGE(B38:G38) -> -2200.6667 | K38: =STDEV(B38:G38) -> 562.01981 | L38: =MIN(B38:G38) -> -2810 | M38: =MEDIAN(B38:G38) -> -2215.5 | N38: =MAX(B38:G38) -> -1563
A39: Retained Earnings | J39: =AVERAGE(B39:G39) -> #DIV/0! | K39: =STDEV(B39:G39) -> #DIV/0! | L39: =MIN(B39:G39) -> 0 | M39: =MEDIAN(B39:G39) -> #NUM! | N39: =MAX(B39:G39) -> 0
A40: Retained Earnings (Accumulated Deficit) | B40: 22508 | C40: 33740 | D40: 31029 | E40: 31754 | F40: 35769 | G40: 18243 | J40: =AVERAGE(B40:G40) -> 28840.5 | K40: =STDEV(B40:G40) -> 6894.8501 | L40: =MIN(B40:G40) -> 18243 | M40: =MEDIAN(B40:G40) -> 31391.5 | N40: =MAX(B40:G40) -> 35769
A41: Accumulated Other Comprehensive Income (Loss) | B41: -7710 | C41: -9639 | D41: -9042 | E41: -9339 | F41: -8339 | G41: -8294 | J41: =AVERAGE(B41:G41) -> -8727.1667 | K41: =STDEV(B41:G41) -> 731.82441 | L41: =MIN(B41:G41) -> -9639 | M41: =MEDIAN(B41:G41) -> -8690.5 | N41: =MAX(B41:G41) -> -7710
A42: Total Shareholders Equity | B42: 35952 | C42: 44835 | D42: 42773 | E42: 43242 | F42: 48519 | G42: 30690 | J42: =AVERAGE(B42:G42) -> 41001.833 | K42: =STDEV(B42:G42) -> 6499.0932 | L42: =MIN(B42:G42) -> 30690 | M42: =MEDIAN(B42:G42) -> 43007.5 | N42: =MAX(B42:G42) -> 48519
A43: Total Liabilities & Shareholders Equity | B43: 289160 | C43: 285196 | D43: 273310 | E43: 255884 | F43: 257035 | G43: 267261 | J43: =AVERAGE(B43:G43) -> 271307.67 | K43: =STDEV(B43:G43) -> 13954.031 | L43: =MIN(B43:G43) -> 255884 | M43: =MEDIAN(B43:G43) -> 270285.5 | N43: =MAX(B43:G43) -> 289160
A44: Total liabilties | B44: =B43-B42 -> 253208 | C44: =C43-C42 -> 240361 | D44: =D43-D42 -> 230537 | E44: =E43-E42 -> 212642 | F44: =F43-F42 -> 208516 | G44: =G43-G42 -> 236571

Sheet D2_BalanceSheetCommonSize
A1: Common Size balance sheet | B1: Year(t=0) | C1: Year(t=-1) | D1: Year(t=-2) | E1: Year(t=-3) | F1: Year(t=-4) | G1: Year(t=-5)
A2: % of Total assests = (line item/total assests)x100
B3: 2025 | C3: 2024 | D3: 2023 | E3: 2022 | F3: 2021 | G3: 2020
A4: Current Assets
A5: Cash and Cash Equivalents | B5: =('D1_Balance Sheet'!B4/'D1_Balance Sheet'!$B$19) -> 0.080771891 | C5: =('D1_Balance Sheet'!C4/'D1_Balance Sheet'!$C$19) -> 0.080418379 | D5: =('D1_Balance Sheet'!D4/'D1_Balance Sheet'!$D$19) -> 0.090966302 | E5: =('D1_Balance Sheet'!E4/'D1_Balance Sheet'!$E$19) -> 0.098224195 | F5: =('D1_Balance Sheet'!F4/'D1_Balance Sheet'!$F$19) -> 0.079911296 | G5: =('D1_Balance Sheet'!G4/'D1_Balance Sheet'!$G$19) -> 0.094450743
A6: Marketable Securities | B6: =('D1_Balance Sheet'!B5/'D1_Balance Sheet'!$B$19) -> 0.052327431 | C6: =('D1_Balance Sheet'!C5/'D1_Balance Sheet'!$C$19) -> 0.054043535 | D6: =('D1_Balance Sheet'!D5/'D1_Balance Sheet'!$D$19) -> 0.056013318 | E6: =('D1_Balance Sheet'!E5/'D1_Balance Sheet'!$E$19) -> 0.074002282 | F6: =('D1_Balance Sheet'!F5/'D1_Balance Sheet'!$F$19) -> 0.1130313 | G6: =('D1_Balance Sheet'!G5/'D1_Balance Sheet'!$G$19) -> 0.092486371
A7: Trade and Other Receivables | B7: =('D1_Balance Sheet'!B6/'D1_Balance Sheet'!$B$19) -> 0.053250795 | C7: =('D1_Balance Sheet'!C6/'D1_Balance Sheet'!$C$19) -> 0.051624146 | D7: =('D1_Balance Sheet'!D6/'D1_Balance Sheet'!$D$19) -> 0.057081702 | E7: =('D1_Balance Sheet'!E6/'D1_Balance Sheet'!$E$19) -> 0.06146926 | F7: =('D1_Balance Sheet'!F6/'D1_Balance Sheet'!$F$19) -> 0.044235221 | G7: =('D1_Balance Sheet'!G6/'D1_Balance Sheet'!$G$19) -> 0.037390416
A8: Inventories | B8: =('D1_Balance Sheet'!B7/'D1_Balance Sheet'!$B$19) -> 0.052860008 | C8: =('D1_Balance Sheet'!C7/'D1_Balance Sheet'!$C$19) -> 0.052423596 | D8: =('D1_Balance Sheet'!D7/'D1_Balance Sheet'!$D$19) -> 0.057264645 | E8: =('D1_Balance Sheet'!E7/'D1_Balance Sheet'!$E$19) -> 0.055024933 | F8: =('D1_Balance Sheet'!F7/'D1_Balance Sheet'!$F$19) -> 0.046939133 | G8: =('D1_Balance Sheet'!G7/'D1_Balance Sheet'!$G$19) -> 0.04043987
A9: Financial Services Finance Receivables, Net | B9: =('D1_Balance Sheet'!B8/'D1_Balance Sheet'!$B$19) -> 0.16990593 | C9: =('D1_Balance Sheet'!C8/'D1_Balance Sheet'!$C$19) -> 0.18180479 | D9: =('D1_Balance Sheet'!D8/'D1_Balance Sheet'!$D$19) -> 0.16986206 | E9: =('D1_Balance Sheet'!E8/'D1_Balance Sheet'!$E$19) -> 0.15131857 | F9: =('D1_Balance Sheet'!F8/'D1_Balance Sheet'!$F$19) -> 0.12660922 | G9: =('D1_Balance Sheet'!G8/'D1_Balance Sheet'!$G$19) -> 0.15865016
A10: Asset Held for Sale | B10: =('D1_Balance Sheet'!B9/'D1_Balance Sheet'!$B$19) -> 0 | C10: =('D1_Balance Sheet'!C9/'D1_Balance Sheet'!$C$19) -> 0 | D10: =('D1_Balance Sheet'!D9/'D1_Balance Sheet'!$D$19) -> 0 | E10: =('D1_Balance Sheet'!E9/'D1_Balance Sheet'!$E$19) -> 0 | F10: =('D1_Balance Sheet'!F9/'D1_Balance Sheet'!$F$19) -> 3.5014687e-05 | G10: =('D1_Balance Sheet'!G9/'D1_Balance Sheet'!$G$19) -> 0
A11: Other Current Assets | B11: =('D1_Balance Sheet'!B10/'D1_Balance Sheet'!$B$19) -> 0.017938166 | C11: =('D1_Balance Sheet'!C10/'D1_Balance Sheet'!$C$19) -> 0.016136271 | D11: =('D1_Balance Sheet'!D10/'D1_Balance Sheet'!$D$19) -> 0.013292598 | E11: =('D1_Balance Sheet'!E10/'D1_Balance Sheet'!$E$19) -> 0.015151397 | F11: =('D1_Balance Sheet'!F10/'D1_Balance Sheet'!$F$19) -> 0.013290019 | G11: =('D1_Balance Sheet'!G10/'D1_Balance Sheet'!$G$19) -> 0.013398887
A12: Total Current Assets | B12: =('D1_Balance Sheet'!B11/'D1_Balance Sheet'!$B$19) -> 0.42705423 | C12: =('D1_Balance Sheet'!C11/'D1_Balance Sheet'!$C$19) -> 0.43645072 | D12: =('D1_Balance Sheet'!D11/'D1_Balance Sheet'!$D$19) -> 0.44448063 | E12: =('D1_Balance Sheet'!E11/'D1_Balance Sheet'!$E$19) -> 0.45519063 | F12: =('D1_Balance Sheet'!F11/'D1_Balance Sheet'!$F$19) -> 0.4240512 | G12: =('D1_Balance Sheet'!G11/'D1_Balance Sheet'!$G$19) -> 0.43681645
A13: Noncurrent Assets | B13: =('D1_Balance Sheet'!B12/'D1_Balance Sheet'!$B$19) -> 0 | C13: =('D1_Balance Sheet'!C12/'D1_Balance Sheet'!$C$19) -> 0 | D13: =('D1_Balance Sheet'!D12/'D1_Balance Sheet'!$D$19) -> 0 | E13: =('D1_Balance Sheet'!E12/'D1_Balance Sheet'!$E$19) -> 0 | F13: =('D1_Balance Sheet'!F12/'D1_Balance Sheet'!$F$19) -> 0 | G13: =('D1_Balance Sheet'!G12/'D1_Balance Sheet'!$G$19) -> 0
A14: Net Property | B14: =('D1_Balance Sheet'!B13/'D1_Balance Sheet'!$B$19) -> 0.12895283 | C14: =('D1_Balance Sheet'!C13/'D1_Balance Sheet'!$C$19) -> 0.14701468 | D14: =('D1_Balance Sheet'!D13/'D1_Balance Sheet'!$D$19) -> 0.14935787 | E14: =('D1_Balance Sheet'!E13/'D1_Balance Sheet'!$E$19) -> 0.1456324 | F14: =('D1_Balance Sheet'!F13/'D1_Balance Sheet'!$F$19) -> 0.14449005 | G14: =('D1_Balance Sheet'!G13/'D1_Balance Sheet'!$G$19) -> 0.13875201
A15: Net Investment in Operating Leases | B15: =('D1_Balance Sheet'!B14/'D1_Balance Sheet'!$B$19) -> 0.098699682 | C15: =('D1_Balance Sheet'!C14/'D1_Balance Sheet'!$C$19) -> 0.080460455 | D15: =('D1_Balance Sheet'!D14/'D1_Balance Sheet'!$D$19) -> 0.078240825 | E15: =('D1_Balance Sheet'!E14/'D1_Balance Sheet'!$E$19) -> 0.08899345 | F15: =('D1_Balance Sheet'!F14/'D1_Balance Sheet'!$F$19) -> 0.10255802 | G15: =('D1_Balance Sheet'!G14/'D1_Balance Sheet'!$G$19) -> 0.10458316
A16: Equity in Net Assets of Affiliated Companies | B16: =('D1_Balance Sheet'!B15/'D1_Balance Sheet'!$B$19) -> 0.0095206806 | C16: =('D1_Balance Sheet'!C15/'D1_Balance Sheet'!$C$19) -> 0.023916885 | D16: =('D1_Balance Sheet'!D15/'D1_Balance Sheet'!$D$19) -> 0.020299294 | E16: =('D1_Balance Sheet'!E15/'D1_Balance Sheet'!$E$19) -> 0.010934642 | F16: =('D1_Balance Sheet'!F15/'D1_Balance Sheet'!$F$19) -> 0.017682417 | G16: =('D1_Balance Sheet'!G15/'D1_Balance Sheet'!$G$19) -> 0.018337879
... A22: Company Excluding Ford Credit | B22: =('D1_Balance Sheet'!B21/'D1_Balance Sheet'!$B$19) -> 0.019193526 | C22: =('D1_Balance Sheet'!C21/'D1_Balance Sheet'!$C$19) -> 0.0061571691 | D22: =('D1_Balance Sheet'!D21/'D1_Balance Sheet'!$D$19) -> 0.0017452709 | E22: =('D1_Balance Sheet'!E21/'D1_Balance Sheet'!$E$19) -> 0.0028528552 | F22: =('D1_Balance Sheet'!F21/'D1_Balance Sheet'!$F$19) -> 0.012352403 | G22: =('D1_Balance Sheet'!G21/'D1_Balance Sheet'!$G$19) -> 0.0051410419
A23: Ford Credit | B23: =('D1_Balance Sheet'!B22/'D1_Balance Sheet'!$B$19) -> 0 | C23: =('D1_Balance Sheet'!C22/'D1_Balance Sheet'!$C$19) -> 0 | D23: =('D1_Balance Sheet'!D23/'D1_Balance Sheet'!$D$19) -> 0.1799861 | E23: =('D1_Balance Sheet'!E22/'D1_Balance Sheet'!$E$19) -> 0 | F23: =('D1_Balance Sheet'!F22/'D1_Balance Sheet'!$F$19) -> 0 | G23: =('D1_Balance Sheet'!G22/'D1_Balance Sheet'!$G$19) -> 0
A24: Ford Credit Debt Payable within One Year | B24: =('D1_Balance Sheet'!B23/'D1_Balance Sheet'!$B$19) -> 0.17897358 | C24: =('D1_Balance Sheet'!C23/'D1_Balance Sheet'!$C$19) -> 0.18651384 | D24: =('D1_Balance Sheet'!D23/'D1_Balance Sheet'!$C$19) -> 0.17248489 | E24: =('D1_Balance Sheet'!E23/'D1_Balance Sheet'!$E$19) -> 0.1931891 | F24: =('D1_Balance Sheet'!F23/'D1_Balance Sheet'!$F$19) -> 0.18097535 | G24: =('D1_Balance Sheet'!G23/'D1_Balance Sheet'!$G$19) -> 0.18696705
A25: Payables | B25: =('D1_Balance Sheet'!B24/'D1_Balance Sheet'!$B$19) -> 0.089255084 | C25: =('D1_Balance Sheet'!C24/'D1_Balance Sheet'!$C$19) -> 0.084601467 | D25: =('D1_Balance Sheet'!D24/'D1_Balance Sheet'!$D$19) -> 0.095100801 | E25: =('D1_Balance Sheet'!E24/'D1_Balance Sheet'!$E$19) -> 0.10006487 | F25: =('D1_Balance Sheet'!F24/'D1_Balance Sheet'!$F$19) -> 0.086949248 | G25: =('D1_Balance Sheet'!G24/'D1_Balance Sheet'!$G$19) -> 0.083079836
A26: Other Liabilities and Deferred Revenue | B26: =('D1_Balance Sheet'!B25/'D1_Balance Sheet'!$B$19) -> 0.10990109 | C26: =('D1_Balance Sheet'!C25/'D1_Balance Sheet'!$C$19) -> 0.097413708 | D26: =('D1_Balance Sheet'!D25/'D1_Balance Sheet'!$D$19) -> 0.094654422 | E26: =('D1_Balance Sheet'!E25/'D1_Balance Sheet'!$E$19) -> 0.082447515 | F26: =('D1_Balance Sheet'!F25/'D1_Balance Sheet'!$F$19) -> 0.072698271 | G26: =('D1_Balance Sheet'!G25/'D1_Balance Sheet'!$G$19) -> 0.088471569
A27: Total Current Liabilities | B27: =('D1_Balance Sheet'!B26/'D1_Balance Sheet'!$B$19) -> 0.39732328 | C27: =('D1_Balance Sheet'!C26/'D1_Balance Sheet'!$C$19) -> 0.37468618 | D27: =('D1_Balance Sheet'!D26/'D1_Balance Sheet'!$D$19) -> 0.37148659 | E27: =('D1_Balance Sheet'!E26/'D1_Balance Sheet'!$E$19) -> 0.37855434 | F27: =('D1_Balance Sheet'!F26/'D1_Balance Sheet'!$F$19) -> 0.35297528 | G27: =('D1_Balance Sheet'!G26/'D1_Balance Sheet'!$G$19) -> 0.36365949
A28: Noncurrent Liabilities | B28: =('D1_Balance Sheet'!B27/'D1_Balance Sheet'!$B$19) -> 0 | C28: =('D1_Balance Sheet'!C27/'D1_Balance Sheet'!$C$19) -> 0 | D28: =('D1_Balance Sheet'!D27/'D1_Balance Sheet'!$D$19) -> 0 | E28: =('D1_Balance Sheet'!E27/'D1_Balance Sheet'!$E$19) -> 0 | F28: =('D1_Balance Sheet'!F27/'D1_Balance Sheet'!$F$19) -> 0 | G28: =('D1_Balance Sheet'!G27/'D1_Balance Sheet'!$G$19) -> 0
A29: Company Excluding Ford Credit | B29: =('D1_Balance Sheet'!B28/'D1_Balance Sheet'!$B$19) -> 0.056608798 | C29: =('D1_Balance Sheet'!C28/'D1_Balance Sheet'!$C$19) -> 0.066263201 | D29: =('D1_Balance Sheet'!D28/'D1_Balance Sheet'!$D$19) -> 0.071226812 | E29: =('D1_Balance Sheet'!E28/'D1_Balance Sheet'!$E$19) -> 0.075034 | F29: =('D1_Balance Sheet'!F28/'D1_Balance Sheet'!$F$19) -> 0.066916957 | G29: =('D1_Balance Sheet'!G28/'D1_Balance Sheet'!$G$19) -> 0.084685008
A30: Deferred Income Taxes | B30: =('D1_Balance Sheet'!B29/'D1_Balance Sheet'!$B$19) -> 0.0046825287 | C30: =('D1_Balance Sheet'!C29/'D1_Balance Sheet'!$C$19) -> 0.0037658312 | D30: =('D1_Balance Sheet'!D29/'D1_Balance Sheet'!$D$19) -> 0.0036771432 | E30: =('D1_Balance Sheet'!E29/'D1_Balance Sheet'!$E$19) -> 0.0060535243 | F30: =('D1_Balance Sheet'!F29/'D1_Balance Sheet'!$F$19) -> 0.0061509133 | G30: =('D1_Balance Sheet'!G29/'D1_Balance Sheet'!$G$19) -> 0.0020130135
A31: Minority Interest | B31: =('D1_Balance Sheet'!B30/'D1_Balance Sheet'!$B$19) -> 9.6832204e-05 | C31: =('D1_Balance Sheet'!C30/'D1_Balance Sheet'!$C$19) -> 8.0646292e-05 | D31: =('D1_Balance Sheet'!D30/'D1_Balance Sheet'!$D$19) -> 9.1471223e-05 | E31: =('D1_Balance Sheet'!E30/'D1_Balance Sheet'!$E$19) -> -0.00029310156 | F31: =('D1_Balance Sheet'!F30/'D1_Balance Sheet'!$F$19) -> 0.00040072364 | G31: =('D1_Balance Sheet'!G30/'D1_Balance Sheet'!$G$19) -> 0.00045274095
A32: Ford Credit | B32: =('D1_Balance Sheet'!B31/'D1_Balance Sheet'!$B$19) -> 0 | C32: =('D1_Balance Sheet'!C31/'D1_Balance Sheet'!$C$19) -> 0 | D32: =('D1_Balance Sheet'!D32/'D1_Balance Sheet'!$D$19) -> 0.2930555 | E32: =('D1_Balance Sheet'!E31/'D1_Balance Sheet'!$E$19) -> 0 | F32: =('D1_Balance Sheet'!F31/'D1_Balance Sheet'!$F$19) -> 0 | G32: =('D1_Balance Sheet'!G31/'D1_Balance Sheet'!$G$19) -> 0
A33: Ford Credit Long- Term Debt | B33: =('D1_Balance Sheet'!B32/'D1_Balance Sheet'!$B$19) -> 0.31008784 | C33: =('D1_Balance Sheet'!C32/'D1_Balance Sheet'!$C$19) -> 0.29690108 | D33: =('D1_Balance Sheet'!D32/'D1_Balance Sheet'!$C$19) -> 0.28084195 | E33: =('D1_Balance Sheet'!E32/'D1_Balance Sheet'!$E$19) -> 0.27201779 | F33: =('D1_Balance Sheet'!F32/'D1_Balance Sheet'!$F$19) -> 0.27700508 | G33: =('D1_Balance Sheet'!G32/'D1_Balance Sheet'!$G$19) -> 0.32817358
A34: Other Liabilities and Deferred Revenue | B34: =('D1_Balance Sheet'!B33/'D1_Balance Sheet'!$B$19) -> 0.10686817 | C34: =('D1_Balance Sheet'!C33/'D1_Balance Sheet'!$C$19) -> 0.10109539 | D34: =('D1_Balance Sheet'!D33/'D1_Balance Sheet'!$D$19) -> 0.10396253 | E34: =('D1_Balance Sheet'!E33/'D1_Balance Sheet'!$E$19) -> 0.099642807 | F34: =('D1_Balance Sheet'!F33/'D1_Balance Sheet'!$F$19) -> 0.10778688 | G34: =('D1_Balance Sheet'!G33/'D1_Balance Sheet'!$G$19) -> 0.10618459
A35: Shareholders' Equity | B35: =('D1_Balance Sheet'!B34/'D1_Balance Sheet'!$B$19) -> 0 | C35: =('D1_Balance Sheet'!C34/'D1_Balance Sheet'!$C$19) -> 0 | D35: =('D1_Balance Sheet'!D34/'D1_Balance Sheet'!$D$19) -> 0 | E35: =('D1_Balance Sheet'!E34/'D1_Balance Sheet'!$E$19) -> 0 | F35: =('D1_Balance Sheet'!F34/'D1_Balance Sheet'!$F$19) -> 0 | G35: =('D1_Balance Sheet'!G34/'D1_Balance Sheet'!$G$19) -> 0
A36: Common Stock - Par Value | B36: =('D1_Balance Sheet'!B35/'D1_Balance Sheet'!$B$19) -> 3.458293e-06 | C36: =('D1_Balance Sheet'!C35/'D1_Balance Sheet'!$C$19) -> 3.5063605e-06 | D36: =('D1_Balance Sheet'!D35/'D1_Balance Sheet'!$D$19) -> 3.6588489e-06 | E36: =('D1_Balance Sheet'!E35/'D1_Balance Sheet'!$E$19) -> 3.9080208e-06 | F36: =('D1_Balance Sheet'!F35/'D1_Balance Sheet'!$F$19) -> 3.8905207e-06 | G36: =('D1_Balance Sheet'!G35/'D1_Balance Sheet'!$G$19) -> 3.7416608e-06
A37: Common Stock - Par Value | B37: =('D1_Balance Sheet'!B36/'D1_Balance Sheet'!$B$19) -> 0.00014179001 | C37: =('D1_Balance Sheet'!C36/'D1_Balance Sheet'!$C$19) -> 0.00014376078 | D37: =('D1_Balance Sheet'!D36/'D1_Balance Sheet'!$D$19) -> 0.00015001281 | E37: =('D1_Balance Sheet'!E36/'D1_Balance Sheet'!$E$19) -> 0.00016022885 | F37: =('D1_Balance Sheet'!F36/'D1_Balance Sheet'!$F$19) -> 0.00015562083 | G37: =('D1_Balance Sheet'!G36/'D1_Balance Sheet'!$G$19) -> 0.00014966643
A38: Additional Paid in Capital | B38: =('D1_Balance Sheet'!B37/'D1_Balance Sheet'!$B$19) -> 0.082729285 | C38: =('D1_Balance Sheet'!C37/'D1_Balance Sheet'!$C$19) -> 0.082406485 | D38: =('D1_Balance Sheet'!D37/'D1_Balance Sheet'!$D$19) -> 0.084621858 | E38: =('D1_Balance Sheet'!E37/'D1_Balance Sheet'!$E$19) -> 0.089227931 | F38: =('D1_Balance Sheet'!F37/'D1_Balance Sheet'!$F$19) -> 0.087968565 | G38: =('D1_Balance Sheet'!G37/'D1_Balance Sheet'!$G$19) -> 0.083401619
A39: Treasury Stock - Common | B39: =('D1_Balance Sheet'!B38/'D1_Balance Sheet'!$B$19) -> -0.0097178033 | C39: =('D1_Balance Sheet'!C38/'D1_Balance Sheet'!$C$19) -> -0.0098528731 | D39: =('D1_Balance Sheet'!D38/'D1_Balance Sheet'!$D$19) -> -0.0087226958 | E39: =('D1_Balance Sheet'!E38/'D1_Balance Sheet'!$E$19) -> -0.0079997186 | F39: =('D1_Balance Sheet'!F38/'D1_Balance Sheet'!$F$19) -> -0.0060808839 | G39: =('D1_Balance Sheet'!G38/'D1_Balance Sheet'!$G$19) -> -0.0059492406
A40: Retained Earnings | B40: =('D1_Balance Sheet'!B39/'D1_Balance Sheet'!$B$19) -> 0 | C40: =('D1_Balance Sheet'!C39/'D1_Balance Sheet'!$C$19) -> 0 | D40: =('D1_Balance Sheet'!D40/'D1_Balance Sheet'!$D$19) -> 0.11353042 | E40: =('D1_Balance Sheet'!E39/'D1_Balance Sheet'!$E$19) -> 0 | F40: =('D1_Balance Sheet'!F39/'D1_Balance Sheet'!$F$19) -> 0 | G40: =('D1_Balance Sheet'!G39/'D1_Balance Sheet'!$G$19) -> 0
A41: Retained Earnings (Accumulated Deficit) | B41: =('D1_Balance Sheet'!B40/'D1_Balance Sheet'!$B$19) -> 0.077839259 | C41: =('D1_Balance Sheet'!C40/'D1_Balance Sheet'!$C$19) -> 0.1183046 | D41: =('D1_Balance Sheet'!D40/'D1_Balance Sheet'!$C$19) -> 0.10879886 | E41: =('D1_Balance Sheet'!E40/'D1_Balance Sheet'!$E$19) -> 0.12409529 | F41: =('D1_Balance Sheet'!F40/'D1_Balance Sheet'!$F$19) -> 0.13916004 | G41: =('D1_Balance Sheet'!G40/'D1_Balance Sheet'!$G$19) -> 0.068259117
A42: Accumulated Other Comprehensive Income (Loss) | B42: =('D1_Balance Sheet'!B41/'D1_Balance Sheet'!$B$19) -> -0.026663439 | C42: =('D1_Balance Sheet'!C41/'D1_Balance Sheet'!$C$19) -> -0.033797809 | D42: =('D1_Balance Sheet'!D41/'D1_Balance Sheet'!$D$19) -> -0.033083312 | E42: =('D1_Balance Sheet'!E41/'D1_Balance Sheet'!$E$19) -> -0.036497006 | F42: =('D1_Balance Sheet'!F41/'D1_Balance Sheet'!$F$19) -> -0.032443053 | G42: =('D1_Balance Sheet'!G41/'D1_Balance Sheet'!$G$19) -> -0.031033334
A43: Total Shareholders Equity | B43: =('D1_Balance Sheet'!B42/'D1_Balance Sheet'!$B$19) -> 0.12433255 | C43: =('D1_Balance Sheet'!C42/'D1_Balance Sheet'!$C$19) -> 0.15720767 | D43: =('D1_Balance Sheet'!D42/'D1_Balance Sheet'!$D$19) -> 0.15649995 | E43: =('D1_Balance Sheet'!E42/'D1_Balance Sheet'!$E$19) -> 0.16899064 | F43: =('D1_Balance Sheet'!F42/'D1_Balance Sheet'!$F$19) -> 0.18876418 | G43: =('D1_Balance Sheet'!G42/'D1_Balance Sheet'!$G$19) -> 0.11483157
A44: Total Liabilities & Shareholders Equity | B44: =('D1_Balance Sheet'!B43/'D1_Balance Sheet'!$B$19) -> 1 | C44: =('D1_Balance Sheet'!C43/'D1_Balance Sheet'!$C$19) -> 1 | D44: =('D1_Balance Sheet'!D43/'D1_Balance Sheet'!$D$19) -> 1 | E44: =('D1_Balance Sheet'!E43/'D1_Balance Sheet'!$E$19) -> 1 | F44: =('D1_Balance Sheet'!F43/'D1_Balance Sheet'!$F$19) -> 1 | G44: =('D1_Balance Sheet'!G43/'D1_Balance Sheet'!$G$19) -> 1
A46: Long Term Liabilities | B46: =1-B27-B43 -> 0.47834417 | C46: =1-C27-C43 -> 0.46810614 | D46: =1-D27-D43 -> 0.47201346 | E46: =1-E27-E43 -> 0.45245502 | F46: =1-F27-F43 -> 0.45826055 | G46: =1-G27-G43 -> 0.52150894

Sheet D2_Fig_BSCommonGraph

Sheet D2_Liquidity-NWCandNOWC
B1: Year(t=0) | C1: Year(t=-1) | D1: Year(t=-2) | E1: Year(t=-3) | F1: Year(t=-4) | G1: Year(t=-5)
B2: 2025 | C2: 2024 | D2: 2023 | E2: 2022 | F2: 2021 | G2: 2020
A3: Net Working Capital = CA-CL | B3: ='D1_Balance Sheet'!B11-'D1_Balance Sheet'!B26 -> 8597 | C3: ='D1_Balance Sheet'!C11-'D1_Balance Sheet'!C26 -> 17615 | D3: ='D1_Balance Sheet'!D11-'D1_Balance Sheet'!D26 -> 19950 | E3: ='D1_Balance Sheet'!E11-'D1_Balance Sheet'!E26 -> 19610 | F3: ='D1_Balance Sheet'!F11-'D1_Balance Sheet'!F26 -> 18269 | G3: ='D1_Balance Sheet'!G11-'D1_Balance Sheet'!G26 -> 19552
A5: (Notes payable(NP)) | B5: ='D1_Balance Sheet'!B21+'D1_Balance Sheet'!B22+'D1_Balance Sheet'!B23 -> 57302 | C5: ='D1_Balance Sheet'!C21+'D1_Balance Sheet'!C22+'D1_Balance Sheet'!C23 -> 54949 | D5: ='D1_Balance Sheet'!D21+'D1_Balance Sheet'!D22+'D1_Balance Sheet'!D23 -> 49669 | E5: ='D1_Balance Sheet'!E21+'D1_Balance Sheet'!E22+'D1_Balance Sheet'!E23 -> 50164 | F5: ='D1_Balance Sheet'!F21+'D1_Balance Sheet'!F22+'D1_Balance Sheet'!F23 -> 49692 | G5: ='D1_Balance Sheet'!G21+'D1_Balance Sheet'!G22+'D1_Balance Sheet'!G23 -> 51343
A7: Net Operating Working Capital = CA-(CL-NP) | B7: ='D1_Balance Sheet'!B11-('D1_Balance Sheet'!B26-B5) -> 65899 | C7: ='D1_Balance Sheet'!C11-('D1_Balance Sheet'!C26-C5) -> 72564 | D7: ='D1_Balance Sheet'!D11-('D1_Balance Sheet'!D26-D5) -> 69619 | E7: ='D1_Balance Sheet'!E11-('D1_Balance Sheet'!E26-E5) -> 69774 | F7: ='D1_Balance Sheet'!F11-('D1_Balance Sheet'!F26-F5) -> 67961 | G7: ='D1_Balance Sheet'!G11-('D1_Balance Sheet'!G26-G5) -> 70895
A9: Change in Working Capital (current year - previous year) | B9: =B7-C7 -> -6665 | C9: =C7-D7 -> 2945 | D9: =D7-E7 -> -155 | E9: =E7-F7 -> 1813 | F9: =F7-G7 -> -2934
A11: Free Cash Flow = (EBIT(1-T)+Dep)-(Capex + Change in NOWC) | B11: =(D1_IncomeStatment!B28*(1-0.21)+D1_StatmentofCFs!B5)-('D2_Liquidity-NWCandNOWC'!B13+'D2_Liquidity-NWCandNOWC'!B9) -> 4061.49 | C11: =(D1_IncomeStatment!C28*(1-0.21)+D1_StatmentofCFs!C5)-('D2_Liquidity-NWCandNOWC'!C13+'D2_Liquidity-NWCandNOWC'!C9) -> 71.01 | D11: =(D1_IncomeStatment!D28*(1-0.21)+D1_StatmentofCFs!D5)-('D2_Liquidity-NWCandNOWC'!D13+'D2_Liquidity-NWCandNOWC'!D9) -> 910.82 | E11: =(D1_IncomeStatment!E28*(1-0.21)+D1_StatmentofCFs!E5)-('D2_Liquidity-NWCandNOWC'!E13+'D2_Liquidity-NWCandNOWC'!E9) -> 3019.04 | F11: =(D1_IncomeStatment!F28*(1-0.21)+D1_StatmentofCFs!F5)-('D2_Liquidity-NWCandNOWC'!F13+'D2_Liquidity-NWCandNOWC'!F9) -> 6451.17
A13: Capex = NFA1- NFA0 +DEP | B13: ='D1_Balance Sheet'!B13-'D1_Balance Sheet'!C13+D1_StatmentofCFs!B5 -> 3194 | C13: ='D1_Balance Sheet'!C13-'D1_Balance Sheet'!D13+D1_StatmentofCFs!C5 -> 8674 | D13: ='D1_Balance Sheet'!D13-'D1_Balance Sheet'!E13+D1_StatmentofCFs!D5 -> 11246 | E13: ='D1_Balance Sheet'!E13-'D1_Balance Sheet'!F13+D1_StatmentofCFs!E5 -> 7768 | F13: ='D1_Balance Sheet'!F13-'D1_Balance Sheet'!G13+D1_StatmentofCFs!F5 -> 7374
B20: Year(t=0) | C20: Year(t=-1) | D20: Year(t=-2) | E20: Year(t=-3) | F20: Year(t=-4) | G20: Year(t=-5)
B21: 2025 | C21: 2024 | D21: 2023 | E21: 2022 | F21: 2021 | G21: 2020
A22: Net Working Capital = CA-CL | B22: =('D1_Balance Sheet'!B11-'D1_Balance Sheet'!B8)-('D1_Balance Sheet'!B26-'D1_Balance Sheet'!B23) -> 11219 | C22: =('D1_Balance Sheet'!C11-'D1_Balance Sheet'!C8)-('D1_Balance Sheet'!C26-'D1_Balance Sheet'!C23) -> 18958 | D22: =('D1_Balance Sheet'!D11-'D1_Balance Sheet'!D8)-('D1_Balance Sheet'!D26-'D1_Balance Sheet'!D23) -> 22717 | E22: =('D1_Balance Sheet'!E11-'D1_Balance Sheet'!E8)-('D1_Balance Sheet'!E26-'D1_Balance Sheet'!E23) -> 30324 | F22: =('D1_Balance Sheet'!F11-'D1_Balance Sheet'!F8)-('D1_Balance Sheet'!F26-'D1_Balance Sheet'!F23) -> 32243 | G22: =('D1_Balance Sheet'!G11-'D1_Balance Sheet'!G8)-('D1_Balance Sheet'!G26-'D1_Balance Sheet'!G23) -> 27120
A23: (Total current assests- Minus Ford Credit) - (Total current liabilities Minus Ford Credit Debt)
A26: Net Operating Working Capital = CA-(CL-NP) | B26: =('D1_Balance Sheet'!B11-'D1_Balance Sheet'!B8)-(('D1_Balance Sheet'!B26-'D1_Balance Sheet'!B23)-'D1_Balance Sheet'!B21) -> 16769 | C26: =('D1_Balance Sheet'!C11-'D1_Balance Sheet'!C8)-(('D1_Balance Sheet'!C26-'D1_Balance Sheet'!C23)-'D1_Balance Sheet'!C21) -> 20714 | D26: =('D1_Balance Sheet'!D11-'D1_Balance Sheet'!D8)-(('D1_Balance Sheet'!D26-'D1_Balance Sheet'!D23)-'D1_Balance Sheet'!D21) -> 23194 | E26: =('D1_Balance Sheet'!E11-'D1_Balance Sheet'!E8)-(('D1_Balance Sheet'!E26-'D1_Balance Sheet'!E23)-'D1_Balance Sheet'!E21) -> 31054 | F26: =('D1_Balance Sheet'!F11-'D1_Balance Sheet'!F8)-(('D1_Balance Sheet'!F26-'D1_Balance Sheet'!F23)-'D1_Balance Sheet'!F21) -> 35418 | G26: =('D1_Balance Sheet'!G11-'D1_Balance Sheet'!G8)-(('D1_Balance Sheet'!G26-'D1_Balance Sheet'!G23)-'D1_Balance Sheet'!G21) -> 28494
A28: Change in Working Capital (current year - previous year) | B28: =B26-C26 -> -3945 | C28: =C26-D26 -> -2480 | D28: =D26-E26 -> -7860 | E28: =E26-F26 -> -4364 | F28: =F26-G26 -> 6924 | G28: =G26-H26 -> 28494
A30: Free Cash Flow = (EBIT(1-T)+Dep)-(Capex + Change in NOWC) | B30: =(D1_IncomeStatment!B28*(1-0.21)+D1_StatmentofCFs!B5)-('D2_Liquidity-NWCandNOWC'!B32+'D2_Liquidity-NWCandNOWC'!B28) -> 1341.49 | C30: =(D1_IncomeStatment!C28*(1-0.21)+D1_StatmentofCFs!C5)-('D2_Liquidity-NWCandNOWC'!C32+'D2_Liquidity-NWCandNOWC'!C28) -> 5496.01 | D30: =(D1_IncomeStatment!D28*(1-0.21)+D1_StatmentofCFs!D5)-('D2_Liquidity-NWCandNOWC'!D32+'D2_Liquidity-NWCandNOWC'!D28) -> 8615.82 | E30: =(D1_IncomeStatment!E28*(1-0.21)+D1_StatmentofCFs!E5)-('D2_Liquidity-NWCandNOWC'!E32+'D2_Liquidity-NWCandNOWC'!E28) -> 9196.04 | F30: =(D1_IncomeStatment!F28*(1-0.21)+D1_StatmentofCFs!F5)-('D2_Liquidity-NWCandNOWC'!F32+'D2_Liquidity-NWCandNOWC'!F28) -> -3406.83
A32: Capex = NFA1- NFA0 +DEP | B32: ='D1_Balance Sheet'!B13-'D1_Balance Sheet'!C13+D1_StatmentofCFs!B5 -> 3194 | C32: ='D1_Balance Sheet'!C13-'D1_Balance Sheet'!D13+D1_StatmentofCFs!C5 -> 8674 | D32: ='D1_Balance Sheet'!D13-'D1_Balance Sheet'!E13+D1_StatmentofCFs!D5 -> 11246 | E32: ='D1_Balance Sheet'!E13-'D1_Balance Sheet'!F13+D1_StatmentofCFs!E5 -> 7768 | F32: ='D1_Balance Sheet'!F13-'D1_Balance Sheet'!G13+D1_StatmentofCFs!F5 -> 7374

Sheet D3_BalSheetHorizontalAnalysis
A1: Line Items | B1: 2025 | C1: 2024 | D1: 2023 | E1: 2022 | F1: 2021 | G1: 2020 | M1: Year | N1: 2020 | O1: 2021 | P1: 2022 | Q1: 2023 | R1: 2024 | S1: 2025
M2: Cash and Cash Equivalents | N2: 25243 | O2: 20540 | P2: 25134 | Q2: 24862 | R2: 22935 | S2: 23356
A3: Current Assets | G3: - | M3: % change | N3: - | O3: =F4 -> -0.18630908 | P3: =E4 -> 0.22366115 | Q3: =D4 -> -0.010821994 | R3: =C4 -> -0.077507843 | S3: =B4 -> 0.018356224
A4: Cash and Cash Equivalents | B4: =('D1_Balance Sheet'!$B$4-'D1_Balance Sheet'!$C$4)/ABS('D1_Balance Sheet'!$C$4) -> 0.018356224 | C4: =('D1_Balance Sheet'!$C$4-'D1_Balance Sheet'!$D$4)/ABS('D1_Balance Sheet'!$D$4) -> -0.077507843 | D4: =('D1_Balance Sheet'!D4-'D1_Balance Sheet'!E4)/ABS('D1_Balance Sheet'!E4) -> -0.010821994 | E4: =('D1_Balance Sheet'!E4-'D1_Balance Sheet'!F4)/ABS('D1_Balance Sheet'!F4) -> 0.22366115 | F4: =('D1_Balance Sheet'!F4-'D1_Balance Sheet'!G4)/ABS('D1_Balance Sheet'!G4) -> -0.18630908 | G4: -
A5: Trade and Other Receivables | B5: =('D1_Balance Sheet'!B6-'D1_Balance Sheet'!C6)/ABS('D1_Balance Sheet'!C6) -> 0.045846635 | C5: =('D1_Balance Sheet'!C6-'D1_Balance Sheet'!D6)/ABS('D1_Balance Sheet'!D6) -> -0.056278444 | D5: =('D1_Balance Sheet'!D6-'D1_Balance Sheet'!E6)/ABS('D1_Balance Sheet'!E6) -> -0.0081378346 | E5: =('D1_Balance Sheet'!E6-'D1_Balance Sheet'!F6)/ABS('D1_Balance Sheet'!F6) -> 0.38337731 | F5: =('D1_Balance Sheet'!F6-'D1_Balance Sheet'!G6)/ABS('D1_Balance Sheet'!G6) -> 0.13779646 | G5: - | M5: Year | N5: 2020 | O5: 2021 | P5: 2022 | Q5: 2023 | R5: 2024 | S5: 2025
A6: Inventories | B6: =('D1_Balance Sheet'!B7-'D1_Balance Sheet'!C7)/ABS('D1_Balance Sheet'!C7) -> 0.022339643 | C6: =('D1_Balance Sheet'!C7-'D1_Balance Sheet'!D7)/ABS('D1_Balance Sheet'!D7) -> -0.044725577 | D6: =('D1_Balance Sheet'!D7-'D1_Balance Sheet'!E7)/ABS('D1_Balance Sheet'!E7) -> 0.1115767 | E6: =('D1_Balance Sheet'!E7-'D1_Balance Sheet'!F7)/ABS('D1_Balance Sheet'!F7) -> 0.16701202 | F6: =('D1_Balance Sheet'!F7-'D1_Balance Sheet'!G7)/ABS('D1_Balance Sheet'!G7) -> 0.11630274 | G6: - | M6: Total Equity | N6: 30690 | O6: 48519 | P6: 43242 | Q6: 42773 | R6: 44835 | S6: 35952
A7: Noncurrent Assets | G7: - | M7: % Change | N7: - | O7: =F18 -> 0.58093842 | P7: =E18 -> -0.10876152 | Q7: =D18 -> -0.010845937 | R7: =C18 -> 0.048207982 | S7: =B18 -> -0.19812646
A8: Property-net | B8: =('D1_Balance Sheet'!B13-'D1_Balance Sheet'!C13)/ABS('D1_Balance Sheet'!C13) -> -0.1106659 | C8: =('D1_Balance Sheet'!C13-'D1_Balance Sheet'!D13)/ABS('D1_Balance Sheet'!D13) -> 0.027118395 | D8: =('D1_Balance Sheet'!D13-'D1_Balance Sheet'!E13)/ABS('D1_Balance Sheet'!E13) -> 0.095424661 | E8: =('D1_Balance Sheet'!E13-'D1_Balance Sheet'!F13)/ABS('D1_Balance Sheet'!F13) -> 0.00339266 | F8: =('D1_Balance Sheet'!F13-'D1_Balance Sheet'!G13)/ABS('D1_Balance Sheet'!G13) -> 0.0015101259 | G8: -
A9: Total Assets | B9: =('D1_Balance Sheet'!B19-'D1_Balance Sheet'!C19)/ABS('D1_Balance Sheet'!C19) -> 0.013899213 | C9: =('D1_Balance Sheet'!C19-'D1_Balance Sheet'!D19)/ABS('D1_Balance Sheet'!D19) -> 0.043489078 | D9: =('D1_Balance Sheet'!D19-'D1_Balance Sheet'!E19)/ABS('D1_Balance Sheet'!E19) -> 0.068101171 | E9: =('D1_Balance Sheet'!E19-'D1_Balance Sheet'!F19)/ABS('D1_Balance Sheet'!F19) -> -0.0044779894 | F9: =('D1_Balance Sheet'!F19-'D1_Balance Sheet'!G19)/ABS('D1_Balance Sheet'!G19) -> -0.038262223 | G9: - | M9: Year | N9: 2020 | O9: 2021 | P9: 2022 | Q9: 2023 | R9: 2024 | S9: 2025
A10: Current Liabilities | G10: - | M10: Long-Term Debt | N10: 87708 | O10: 71200 | P10: 69605 | Q10: 80095 | R10: 84675 | S10: 89665
A11: Payables | B11: =('D1_Balance Sheet'!B24-'D1_Balance Sheet'!C24)/ABS('D1_Balance Sheet'!C24) -> 0.069670093 | C11: =('D1_Balance Sheet'!C24-'D1_Balance Sheet'!D24)/ABS('D1_Balance Sheet'!D24) -> -0.071714374 | D11: =('D1_Balance Sheet'!D24-'D1_Balance Sheet'!E24)/ABS('D1_Balance Sheet'!E24) -> 0.015114236 | E11: =('D1_Balance Sheet'!E24-'D1_Balance Sheet'!F24)/ABS('D1_Balance Sheet'!F24) -> 0.14568885 | F11: =('D1_Balance Sheet'!F24-'D1_Balance Sheet'!G24)/ABS('D1_Balance Sheet'!G24) -> 0.0065303549 | G11: - | M11: % Change | N11: - | O11: =F13 -> -0.18821544 | P11: =E13 -> -0.022401685 | Q11: =D13 -> 0.15070756 | R11: =C13 -> 0.057182096 | S11: =B13 -> 0.058931208
A12: Ford Credit Debt Payable within One Year | B12: =('D1_Balance Sheet'!B23-'D1_Balance Sheet'!C23)/ABS('D1_Balance Sheet'!C23) -> -0.027090031 | C12: =('D1_Balance Sheet'!C23-'D1_Balance Sheet'!D23)/ABS('D1_Balance Sheet'!D23) -> 0.081334363 | D12: =('D1_Balance Sheet'!D23-'D1_Balance Sheet'!E23)/ABS('D1_Balance Sheet'!E23) -> -0.0048954161 | E12: =('D1_Balance Sheet'!E23-'D1_Balance Sheet'!F23)/ABS('D1_Balance Sheet'!F23) -> 0.062708257 | F12: =('D1_Balance Sheet'!F23-'D1_Balance Sheet'!G23)/ABS('D1_Balance Sheet'!G23) -> -0.069082831 | G12: -
A13: Ford Credit Long- Term Debt | B13: =('D1_Balance Sheet'!B32-'D1_Balance Sheet'!C32)/ABS('D1_Balance Sheet'!C32) -> 0.058931208 | C13: =('D1_Balance Sheet'!C32-'D1_Balance Sheet'!D32)/ABS('D1_Balance Sheet'!D32) -> 0.057182096 | D13: =('D1_Balance Sheet'!D32-'D1_Balance Sheet'!E32)/ABS('D1_Balance Sheet'!E32) -> 0.15070756 | E13: =('D1_Balance Sheet'!E32-'D1_Balance Sheet'!F32)/ABS('D1_Balance Sheet'!F32) -> -0.022401685 | F13: =('D1_Balance Sheet'!F32-'D1_Balance Sheet'!G32)/ABS('D1_Balance Sheet'!G32) -> -0.18821544 | G13: - | M13: Year | N13: 2020 | O13: 2021 | P13: 2022 | Q13: 2023 | R13: 2024 | S13: 2025
A14: Total Liabilities | B14: =(('D1_Balance Sheet'!B43-'D1_Balance Sheet'!B42)-('D1_Balance Sheet'!C43-'D1_Balance Sheet'!C42))/ABS('D1_Balance Sheet'!C43-'D1_Balance Sheet'!C42) -> 0.053448771 | C14: =(('D1_Balance Sheet'!C43-'D1_Balance Sheet'!C42)-('D1_Balance Sheet'!D43-'D1_Balance Sheet'!D42))/ABS('D1_Balance Sheet'!D43-'D1_Balance Sheet'!D42) -> 0.04261355 | D14: =(('D1_Balance Sheet'!D43-'D1_Balance Sheet'!D42)-('D1_Balance Sheet'!E43-'D1_Balance Sheet'!E42))/ABS('D1_Balance Sheet'!E43-'D1_Balance Sheet'!E42) -> 0.084155529 | E14: =(('D1_Balance Sheet'!E43-'D1_Balance Sheet'!E42)-('D1_Balance Sheet'!F43-'D1_Balance Sheet'!F42))/ABS('D1_Balance Sheet'!F43-'D1_Balance Sheet'!F42) -> 0.01978745 | F14: =(('D1_Balance Sheet'!F43-'D1_Balance Sheet'!F42)-('D1_Balance Sheet'!G43-'D1_Balance Sheet'!G42))/ABS('D1_Balance Sheet'!G43-'D1_Balance Sheet'!G42) -> -0.11859019 | G14: - | M14: Trade and Other Receivables | N14: 9993 | O14: 11370 | P14: 15729 | Q14: 15601 | R14: 14723 | S14: 15398
A15: Shareholders' Equity | G15: - | M15: % Change | N15: - | O15: =F5 -> 0.13779646 | P15: =E5 -> 0.38337731 | Q15: =D5 -> -0.0081378346 | R15: =C5 -> -0.056278444 | S15: =B5 -> 0.045846635
A16: Common Stock - Par Value | B16: =('D1_Balance Sheet'!B36-'D1_Balance Sheet'!C36)/ABS('D1_Balance Sheet'!C36) -> 0 | C16: =('D1_Balance Sheet'!C36-'D1_Balance Sheet'!D36)/ABS('D1_Balance Sheet'!D36) -> 0 | D16: =('D1_Balance Sheet'!D36-'D1_Balance Sheet'!E36)/ABS('D1_Balance Sheet'!E36) -> 0 | E16: =('D1_Balance Sheet'!E36-'D1_Balance Sheet'!F36)/ABS('D1_Balance Sheet'!F36) -> 0.025 | F16: =('D1_Balance Sheet'!F36-'D1_Balance Sheet'!G36)/ABS('D1_Balance Sheet'!G36) -> 0 | G16: -
A17: Retained Earnings (Accumulated Deficit) | B17: =('D1_Balance Sheet'!B40-'D1_Balance Sheet'!C40)/ABS('D1_Balance Sheet'!C40) -> -0.33289864 | C17: =('D1_Balance Sheet'!C40-'D1_Balance Sheet'!D40)/ABS('D1_Balance Sheet'!D40) -> 0.08736988 | D17: =('D1_Balance Sheet'!D40-'D1_Balance Sheet'!E40)/ABS('D1_Balance Sheet'!E40) -> -0.022831769 | E17: =('D1_Balance Sheet'!E40-'D1_Balance Sheet'!F40)/ABS('D1_Balance Sheet'!F40) -> -0.11224804 | F17: =('D1_Balance Sheet'!F40-'D1_Balance Sheet'!G40)/ABS('D1_Balance Sheet'!G40) -> 0.96069725 | G17: - | M17: Year | N17: 2020 | O17: 2021 | P17: 2022 | Q17: 2023 | R17: 2024 | S17: 2025
A18: Total Equity | B18: =('D1_Balance Sheet'!B42-'D1_Balance Sheet'!C42)/ABS('D1_Balance Sheet'!C42) -> -0.19812646 | C18: =('D1_Balance Sheet'!C42-'D1_Balance Sheet'!D42)/ABS('D1_Balance Sheet'!D42) -> 0.048207982 | D18: =('D1_Balance Sheet'!D42-'D1_Balance Sheet'!E42)/ABS('D1_Balance Sheet'!E42) -> -0.010845937 | E18: =('D1_Balance Sheet'!E42-'D1_Balance Sheet'!F42)/ABS('D1_Balance Sheet'!F42) -> -0.10876152 | F18: =('D1_Balance Sheet'!F42-'D1_Balance Sheet'!G42)/ABS('D1_Balance Sheet'!G42) -> 0.58093842 | G18: - | M18: Trade and Other Receivables | N18: ='D1_Balance Sheet'!G6 -> 9993 | O18: ='D1_Balance Sheet'!F6 -> 11370 | P18: ='D1_Balance Sheet'!E6 -> 15729 | Q18: ='D1_Balance Sheet'!D6 -> 15601 | R18: ='D1_Balance Sheet'!C6 -> 14723 | S18: ='D1_Balance Sheet'!B6 -> 15398
A19: Additional Paid in Capital | B19: =('D1_Balance Sheet'!B37-'D1_Balance Sheet'!C37)/ABS('D1_Balance Sheet'!C37) -> 0.01787082 | C19: =('D1_Balance Sheet'!C37-'D1_Balance Sheet'!D37)/ABS('D1_Balance Sheet'!D37) -> 0.016170875 | D19: =('D1_Balance Sheet'!D37-'D1_Balance Sheet'!E37)/ABS('D1_Balance Sheet'!E37) -> 0.012964261 | E19: =('D1_Balance Sheet'!E37-'D1_Balance Sheet'!F37)/ABS('D1_Balance Sheet'!F37) -> 0.0097740038 | F19: =('D1_Balance Sheet'!F37-'D1_Balance Sheet'!G37)/ABS('D1_Balance Sheet'!G37) -> 0.014401077 | G19: - | M19: % Change AR | N19: 0 | O19: =F5 -> 0.13779646 | P19: =E5 -> 0.38337731 | Q19: =D5 -> -0.0081378346 | R19: =C5 -> -0.056278444 | S19: =B5 -> 0.045846635
A20: Accumulated Other Comprehensive Income (Loss) | B20: =('D1_Balance Sheet'!B41-'D1_Balance Sheet'!C41)/ABS('D1_Balance Sheet'!C41) -> 0.20012449 | C20: =('D1_Balance Sheet'!C41-'D1_Balance Sheet'!D41)/ABS('D1_Balance Sheet'!D41) -> -0.066025216 | D20: =('D1_Balance Sheet'!D41-'D1_Balance Sheet'!E41)/ABS('D1_Balance Sheet'!E41) -> 0.03180212 | E20: =('D1_Balance Sheet'!E41-'D1_Balance Sheet'!F41)/ABS('D1_Balance Sheet'!F41) -> -0.11991846 | F20: =('D1_Balance Sheet'!F41-'D1_Balance Sheet'!G41)/ABS('D1_Balance Sheet'!G41) -> -0.0054256089 | G20: - | M20: Revenue | N20: =D1_IncomeStatment!G9 -> 127144 | O20: =D1_IncomeStatment!F9 -> 136341 | P20: =D1_IncomeStatment!E9 -> 158057 | Q20: =D1_IncomeStatment!D9 -> 176191 | R20: =D1_IncomeStatment!C9 -> 184992 | S20: =D1_IncomeStatment!B9 -> 187267
M21: % Change Rev | N21: 0 | O21: =D3_ISHorizontalAnalysis!F3 -> 0.072335305 | P21: =D3_ISHorizontalAnalysis!E3 -> 0.15927711 | Q21: =D3_ISHorizontalAnalysis!D3 -> 0.11473076 | R21: =D3_ISHorizontalAnalysis!C3 -> 0.049951473 | S21: =D3_ISHorizontalAnalysis!B3 -> 0.012297829

Sheet D3_Analysis of Balance Sheet
A1: *Please use calculations as shown in the slides and/or textbook (please do not use the internet)
B2: Year(t=0) | C2: Year(t=-1) | D2: Year(t=-2) | E2: Year(t=-3) | F2: Year(t=-4) | G2: Year(t=-5)
A3: Liquidity Ratios
A4: Current Ratio | B4: ='D1_Balance Sheet'!B11/'D1_Balance Sheet'!B26 -> 1.0748281 | C4: ='D1_Balance Sheet'!C11/'D1_Balance Sheet'!C26 -> 1.1648434 | D4: ='D1_Balance Sheet'!D11/'D1_Balance Sheet'!D26 -> 1.1964917 | E4: ='D1_Balance Sheet'!E11/'D1_Balance Sheet'!E26 -> 1.2024446 | F4: ='D1_Balance Sheet'!F11/'D1_Balance Sheet'!F26 -> 1.2013623 | G4: ='D1_Balance Sheet'!G11/'D1_Balance Sheet'!G26 -> 1.2011688
A5: Quick Ratio | B5: =('D1_Balance Sheet'!B4+'D1_Balance Sheet'!B5+'D1_Balance Sheet'!B6)/'D1_Balance Sheet'!B26 -> 0.46901384 | C5: =('D1_Balance Sheet'!C4+'D1_Balance Sheet'!C5+'D1_Balance Sheet'!C6)/'D1_Balance Sheet'!C26 -> 0.49664511 | D5: =('D1_Balance Sheet'!D4+'D1_Balance Sheet'!D5+'D1_Balance Sheet'!D6)/'D1_Balance Sheet'!D26 -> 0.54931006 | E5: =('D1_Balance Sheet'!E4+'D1_Balance Sheet'!E5+'D1_Balance Sheet'!E6)/'D1_Balance Sheet'!E26 -> 0.61733735 | F5: =('D1_Balance Sheet'!F4+'D1_Balance Sheet'!F5+'D1_Balance Sheet'!F6)/'D1_Balance Sheet'!F26 -> 0.67193889 | G5: =('D1_Balance Sheet'!G4+'D1_Balance Sheet'!G5+'D1_Balance Sheet'!G6)/'D1_Balance Sheet'!G26 -> 0.61686147
A6: Cash Ratio | B6: =('D1_Balance Sheet'!B4+'D1_Balance Sheet'!B6)/'D1_Balance Sheet'!B26 -> 0.33731395 | C6: =('D1_Balance Sheet'!C4+'D1_Balance Sheet'!C6)/'D1_Balance Sheet'!C26 -> 0.35240831 | D6: =('D1_Balance Sheet'!D4+'D1_Balance Sheet'!D6)/'D1_Balance Sheet'!D26 -> 0.39852853 | E6: =('D1_Balance Sheet'!E4+'D1_Balance Sheet'!E6)/'D1_Balance Sheet'!E26 -> 0.4218508 | F6: =('D1_Balance Sheet'!F4+'D1_Balance Sheet'!F6)/'D1_Balance Sheet'!F26 -> 0.35171448 | G6: =('D1_Balance Sheet'!G4+'D1_Balance Sheet'!G6)/'D1_Balance Sheet'!G26 -> 0.36254013
B9: Year(t=0) | C9: Year(t=-1) | D9: Year(t=-2) | E9: Year(t=-3) | F9: Year(t=-4) | G9: Year(t=-5)
A10: Solvency Ratios
A11: Long-term Debt to Equity | B11: ='D1_Balance Sheet'!B32/'D1_Balance Sheet'!B42 -> 2.4940198 | C11: ='D1_Balance Sheet'!C32/'D1_Balance Sheet'!C42 -> 1.8885915 | D11: ='D1_Balance Sheet'!D32/'D1_Balance Sheet'!D42 -> 1.8725598 | E11: ='D1_Balance Sheet'!E32/'D1_Balance Sheet'!E42 -> 1.6096619 | F11: ='D1_Balance Sheet'!F32/'D1_Balance Sheet'!F42 -> 1.4674664 | G11: ='D1_Balance Sheet'!G32/'D1_Balance Sheet'!G42 -> 2.857869
A12: Debt to Equity | B12: ='D1_Balance Sheet'!B26/'D1_Balance Sheet'!B42 -> 3.1956498 | C12: ='D1_Balance Sheet'!C26/'D1_Balance Sheet'!C42 -> 2.3833835 | D12: ='D1_Balance Sheet'!D26/'D1_Balance Sheet'!D42 -> 2.3737171 | E12: ='D1_Balance Sheet'!E26/'D1_Balance Sheet'!E42 -> 2.2400907 | F12: ='D1_Balance Sheet'!F26/'D1_Balance Sheet'!F42 -> 1.8699272 | G12: ='D1_Balance Sheet'!G26/'D1_Balance Sheet'!G42 -> 3.1668948
A13: Debt to Assets | B13: ='D1_Balance Sheet'!B26/'D1_Balance Sheet'!B19 -> 0.39732328 | C13: ='D1_Balance Sheet'!C26/'D1_Balance Sheet'!C19 -> 0.37468618 | D13: ='D1_Balance Sheet'!D26/'D1_Balance Sheet'!D19 -> 0.37148659 | E13: ='D1_Balance Sheet'!E26/'D1_Balance Sheet'!E19 -> 0.37855434 | F13: ='D1_Balance Sheet'!F26/'D1_Balance Sheet'!F19 -> 0.35297528 | G13: ='D1_Balance Sheet'!G26/'D1_Balance Sheet'!G19 -> 0.36365949
A14: Debt to Capital | B14: =('D1_Balance Sheet'!B26+'D1_Balance Sheet'!B32+'D1_Balance Sheet'!B33)/('D1_Balance Sheet'!B26+'D1_Balance Sheet'!B32++'D1_Balance Sheet'!B33+'D1_Balance Sheet'!B42) -> 0.86753571 | C14: =('D1_Balance Sheet'!C26+'D1_Balance Sheet'!C32+'D1_Balance Sheet'!C33)/('D1_Balance Sheet'!C26+'D1_Balance Sheet'!C32++'D1_Balance Sheet'!C33+'D1_Balance Sheet'!C42) -> 0.83093955 | D14: =('D1_Balance Sheet'!D26+'D1_Balance Sheet'!D32+'D1_Balance Sheet'!D33)/('D1_Balance Sheet'!D26+'D1_Balance Sheet'!D32++'D1_Balance Sheet'!D33+'D1_Balance Sheet'!D42) -> 0.83081171 | E14: =('D1_Balance Sheet'!E26+'D1_Balance Sheet'!E32+'D1_Balance Sheet'!E33)/('D1_Balance Sheet'!E26+'D1_Balance Sheet'!E32++'D1_Balance Sheet'!E33+'D1_Balance Sheet'!E42) -> 0.81615578 | F14: =('D1_Balance Sheet'!F26+'D1_Balance Sheet'!F32+'D1_Balance Sheet'!F33)/('D1_Balance Sheet'!F26+'D1_Balance Sheet'!F32++'D1_Balance Sheet'!F33+'D1_Balance Sheet'!F42) -> 0.79626791 | G14: =('D1_Balance Sheet'!G26+'D1_Balance Sheet'!G32+'D1_Balance Sheet'!G33)/('D1_Balance Sheet'!G26+'D1_Balance Sheet'!G32++'D1_Balance Sheet'!G33+'D1_Balance Sheet'!G42) -> 0.87420533
A15: Financial Leverage | B15: ='D1_Balance Sheet'!B19/'D1_Balance Sheet'!B42 -> 8.0429462 | C15: ='D1_Balance Sheet'!C19/'D1_Balance Sheet'!C42 -> 6.3610126 | D15: ='D1_Balance Sheet'!D19/'D1_Balance Sheet'!D42 -> 6.3897786 | E15: ='D1_Balance Sheet'!E19/'D1_Balance Sheet'!E42 -> 5.9174876 | F15: ='D1_Balance Sheet'!F19/'D1_Balance Sheet'!F42 -> 5.2976154 | G15: ='D1_Balance Sheet'!G19/'D1_Balance Sheet'!G42 -> 8.7084066
B18: Year(t=0) | C18: Year(t=-1) | D18: Year(t=-2) | E18: Year(t=-3) | F18: Year(t=-4) | G18: Year(t=-5)
A19: Solvency Ratios
A20: Debt to Assets | B20: =B13 -> 0.39732328 | C20: =C13 -> 0.37468618 | D20: =D13 -> 0.37148659 | E20: =E13 -> 0.37855434 | F20: =F13 -> 0.35297528 | G20: =G13 -> 0.36365949
A21: Equity to Assets | B21: ='D1_Balance Sheet'!B42/'D1_Balance Sheet'!B19 -> 0.12433255 | C21: ='D1_Balance Sheet'!C42/'D1_Balance Sheet'!C19 -> 0.15720767 | D21: ='D1_Balance Sheet'!D42/'D1_Balance Sheet'!D19 -> 0.15649995 | E21: ='D1_Balance Sheet'!E42/'D1_Balance Sheet'!E19 -> 0.16899064 | F21: ='D1_Balance Sheet'!F42/'D1_Balance Sheet'!F19 -> 0.18876418 | G21: ='D1_Balance Sheet'!G42/'D1_Balance Sheet'!G19 -> 0.11483157
B24: Year(t=0) | C24: Year(t=-1) | D24: Year(t=-2) | E24: Year(t=-3) | F24: Year(t=-4) | G24: Year(t=-5)
A25: Other Ratios
A26: Current Assets to Total Assets | B26: ='D1_Balance Sheet'!B11/'D1_Balance Sheet'!B19 -> 0.42705423 | C26: ='D1_Balance Sheet'!C11/'D1_Balance Sheet'!C19 -> 0.43645072 | D26: ='D1_Balance Sheet'!D11/'D1_Balance Sheet'!D19 -> 0.44448063 | E26: ='D1_Balance Sheet'!E11/'D1_Balance Sheet'!E19 -> 0.45519063 | F26: ='D1_Balance Sheet'!F11/'D1_Balance Sheet'!F19 -> 0.4240512 | G26: ='D1_Balance Sheet'!G11/'D1_Balance Sheet'!G19 -> 0.43681645
A27: Non-current Assets to Total Assets | B27: =('D1_Balance Sheet'!B13+'D1_Balance Sheet'!B14+'D1_Balance Sheet'!B15+'D1_Balance Sheet'!B16+'D1_Balance Sheet'!B17+'D1_Balance Sheet'!B18)/'D1_Balance Sheet'!B19 -> 0.57294577 | C27: =('D1_Balance Sheet'!C13+'D1_Balance Sheet'!C14+'D1_Balance Sheet'!C15+'D1_Balance Sheet'!C16+'D1_Balance Sheet'!C17+'D1_Balance Sheet'!C18)/'D1_Balance Sheet'!C19 -> 0.56354928 | D27: =('D1_Balance Sheet'!D13+'D1_Balance Sheet'!D14+'D1_Balance Sheet'!D15+'D1_Balance Sheet'!D16+'D1_Balance Sheet'!D17+'D1_Balance Sheet'!D18)/'D1_Balance Sheet'!D19 -> 0.55551937 | E27: =('D1_Balance Sheet'!E13+'D1_Balance Sheet'!E14+'D1_Balance Sheet'!E15+'D1_Balance Sheet'!E16+'D1_Balance Sheet'!E17+'D1_Balance Sheet'!E18)/'D1_Balance Sheet'!E19 -> 0.54480937 | F27: =('D1_Balance Sheet'!F13+'D1_Balance Sheet'!F14+'D1_Balance Sheet'!F15+'D1_Balance Sheet'!F16+'D1_Balance Sheet'!F17+'D1_Balance Sheet'!F18)/'D1_Balance Sheet'!F19 -> 0.5759488 | G27: =('D1_Balance Sheet'!G13+'D1_Balance Sheet'!G14+'D1_Balance Sheet'!G15+'D1_Balance Sheet'!G16+'D1_Balance Sheet'!G17+'D1_Balance Sheet'!G18)/'D1_Balance Sheet'!G19 -> 0.56318355
A28: Current Liabilities to Total Liabilities | B28: ='D1_Balance Sheet'!B26/('D1_Balance Sheet'!B43-'D1_Balance Sheet'!B42) -> 0.45373764 | C28: ='D1_Balance Sheet'!C26/('D1_Balance Sheet'!C43-'D1_Balance Sheet'!C42) -> 0.44457712 | D28: ='D1_Balance Sheet'!D26/('D1_Balance Sheet'!D43-'D1_Balance Sheet'!D42) -> 0.44041087 | E28: ='D1_Balance Sheet'!E26/('D1_Balance Sheet'!E43-'D1_Balance Sheet'!E42) -> 0.4555356 | F28: ='D1_Balance Sheet'!F26/('D1_Balance Sheet'!F43-'D1_Balance Sheet'!F42) -> 0.4351081 | G28: ='D1_Balance Sheet'!G26/('D1_Balance Sheet'!G43-'D1_Balance Sheet'!G42) -> 0.41083649
A29: Non-current Liabilities to Total Liaibilities | B29: =('D1_Balance Sheet'!B28+'D1_Balance Sheet'!B29+'D1_Balance Sheet'!B30+'D1_Balance Sheet'!B32+'D1_Balance Sheet'!B33)/('D1_Balance Sheet'!B43-'D1_Balance Sheet'!B42) -> 0.54626236 | C29: =('D1_Balance Sheet'!C28+'D1_Balance Sheet'!C29+'D1_Balance Sheet'!C30+'D1_Balance Sheet'!C32+'D1_Balance Sheet'!C33)/('D1_Balance Sheet'!C43-'D1_Balance Sheet'!C42) -> 0.55542288 | D29: =('D1_Balance Sheet'!D28+'D1_Balance Sheet'!D29+'D1_Balance Sheet'!D30+'D1_Balance Sheet'!D32+'D1_Balance Sheet'!D33)/('D1_Balance Sheet'!D43-'D1_Balance Sheet'!D42) -> 0.55958913 | E29: =('D1_Balance Sheet'!E28+'D1_Balance Sheet'!E29+'D1_Balance Sheet'!E30+'D1_Balance Sheet'!E32+'D1_Balance Sheet'!E33)/('D1_Balance Sheet'!E43-'D1_Balance Sheet'!E42) -> 0.5444644 | F29: =('D1_Balance Sheet'!F28+'D1_Balance Sheet'!F29+'D1_Balance Sheet'!F30+'D1_Balance Sheet'!F32+'D1_Balance Sheet'!F33)/('D1_Balance Sheet'!F43-'D1_Balance Sheet'!F42) -> 0.5648919 | G29: =('D1_Balance Sheet'!G28+'D1_Balance Sheet'!G29+'D1_Balance Sheet'!G30+'D1_Balance Sheet'!G32+'D1_Balance Sheet'!G33)/('D1_Balance Sheet'!G43-'D1_Balance Sheet'!G42) -> 0.58916351
A30: Retained Earnings to Total Equity | B30: ='D1_Balance Sheet'!B40/'D1_Balance Sheet'!B42 -> 0.62605696 | C30: ='D1_Balance Sheet'!C40/'D1_Balance Sheet'!C42 -> 0.75253708 | D30: ='D1_Balance Sheet'!D40/'D1_Balance Sheet'!D42 -> 0.72543427 | E30: ='D1_Balance Sheet'!E40/'D1_Balance Sheet'!E42 -> 0.73433236 | F30: ='D1_Balance Sheet'!F40/'D1_Balance Sheet'!F42 -> 0.73721635 | G30: ='D1_Balance Sheet'!G40/'D1_Balance Sheet'!G42 -> 0.59442815
A31: AOCI to Total Equity | B31: ='D1_Balance Sheet'!B41/'D1_Balance Sheet'!B42 -> -0.2144526 | C31: ='D1_Balance Sheet'!C41/'D1_Balance Sheet'!C42 -> -0.21498829 | D31: ='D1_Balance Sheet'!D41/'D1_Balance Sheet'!D42 -> -0.21139504 | E31: ='D1_Balance Sheet'!E41/'D1_Balance Sheet'!E42 -> -0.21597058 | F31: ='D1_Balance Sheet'!F41/'D1_Balance Sheet'!F42 -> -0.17187081 | G31: ='D1_Balance Sheet'!G41/'D1_Balance Sheet'!G42 -> -0.2702509
A32: Paid-In Capital to Total Equity | B32: ='D1_Balance Sheet'!B37/'D1_Balance Sheet'!B42 -> 0.66538718 | C32: ='D1_Balance Sheet'!C37/'D1_Balance Sheet'!C42 -> 0.52418869 | D32: ='D1_Balance Sheet'!D37/'D1_Balance Sheet'!D42 -> 0.54071494 | E32: ='D1_Balance Sheet'!E37/'D1_Balance Sheet'!E42 -> 0.52800518 | F32: ='D1_Balance Sheet'!F37/'D1_Balance Sheet'!F42 -> 0.46602362 | G32: ='D1_Balance Sheet'!G37/'D1_Balance Sheet'!G42 -> 0.72629521

Sheet D1-4-Place Figures Here
A1: Insert any figures requested in the deliverable instructions here:

Sheet D1_IncomeStatment
A1: Line Items | B1: Year(t=0) | C1: Year(t=-1) | D1: Year(t=-2) | E1: Year(t=-3) | F1: Year(t=-4) | G1: Year(t=-5) | I1: MEAN | J1: STD | K1: MIN | L1: MEDIAN | M1: MAX
B2: 2025 | C2: 2024 | D2: 2023 | E2: 2022 | F2: 2021 | G2: 2020
A3: Revenues
A4: Product Revenues | F4: 126268 | I4: =AVERAGE(B4:G4) -> 126268 | J4: =STDEV(B4:G4) -> #DIV/0! | K4: =MIN(B4:G4) -> 126268 | L4: =MEDIAN(B4:G4) -> 126268 | M4: =MAX(B4:G4) -> 126268
A5: Company excluding Ford Credit | B5: 173996 | C5: 172706 | D5: 165901 | E5: 149079 | I5: =AVERAGE(B5:G5) -> 165420.5 | J5: =STDEV(B5:G5) -> 11458.522 | K5: =MIN(B5:G5) -> 149079 | L5: =MEDIAN(B5:G5) -> 169303.5 | M5: =MAX(B5:G5) -> 173996
A6: Automotive | G6: 115894 | I6: =AVERAGE(B6:G6) -> 115894 | J6: =STDEV(B6:G6) -> #DIV/0! | K6: =MIN(B6:G6) -> 115894 | L6: =MEDIAN(B6:G6) -> 115894 | M6: =MAX(B6:G6) -> 115894
A7: Mobility | G7: 47 | I7: =AVERAGE(B7:G7) -> 47 | J7: =STDEV(B7:G7) -> #DIV/0! | K7: =MIN(B7:G7) -> 47 | L7: =MEDIAN(B7:G7) -> 47 | M7: =MAX(B7:G7) -> 47
A8: Financial Services Revenues | B8: 13271 | C8: 12286 | D8: 10290 | E8: 8978 | F8: 10073 | G8: 11203 | I8: =AVERAGE(B8:G8) -> 11016.833 | J8: =STDEV(B8:G8) -> 1568.6082 | K8: =MIN(B8:G8) -> 8978 | L8: =MEDIAN(B8:G8) -> 10746.5 | M8: =MAX(B8:G8) -> 13271
A9: Total Revenues | B9: 187267 | C9: 184992 | D9: 176191 | E9: 158057 | F9: 136341 | G9: 127144 | I9: =AVERAGE(B9:G9) -> 161665.33 | J9: =STDEV(B9:G9) -> 25521.121 | K9: =MIN(B9:G9) -> 127144 | L9: =MEDIAN(B9:G9) -> 167124 | M9: =MAX(B9:G9) -> 187267
A10: Expenses
A11: Cost of Sales | B11: -150550 | C11: -158434 | D11: -150550 | E11: -134397 | F11: -114651 | G11: -112752 | I11: =AVERAGE(B11:G11) -> -136889 | J11: =STDEV(B11:G11) -> 19599.828 | K11: =MIN(B11:G11) -> -158434 | L11: =MEDIAN(B11:G11) -> -142473.5 | M11: =MAX(B11:G11) -> -112752
A12: Depreciation and Tooling Amortization | B12: -2460 | C12: -2529 | D12: -2589 | E12: -2281 | F12: -1666 | G12: -3269 | I12: =AVERAGE(B12:G12) -> -2465.6667 | J12: =STDEV(B12:G12) -> 517.33303 | K12: =MIN(B12:G12) -> -3269 | L12: =MEDIAN(B12:G12) -> -2494.5 | M12: =MAX(B12:G12) -> -1666
A13: Operating Expenses - Fin. Div. | E13: -881 | F13: -796 | G13: -1936 | I13: =AVERAGE(B13:G13) -> -1204.3333 | J13: =STDEV(B13:G13) -> 635.06561 | K13: =MIN(B13:G13) -> -1936 | L13: =MEDIAN(B13:G13) -> -881 | M13: =MAX(B13:G13) -> -796
A14: Ford Credit Interest, Operating, and Other Expenses | B14: -1634 | C14: -940 | D14: -581 | I14: =AVERAGE(B14:G14) -> -1051.6667 | J14: =STDEV(B14:G14) -> 535.3077 | K14: =MIN(B14:G14) -> -1634 | L14: =MEDIAN(B14:G14) -> -940 | M14: =MAX(B14:G14) -> -581
A15: Selling Administrative and Other Expenses | B15: -10849 | C15: -10287 | D15: -10702 | E15: -10888 | F15: -11915 | G15: -10193 | I15: =AVERAGE(B15:G15) -> -10805.667 | J15: =STDEV(B15:G15) -> 615.53218 | K15: =MIN(B15:G15) -> -11915 | L15: =MEDIAN(B15:G15) -> -10775.5 | M15: =MAX(B15:G15) -> -10193
A16: Interest Expense on Company Debt Excluding Ford Credit | B16: -1254 | C16: -1115 | D16: -1302 | E16: -1259 | F16: -1803 | G16: -1649 | I16: =AVERAGE(B16:G16) -> -1397 | J16: =STDEV(B16:G16) -> 266.9764 | K16: =MIN(B16:G16) -> -1803 | L16: =MEDIAN(B16:G16) -> -1280.5 | M16: =MAX(B16:G16) -> -1115
A17: Interest Expense | B17: -7133 | C17: -7583 | D17: -6311 | E17: -3334 | F17: -2790 | G17: -3402 | I17: =AVERAGE(B17:G17) -> -5092.1667 | J17: =STDEV(B17:G17) -> 2149.5391 | K17: =MIN(B17:G17) -> -7583 | L17: =MEDIAN(B17:G17) -> -4856.5 | M17: =MAX(B17:G17) -> -2790
A18: Equity in Net (Loss)/income of Affiliated Companies | B18: -3153 | C18: 678 | D18: 414 | E18: -2883 | F18: 327 | G18: 42 | I18: =AVERAGE(B18:G18) -> -762.5 | J18: =STDEV(B18:G18) -> 1760.9335 | K18: =MIN(B18:G18) -> -3153 | L18: =MEDIAN(B18:G18) -> 184.5 | M18: =MAX(B18:G18) -> 678
A19: Other Income (Loss), Net | B19: 1746 | C19: 2451 | D19: -603 | E19: -5150 | F19: 14733 | G19: 4899 | I19: =AVERAGE(B19:G19) -> 3012.6667 | J19: =STDEV(B19:G19) -> 6671.5299 | K19: =MIN(B19:G19) -> -5150 | L19: =MEDIAN(B19:G19) -> 2098.5 | M19: =MAX(B19:G19) -> 14733
A20: Income/(Loss) before Income Taxes-financial Services | F20: 4717 | G20: 2608 | I20: =AVERAGE(B20:G20) -> 3662.5 | J20: =STDEV(B20:G20) -> 1491.2882 | K20: =MIN(B20:G20) -> 2608 | L20: =MEDIAN(B20:G20) -> 3662.5 | M20: =MAX(B20:G20) -> 4717
A21: Income (Loss) before Income Taxes | E21: 2657 | I21: =AVERAGE(B21:G21) -> 2657 | J21: =STDEV(B21:G21) -> #DIV/0! | K21: =MIN(B21:G21) -> 2657 | L21: =MEDIAN(B21:G21) -> 2657 | M21: =MAX(B21:G21) -> 2657
A22: Earnings before Taxes | B22: -11830 | C22: 7233 | D22: 3967 | E22: -3016 | F22: 17780 | G22: -1116 | I22: =AVERAGE(B22:G22) -> 2169.6667 | J22: =STDEV(B22:G22) -> 10062.084 | K22: =MIN(B22:G22) -> -11830 | L22: =MEDIAN(B22:G22) -> 1425.5 | M22: =MAX(B22:G22) -> 17780
A23: Taxes and Other Expenses
A24: Provision for Income Tax | B24: 3668 | C24: -1339 | D24: 362 | E24: 864 | F24: 130 | G24: -160 | I24: =AVERAGE(B24:G24) -> 587.5 | J24: =STDEV(B24:G24) -> 1679.0621 | K24: =MIN(B24:G24) -> -1339 | L24: =MEDIAN(B24:G24) -> 246 | M24: =MAX(B24:G24) -> 3668
A25: Minority Interest (After Tax) | B25: -20 | C25: -15 | D25: 18 | E25: 171 | F25: 27 | G25: -3 | I25: =AVERAGE(B25:G25) -> 29.666667 | J25: =STDEV(B25:G25) -> 71.620295 | K25: =MIN(B25:G25) -> -20 | L25: =MEDIAN(B25:G25) -> 7.5 | M25: =MAX(B25:G25) -> 171
A26: Net Income (Loss) | B26: -8182 | C26: 5879 | D26: 4347 | E26: -1981 | F26: 17937 | G26: -1279 | I26: =AVERAGE(B26:G26) -> 2786.8333 | J26: =STDEV(B26:G26) -> 8956.5809 | K26: =MIN(B26:G26) -> -8182 | L26: =MEDIAN(B26:G26) -> 1534 | M26: =MAX(B26:G26) -> 17937
A27: Supplementary Info
A28: Operating Income (Loss) | B28: -9169 | C28: 5219 | D28: 5458 | E28: 6276 | F28: 4523 | G28: -4408 | I28: =AVERAGE(B28:G28) -> 1316.5 | J28: =STDEV(B28:G28) -> 6480.3614 | K28: =MIN(B28:G28) -> -9169 | L28: =MEDIAN(B28:G28) -> 4871 | M28: =MAX(B28:G28) -> 6276
A29: Basic EPS - Continuing Operations | B29: -2.06 | C29: 1.48 | D29: 1.09 | E29: -0.49 | F29: 4.49 | G29: -0.32 | I29: =AVERAGE(B29:G29) -> 0.69833333 | J29: =STDEV(B29:G29) -> 2.2449358 | K29: =MIN(B29:G29) -> -2.06 | L29: =MEDIAN(B29:G29) -> 0.385 | M29: =MAX(B29:G29) -> 4.49
A30: Diluted EPS - Continuing Operations | B30: -2.06 | C30: 1.46 | D30: 1.08 | E30: -0.49 | F30: 4.45 | G30: -0.32 | I30: =AVERAGE(B30:G30) -> 0.68666667 | J30: =STDEV(B30:G30) -> 2.2296876 | K30: =MIN(B30:G30) -> -2.06 | L30: =MEDIAN(B30:G30) -> 0.38 | M30: =MAX(B30:G30) -> 4.45
A31: Share Count | B31: =B26/B30 -> 3971.8447 | C31: =C26/C30 -> 4026.7123 | D31: =D26/D30 -> 4025 | E31: =E26/E30 -> 4042.8571 | F31: =F26/F30 -> 4030.7865 | G31: =G26/G30 -> 3996.875

Sheet D2_IncomeStatmentCommonSize
A1: Line Items | B1: Year(t=0) | C1: Year(t=-1) | D1: Year(t=-2) | E1: Year(t=-3) | F1: Year(t=-4) | G1: Year(t=-5)
B2: 2025 | C2: 2024 | D2: 2023 | E2: 2022 | F2: 2021 | G2: 2020
A3: Revenues | J3: % of revenue = (line item/total rev)
A4: Product Revenues | F4: =D1_IncomeStatment!F4/D1_IncomeStatment!$F$9 -> 0.92611907
A5: Company excluding Ford Credit | B5: =D1_IncomeStatment!B5/D1_IncomeStatment!$B$9 -> 0.92913327 | C5: =D1_IncomeStatment!C5/D1_IncomeStatment!$C$9 -> 0.93358632 | D5: =D1_IncomeStatment!D5/D1_IncomeStatment!$D$9 -> 0.94159747 | E5: =D1_IncomeStatment!E5/D1_IncomeStatment!$E$9 -> 0.94319771 | F5: =D1_IncomeStatment!F5/D1_IncomeStatment!$F$9 -> 0 | G5: =D1_IncomeStatment!G5/D1_IncomeStatment!$G$9 -> 0
A6: Automotive | G6: =D1_IncomeStatment!G6/D1_IncomeStatment!$G$9 -> 0.91151765
A7: Mobility | G7: =D1_IncomeStatment!G7/D1_IncomeStatment!$G$9 -> 0.0003696596
A8: Financial Services Revenues | B8: =D1_IncomeStatment!B8/D1_IncomeStatment!$B$9 -> 0.07086673 | C8: =D1_IncomeStatment!C8/D1_IncomeStatment!$C$9 -> 0.066413683 | D8: =D1_IncomeStatment!D8/D1_IncomeStatment!$D$9 -> 0.058402529 | E8: =D1_IncomeStatment!E8/D1_IncomeStatment!$E$9 -> 0.056802293 | F8: =D1_IncomeStatment!F8/D1_IncomeStatment!$F$9 -> 0.073880931 | G8: =D1_IncomeStatment!G8/D1_IncomeStatment!$G$9 -> 0.088112691
A9: Total Revenues | B9: =D1_IncomeStatment!B9/D1_IncomeStatment!$B$9 -> 1 | C9: =D1_IncomeStatment!C9/D1_IncomeStatment!$C$9 -> 1 | D9: =D1_IncomeStatment!D9/D1_IncomeStatment!$D$9 -> 1 | E9: =D1_IncomeStatment!E9/D1_IncomeStatment!$E$9 -> 1 | F9: =D1_IncomeStatment!F9/D1_IncomeStatment!$F$9 -> 1 | G9: =D1_IncomeStatment!G9/D1_IncomeStatment!$G$9 -> 1
A10: Expenses
A11: Cost of Sales | B11: =D1_IncomeStatment!B11/D1_IncomeStatment!$B$9 -> -0.80393235 | C11: =D1_IncomeStatment!C11/D1_IncomeStatment!$C$9 -> -0.85643704 | D11: =D1_IncomeStatment!D11/D1_IncomeStatment!$D$9 -> -0.85447043 | E11: =D1_IncomeStatment!E11/D1_IncomeStatment!$E$9 -> -0.85030717 | F11: =D1_IncomeStatment!F11/D1_IncomeStatment!$F$9 -> -0.84091359 | G11: =D1_IncomeStatment!G11/D1_IncomeStatment!$G$9 -> -0.88680551
A12: Depreciation and Tooling Amortization | B12: =D1_IncomeStatment!B12/D1_IncomeStatment!$B$9 -> -0.013136324 | C12: =D1_IncomeStatment!C12/D1_IncomeStatment!$C$9 -> -0.013670861 | D12: =D1_IncomeStatment!D12/D1_IncomeStatment!$D$9 -> -0.014694281 | E12: =D1_IncomeStatment!E12/D1_IncomeStatment!$E$9 -> -0.014431503 | F12: =D1_IncomeStatment!F12/D1_IncomeStatment!$F$9 -> -0.012219362 | G12: =D1_IncomeStatment!G12/D1_IncomeStatment!$G$9 -> -0.025711005
A13: Operating Expenses - Fin. Div. | E13: =D1_IncomeStatment!E13/D1_IncomeStatment!$E$9 -> -0.0055739385 | F13: =D1_IncomeStatment!F13/D1_IncomeStatment!$F$9 -> -0.0058383025 | G13: =D1_IncomeStatment!G13/D1_IncomeStatment!$G$9 -> -0.015226829
A14: Ford Credit Interest, Operating, and Other Expenses | B14: =D1_IncomeStatment!B14/D1_IncomeStatment!$B$9 -> -0.0087255096 | C14: =D1_IncomeStatment!C14/D1_IncomeStatment!$C$9 -> -0.0050813008 | D14: =D1_IncomeStatment!D14/D1_IncomeStatment!$D$9 -> -0.0032975578
A15: Selling Administrative and Other Expenses | B15: =D1_IncomeStatment!B15/D1_IncomeStatment!$B$9 -> -0.057933325 | C15: =D1_IncomeStatment!C15/D1_IncomeStatment!$C$9 -> -0.05560781 | D15: =D1_IncomeStatment!D15/D1_IncomeStatment!$D$9 -> -0.060740901 | E15: =D1_IncomeStatment!E15/D1_IncomeStatment!$E$9 -> -0.068886541 | F15: =D1_IncomeStatment!F15/D1_IncomeStatment!$F$9 -> -0.087391174 | G15: =D1_IncomeStatment!G15/D1_IncomeStatment!$G$9 -> -0.080168942
A16: Interest Expense on Company Debt Excluding Ford Credit | B16: =D1_IncomeStatment!B16/D1_IncomeStatment!$B$9 -> -0.0066963213 | C16: =D1_IncomeStatment!C16/D1_IncomeStatment!$C$9 -> -0.0060272877 | D16: =D1_IncomeStatment!D16/D1_IncomeStatment!$D$9 -> -0.0073897078 | E16: =D1_IncomeStatment!E16/D1_IncomeStatment!$E$9 -> -0.0079654808 | F16: =D1_IncomeStatment!F16/D1_IncomeStatment!$F$9 -> -0.013224195 | G16: =D1_IncomeStatment!G16/D1_IncomeStatment!$G$9 -> -0.012969546
A17: Interest Expense | B17: =D1_IncomeStatment!B17/D1_IncomeStatment!$B$9 -> -0.03809 | C17: =D1_IncomeStatment!C17/D1_IncomeStatment!$C$9 -> -0.040990962 | D17: =D1_IncomeStatment!D17/D1_IncomeStatment!$D$9 -> -0.035819083 | E17: =D1_IncomeStatment!E17/D1_IncomeStatment!$E$9 -> -0.021093656 | F17: =D1_IncomeStatment!F17/D1_IncomeStatment!$F$9 -> -0.020463397 | G17: =D1_IncomeStatment!G17/D1_IncomeStatment!$G$9 -> -0.026757063
A18: Equity in Net (Loss)/income of Affiliated Companies | B18: =D1_IncomeStatment!B18/D1_IncomeStatment!$B$9 -> -0.016836923 | C18: =D1_IncomeStatment!C18/D1_IncomeStatment!$C$9 -> 0.0036650234 | D18: =D1_IncomeStatment!D18/D1_IncomeStatment!$D$9 -> 0.0023497227 | E18: =D1_IncomeStatment!E18/D1_IncomeStatment!$E$9 -> -0.018240255 | F18: =D1_IncomeStatment!F18/D1_IncomeStatment!$F$9 -> 0.0023983981 | G18: =D1_IncomeStatment!G18/D1_IncomeStatment!$G$9 -> 0.00033033411
A19: Other Income (Loss), Net | B19: =D1_IncomeStatment!B19/D1_IncomeStatment!$B$9 -> 0.0093235861 | C19: =D1_IncomeStatment!C19/D1_IncomeStatment!$C$9 -> 0.013249222 | D19: =D1_IncomeStatment!D19/D1_IncomeStatment!$D$9 -> -0.0034224223 | E19: =D1_IncomeStatment!E19/D1_IncomeStatment!$E$9 -> -0.032583182 | F19: =D1_IncomeStatment!F19/D1_IncomeStatment!$F$9 -> 0.10805994 | G19: =D1_IncomeStatment!G19/D1_IncomeStatment!$G$9 -> 0.038531114
A20: Income/(Loss) before Income Taxes-financial Services | E20: =D1_IncomeStatment!E20/D1_IncomeStatment!$E$9 -> 0 | F20: =D1_IncomeStatment!F20/D1_IncomeStatment!$F$9 -> 0.034597076 | G20: =D1_IncomeStatment!G20/D1_IncomeStatment!$G$9 -> 0.020512175
A21: Income (Loss) before Income Taxes | E21: =D1_IncomeStatment!E21/D1_IncomeStatment!$E$9 -> 0.016810391 | F21: =D1_IncomeStatment!F21/D1_IncomeStatment!$F$9 -> 0 | G21: =D1_IncomeStatment!G21/D1_IncomeStatment!$G$9 -> 0
A22: Earnings before Taxes | B22: =D1_IncomeStatment!B22/D1_IncomeStatment!$B$9 -> -0.063171835 | C22: =D1_IncomeStatment!C22/D1_IncomeStatment!$C$9 -> 0.039098988 | D22: =D1_IncomeStatment!D22/D1_IncomeStatment!$D$9 -> 0.022515338 | E22: =D1_IncomeStatment!E22/D1_IncomeStatment!$E$9 -> -0.019081724 | F22: =D1_IncomeStatment!F22/D1_IncomeStatment!$F$9 -> 0.13040831 | G22: =D1_IncomeStatment!G22/D1_IncomeStatment!$G$9 -> -0.0087774492
A23: Taxes and Other Expenses
A24: Provision for Income Tax | B24: =D1_IncomeStatment!B24/D1_IncomeStatment!$B$9 -> 0.019587007 | C24: =D1_IncomeStatment!C24/D1_IncomeStatment!$C$9 -> -0.0072381508 | D24: =D1_IncomeStatment!D24/D1_IncomeStatment!$D$9 -> 0.0020545885 | E24: =D1_IncomeStatment!E24/D1_IncomeStatment!$E$9 -> 0.0054663824 | F24: =D1_IncomeStatment!F24/D1_IncomeStatment!$F$9 -> 0.00095349161 | G24: =D1_IncomeStatment!G24/D1_IncomeStatment!$G$9 -> -0.0012584157
A25: Minority Interest (After Tax) | B25: =D1_IncomeStatment!B25/D1_IncomeStatment!$B$9 -> -0.00010679938 | C25: =D1_IncomeStatment!C25/D1_IncomeStatment!$C$9 -> -8.1084587e-05 | D25: =D1_IncomeStatment!D25/D1_IncomeStatment!$D$9 -> 0.00010216186 | E25: =D1_IncomeStatment!E25/D1_IncomeStatment!$E$9 -> 0.0010818882 | F25: =D1_IncomeStatment!F25/D1_IncomeStatment!$F$9 -> 0.00019803287 | G25: =D1_IncomeStatment!G25/D1_IncomeStatment!$G$9 -> -2.3595294e-05
A26: Net Income (Loss) | B26: =D1_IncomeStatment!B26/D1_IncomeStatment!$B$9 -> -0.043691627 | C26: =D1_IncomeStatment!C26/D1_IncomeStatment!$C$9 -> 0.031779753 | D26: =D1_IncomeStatment!D26/D1_IncomeStatment!$D$9 -> 0.024672089 | E26: =D1_IncomeStatment!E26/D1_IncomeStatment!$E$9 -> -0.012533453 | F26: =D1_IncomeStatment!F26/D1_IncomeStatment!$F$9 -> 0.13155984 | G26: =D1_IncomeStatment!G26/D1_IncomeStatment!$G$9 -> -0.01005946
A27: Supplementary Info
A28: Operating Income (Loss) | B28: =D1_IncomeStatment!B28/D1_IncomeStatment!$B$9 -> -0.048962177 | C28: =D1_IncomeStatment!C28/D1_IncomeStatment!$C$9 -> 0.028212031 | D28: =D1_IncomeStatment!D28/D1_IncomeStatment!$D$9 -> 0.030977746 | E28: =D1_IncomeStatment!E28/D1_IncomeStatment!$E$9 -> 0.039707194 | F28: =D1_IncomeStatment!F28/D1_IncomeStatment!$F$9 -> 0.033174174 | G28: =D1_IncomeStatment!G28/D1_IncomeStatment!$G$9 -> -0.034669351
A29: Basic EPS - Continuing Operations | B29: =D1_IncomeStatment!B29/D1_IncomeStatment!$B$9 -> -1.1000336e-05 | C29: =D1_IncomeStatment!C29/D1_IncomeStatment!$C$9 -> 8.000346e-06 | D29: =D1_IncomeStatment!D29/D1_IncomeStatment!$D$9 -> 6.1864681e-06 | E29: =D1_IncomeStatment!E29/D1_IncomeStatment!$E$9 -> -3.1001474e-06 | F29: =D1_IncomeStatment!F29/D1_IncomeStatment!$F$9 -> 3.2932133e-05 | G29: =D1_IncomeStatment!G29/D1_IncomeStatment!$G$9 -> -2.5168313e-06
A30: Diluted EPS - Continuing Operations | B30: =D1_IncomeStatment!B30/D1_IncomeStatment!$B$9 -> -1.1000336e-05 | C30: =D1_IncomeStatment!C30/D1_IncomeStatment!$C$9 -> 7.8922332e-06 | D30: =D1_IncomeStatment!D30/D1_IncomeStatment!$D$9 -> 6.1297115e-06 | E30: =D1_IncomeStatment!E30/D1_IncomeStatment!$E$9 -> -3.1001474e-06 | F30: =D1_IncomeStatment!F30/D1_IncomeStatment!$F$9 -> 3.2638751e-05 | G30: =D1_IncomeStatment!G30/D1_IncomeStatment!$G$9 -> -2.5168313e-06

Sheet D2_IncomeStateGraph

Sheet D3_Fig_Rev_OpInc_NetInc
A1: Insert any figures requested in the deliverable instructions here:
A2: Create a Line Graph of Revenues, Operating Incomes and Net Incomes through time
A4: Year | B4: 2020 | C4: 2021 | D4: 2022 | E4: 2023 | F4: 2024 | G4: 2025
A5: Revenue | B5: ='D3_Analysis of Income Statment'!G4 -> 127144 | C5: ='D3_Analysis of Income Statment'!F4 -> 136341 | D5: ='D3_Analysis of Income Statment'!E4 -> 158057 | E5: ='D3_Analysis of Income Statment'!D4 -> 176191 | F5: ='D3_Analysis of Income Statment'!C4 -> 184992 | G5: ='D3_Analysis of Income Statment'!B4 -> 187267
A6: OpInc | B6: ='D3_Analysis of Income Statment'!G10 -> -4408 | C6: ='D3_Analysis of Income Statment'!F10 -> 4523 | D6: ='D3_Analysis of Income Statment'!E10 -> 6276 | E6: ='D3_Analysis of Income Statment'!D10 -> 5458 | F6: ='D3_Analysis of Income Statment'!C10 -> 5219 | G6: ='D3_Analysis of Income Statment'!B10 -> -9169
A7: Net Income | B7: ='D3_Analysis of Income Statment'!G13 -> -1279 | C7: ='D3_Analysis of Income Statment'!F13 -> 17937 | D7: ='D3_Analysis of Income Statment'!E13 -> -1981 | E7: ='D3_Analysis of Income Statment'!D13 -> 4347 | F7: ='D3_Analysis of Income Statment'!C13 -> 5879 | G7: ='D3_Analysis of Income Statment'!B13 -> -8182

Sheet D3_Analysis of Income Statment
B2: 2025 | C2: 2024 | D2: 2023 | E2: 2022 | F2: 2021 | G2: 2020
A3: Line Items
A4: Revenue ($Amt) | B4: =D1_IncomeStatment!B9 -> 187267 | C4: =D1_IncomeStatment!C9 -> 184992 | D4: =D1_IncomeStatment!D9 -> 176191 | E4: =D1_IncomeStatment!E9 -> 158057 | F4: =D1_IncomeStatment!F9 -> 136341 | G4: =D1_IncomeStatment!G9 -> 127144
A5: Revenue Growth (or Decline) | B5: =D3_ISHorizontalAnalysis!B3 -> 0.012297829 | C5: =D3_ISHorizontalAnalysis!C3 -> 0.049951473 | D5: =D3_ISHorizontalAnalysis!D3 -> 0.11473076 | E5: =D3_ISHorizontalAnalysis!E3 -> 0.15927711 | F5: =D3_ISHorizontalAnalysis!F3 -> 0.072335305 | G5: =D3_ISHorizontalAnalysis!G3 -> -
A7: EBITDA ($Amt) | B7: =D1_IncomeStatment!B22+D1_IncomeStatment!B17+D1_IncomeStatment!B12 -> -21423 | C7: =D1_IncomeStatment!C22+D1_IncomeStatment!C17+D1_IncomeStatment!C12 -> -2879 | D7: =D1_IncomeStatment!D22+D1_IncomeStatment!D17+D1_IncomeStatment!D12 -> -4933 | E7: =D1_IncomeStatment!E22+D1_IncomeStatment!E17+D1_IncomeStatment!E12 -> -8631 | F7: =D1_IncomeStatment!F22+D1_IncomeStatment!F17+D1_IncomeStatment!F12 -> 13324 | G7: =D1_IncomeStatment!G22+D1_IncomeStatment!G17+D1_IncomeStatment!G12 -> -7787
A8: EBITDA Growth (or Decline) | B8: =(B7-C7)/ABS(C7) -> -6.4411254 | C8: =(C7-D7)/ABS(D7) -> 0.41637949 | D8: =(D7-E7)/ABS(E7) -> 0.42845557 | E8: =(E7-F7)/ABS(F7) -> -1.6477784 | F8: =(F7-G7)/ABS(G7) -> 2.7110569 | G8: -
A10: Operating Income ($Amt) | B10: =D1_IncomeStatment!B28 -> -9169 | C10: =D1_IncomeStatment!C28 -> 5219 | D10: =D1_IncomeStatment!D28 -> 5458 | E10: =D1_IncomeStatment!E28 -> 6276 | F10: =D1_IncomeStatment!F28 -> 4523 | G10: =D1_IncomeStatment!G28 -> -4408
A11: Operating Income Growth (or Decline) | B11: =(B10-C10)/ABS(C10) -> -2.75685 | C11: =(C10-D10)/ABS(D10) -> -0.043788934 | D11: =(D10-E10)/ABS(E10) -> -0.13033779 | E11: =(E10-F10)/ABS(F10) -> 0.38757462 | F11: =(F10-G10)/ABS(G10) -> 2.0260889 | G11: -
A13: Net Income ($Amt) | B13: =D1_IncomeStatment!B26 -> -8182 | C13: =D1_IncomeStatment!C26 -> 5879 | D13: =D1_IncomeStatment!D26 -> 4347 | E13: =D1_IncomeStatment!E26 -> -1981 | F13: =D1_IncomeStatment!F26 -> 17937 | G13: =D1_IncomeStatment!G26 -> -1279
A14: Net Income Growth (or Decline) | B14: =D3_ISHorizontalAnalysis!B5 -> -2.3917333 | C14: =D3_ISHorizontalAnalysis!C5 -> 0.35242696 | D14: =D3_ISHorizontalAnalysis!D5 -> 3.1943463 | E14: =D3_ISHorizontalAnalysis!E5 -> -1.1104421 | F14: =D3_ISHorizontalAnalysis!F5 -> 15.024238 | G14: =D3_ISHorizontalAnalysis!G5 -> -
A15: *Please use calculations as shown in the slides and/or textbook (please do not use the internet)
B17: 2025 | C17: 2024 | D17: 2023 | E17: 2022 | F17: 2021 | G17: 2020
A18: Profit Measures
A19: Gross Margin | B19: =(D1_IncomeStatment!B9+D1_IncomeStatment!B11)/D1_IncomeStatment!B9 -> 0.19606765 | C19: =(D1_IncomeStatment!C9+D1_IncomeStatment!C11)/D1_IncomeStatment!C9 -> 0.14356296 | D19: =(D1_IncomeStatment!D9+D1_IncomeStatment!D11)/D1_IncomeStatment!D9 -> 0.14552957 | E19: =(D1_IncomeStatment!E9+D1_IncomeStatment!E11)/D1_IncomeStatment!E9 -> 0.14969283 | F19: =(D1_IncomeStatment!F9+D1_IncomeStatment!F11)/D1_IncomeStatment!F9 -> 0.15908641 | G19: =(D1_IncomeStatment!G9+D1_IncomeStatment!G11)/D1_IncomeStatment!G9 -> 0.11319449
A20: Operating Margin | B20: =D1_IncomeStatment!B28/D1_IncomeStatment!B9 -> -0.048962177 | C20: =D1_IncomeStatment!C28/D1_IncomeStatment!C9 -> 0.028212031 | D20: =D1_IncomeStatment!D28/D1_IncomeStatment!D9 -> 0.030977746 | E20: =D1_IncomeStatment!E28/D1_IncomeStatment!E9 -> 0.039707194 | F20: =D1_IncomeStatment!F28/D1_IncomeStatment!F9 -> 0.033174174 | G20: =D1_IncomeStatment!G28/D1_IncomeStatment!G9 -> -0.034669351
A21: Pre-tax Margin | B21: =D1_IncomeStatment!B22/D1_IncomeStatment!B9 -> -0.063171835 | C21: =D1_IncomeStatment!C22/D1_IncomeStatment!C9 -> 0.039098988 | D21: =D1_IncomeStatment!D22/D1_IncomeStatment!D9 -> 0.022515338 | E21: =D1_IncomeStatment!E22/D1_IncomeStatment!E9 -> -0.019081724 | F21: =D1_IncomeStatment!F22/D1_IncomeStatment!F9 -> 0.13040831 | G21: =D1_IncomeStatment!G22/D1_IncomeStatment!G9 -> -0.0087774492
A22: Profit Margin | B22: =D1_IncomeStatment!B26/D1_IncomeStatment!B9 -> -0.043691627 | C22: =D1_IncomeStatment!C26/D1_IncomeStatment!C9 -> 0.031779753 | D22: =D1_IncomeStatment!D26/D1_IncomeStatment!D9 -> 0.024672089 | E22: =D1_IncomeStatment!E26/D1_IncomeStatment!E9 -> -0.012533453 | F22: =D1_IncomeStatment!F26/D1_IncomeStatment!F9 -> 0.13155984 | G22: =D1_IncomeStatment!G26/D1_IncomeStatment!G9 -> -0.01005946
B25: 2025 | C25: 2024 | D25: 2023 | E25: 2022 | F25: 2021 | G25: 2020
A26: Earnings Per Share Measures
A27: Basic EPS | B27: =D1_IncomeStatment!B29 -> -2.06 | C27: =D1_IncomeStatment!C29 -> 1.48 | D27: =D1_IncomeStatment!D29 -> 1.09 | E27: =D1_IncomeStatment!E29 -> -0.49 | F27: =D1_IncomeStatment!F29 -> 4.49 | G27: =D1_IncomeStatment!G29 -> -0.32
A28: Diluted EPS | B28: =D1_IncomeStatment!B30 -> -2.06 | C28: =D1_IncomeStatment!C30 -> 1.46 | D28: =D1_IncomeStatment!D30 -> 1.08 | E28: =D1_IncomeStatment!E30 -> -0.49 | F28: =D1_IncomeStatment!F30 -> 4.45 | G28: =D1_IncomeStatment!G30 -> -0.32
B31: 2025 | C31: 2024 | D31: 2023 | E31: 2022 | F31: 2021 | G31: 2020
A32: Comprehensive Income Measures
A33: Net Income/Total Comprehensive Income | B33: =D1_IncomeStatment!B26 -> -8182 | C33: =D1_IncomeStatment!C26 -> 5879 | D33: =D1_IncomeStatment!D26 -> 4347 | E33: =D1_IncomeStatment!E26 -> -1981 | F33: =D1_IncomeStatment!F26 -> 17937 | G33: =D1_IncomeStatment!G26 -> -1279
A34: Other Comprehensive Income / Total Comprehensive Income | B34: =D1_IncomeStatment!B26 -> -8182 | C34: =D1_IncomeStatment!C26 -> 5879 | D34: =D1_IncomeStatment!D26 -> 4347 | E34: =D1_IncomeStatment!E26 -> -1981 | F34: =D1_IncomeStatment!F26 -> 17937 | G34: =D1_IncomeStatment!G26 -> -1279

Sheet D3_ISHorizontalAnalysis
A1: Line Items | B1: 2025 | C1: 2024 | D1: 2023 | E1: 2022 | F1: 2021 | G1: 2020
A3: Revenue | B3: =(D1_IncomeStatment!B9-D1_IncomeStatment!C9)/ABS(D1_IncomeStatment!C9) -> 0.012297829 | C3: =(D1_IncomeStatment!C9-D1_IncomeStatment!D9)/ABS(D1_IncomeStatment!D9) -> 0.049951473 | D3: =(D1_IncomeStatment!D9-D1_IncomeStatment!E9)/ABS(D1_IncomeStatment!E9) -> 0.11473076 | E3: =(D1_IncomeStatment!E9-D1_IncomeStatment!F9)/ABS(D1_IncomeStatment!F9) -> 0.15927711 | F3: =(D1_IncomeStatment!F9-D1_IncomeStatment!G9)/ABS(D1_IncomeStatment!G9) -> 0.072335305 | G3: -
A4: EBIT | B4: =(D1_IncomeStatment!B22-D1_IncomeStatment!C22)/ABS(D1_IncomeStatment!C22) -> -2.6355592 | C4: =(D1_IncomeStatment!C22-D1_IncomeStatment!D22)/ABS(D1_IncomeStatment!D22) -> 0.82329216 | D4: =(D1_IncomeStatment!D22-D1_IncomeStatment!E22)/ABS(D1_IncomeStatment!E22) -> 2.3153183 | E4: =(D1_IncomeStatment!E22-D1_IncomeStatment!F22)/ABS(D1_IncomeStatment!F22) -> -1.1696288 | F4: =(D1_IncomeStatment!F22-D1_IncomeStatment!G22)/ABS(D1_IncomeStatment!G22) -> 16.9319 | G4: -
A5: Net Income | B5: =(D1_IncomeStatment!B26-D1_IncomeStatment!C26)/ABS(D1_IncomeStatment!C26) -> -2.3917333 | C5: =(D1_IncomeStatment!C26-D1_IncomeStatment!D26)/ABS(D1_IncomeStatment!D26) -> 0.35242696 | D5: =(D1_IncomeStatment!D26-D1_IncomeStatment!E26)/ABS(D1_IncomeStatment!E26) -> 3.1943463 | E5: =(D1_IncomeStatment!E26-D1_IncomeStatment!F26)/ABS(D1_IncomeStatment!F26) -> -1.1104421 | F5: =(D1_IncomeStatment!F26-D1_IncomeStatment!G26)/ABS(D1_IncomeStatment!G26) -> 15.024238 | G5: -

Sheet D1_Statement Of Comp. Income
A1: Line Items | B1: Year(t=0) | C1: Year(t=-1) | D1: Year(t=-2) | E1: Year(t=-3) | F1: Year(t=-4) | G1: Year(t=-5) | I1: MEAN | J1: STD | K1: MIN | L1: MEDIAN | M1: MAX
B2: 2025 | C2: 2024 | D2: 2023 | E2: 2022 | F2: 2021 | G2: 2020
A3: Net income/(loss) | B3: -8162 | C3: 5894 | D3: 4329 | E3: -2152 | F3: 17910 | G3: -1276 | I3: =AVERAGE(B3:G3) -> 2757.1667 | J3: =STDEV(B3:G3) -> 8961.1751 | K3: =MIN(B3:G3) -> -8162 | L3: =MEDIAN(B3:G3) -> 1526.5 | M3: =MAX(B3:G3) -> 17910
A4: Foreign currency translation | B4: 2020 | C4: -1457 | D4: 974 | E4: -933 | F4: 43 | G4: -901 | I4: =AVERAGE(B4:G4) -> -42.333333 | J4: =STDEV(B4:G4) -> 1328.5565 | K4: =MIN(B4:G4) -> -1457 | L4: =MEDIAN(B4:G4) -> -429 | M4: =MAX(B4:G4) -> 2020
A5: Marketable securities | B5: 131 | C5: 120 | D5: 272 | E5: -423 | F5: -175 | G5: 85 | I5: =AVERAGE(B5:G5) -> 1.6666667 | J5: =STDEV(B5:G5) -> 253.89263 | K5: =MIN(B5:G5) -> -423 | L5: =MEDIAN(B5:G5) -> 102.5 | M5: =MAX(B5:G5) -> 272
A6: Derivative instruments | B6: -315 | C6: 608 | D6: -460 | E6: 322 | F6: 73 | G6: 222 | I6: =AVERAGE(B6:G6) -> 75 | J6: =STDEV(B6:G6) -> 401.25702 | K6: =MIN(B6:G6) -> -460 | L6: =MEDIAN(B6:G6) -> 147.5 | M6: =MAX(B6:G6) -> 608
A7: Pension and other postretirement benefits | B7: 92 | C7: 131 | D7: -488 | E7: 30 | F7: 18 | G7: 27 | I7: =AVERAGE(B7:G7) -> -31.666667 | J7: =STDEV(B7:G7) -> 227.90583 | K7: =MIN(B7:G7) -> -488 | L7: =MEDIAN(B7:G7) -> 28.5 | M7: =MAX(B7:G7) -> 131
A8: Total other comprehensive income/(loss), net of tax | B8: 1928 | C8: -598 | D8: 298 | E8: -1004 | F8: -41 | G8: -567 | I8: =AVERAGE(B8:G8) -> 2.6666667 | J8: =STDEV(B8:G8) -> 1048.3068 | K8: =MIN(B8:G8) -> -1004 | L8: =MEDIAN(B8:G8) -> -304 | M8: =MAX(B8:G8) -> 1928
A9: Comprehensive income/(loss) | B9: -6234 | C9: 5296 | D9: 4627 | E9: -3156 | F9: 17869 | G9: -1843 | I9: =AVERAGE(B9:G9) -> 2759.8333 | J9: =STDEV(B9:G9) -> 8663.4585 | K9: =MIN(B9:G9) -> -6234 | L9: =MEDIAN(B9:G9) -> 1392 | M9: =MAX(B9:G9) -> 17869
A10: Less: Comprehensive income/(loss) attributable to noncontrolling interests | B10: 19 | C10: 14 | D10: -17 | E10: -175 | F10: -23 | G10: 2 | I10: =AVERAGE(B10:G10) -> -30 | J10: =STDEV(B10:G10) -> 72.943814 | K10: =MIN(B10:G10) -> -175 | L10: =MEDIAN(B10:G10) -> -7.5 | M10: =MAX(B10:G10) -> 19
A11: Comprehensive income/(loss) attributable to Ford Motor Company | B11: -6253 | C11: 5282 | D11: 4644 | E11: -2981 | F11: 17892 | G11: -1845 | I11: =AVERAGE(B11:G11) -> 2789.8333 | J11: =STDEV(B11:G11) -> 8651.9512 | K11: =MIN(B11:G11) -> -6253 | L11: =MEDIAN(B11:G11) -> 1399.5 | M11: =MAX(B11:G11) -> 17892

Sheet D1_StatmentofCFs
A1: Line Items | B1: Year(t=0) | C1: Year(t=-1) | D1: Year(t=-2) | E1: Year(t=-3) | F1: Year(t=-4) | G1: Year(t=-5) | J1: MEAN | K1: STD | L1: MIN | M1: MEDIAN | N1: MAX
B2: 2025 | C2: 2024 | D2: 2023 | E2: 2022 | F2: 2021 | G2: 2020
A3: Operating Activities
A4: Net Income (Loss) from Continuing Operations | B4: -8162 | C4: 5894 | D4: 4329 | E4: -2152 | F4: 17910 | G4: -1276 | J4: =AVERAGE(B4:G4) -> 2757.1667 | K4: =STDEV(B4:G4) -> 8961.1751 | L4: =MIN(B4:G4) -> -8162 | M4: =MEDIAN(B4:G4) -> 1526.5 | N4: =MAX(B4:G4) -> 17910
A5: Depreciation and Amortization | B5: 7834 | C5: 7567 | D5: 7690 | E5: 7642 | F5: 7318 | G5: 8751 | J5: =AVERAGE(B5:G5) -> 7800.3333 | K5: =STDEV(B5:G5) -> 495.82927 | L5: =MIN(B5:G5) -> 7318 | M5: =MEDIAN(B5:G5) -> 7666 | N5: =MAX(B5:G5) -> 8751
A6: Depreciation and Tooling Amortization | E6: 7642 | J6: =AVERAGE(B6:G6) -> 7642 | K6: =STDEV(B6:G6) -> #DIV/0! | L6: =MIN(B6:G6) -> 7642 | M6: =MEDIAN(B6:G6) -> 7642 | N6: =MAX(B6:G6) -> 7642
A7: Other Amortization | B7: -1839 | C7: -1700 | D7: -1167 | E7: -1149 | F7: -1358 | G7: -1294 | J7: =AVERAGE(B7:G7) -> -1417.8333 | K7: =STDEV(B7:G7) -> 286.74129 | L7: =MIN(B7:G7) -> -1839 | M7: =MEDIAN(B7:G7) -> -1326 | N7: =MAX(B7:G7) -> -1149
A8: Held-for-sale Impairment Charges | G8: 23 | J8: =AVERAGE(B8:G8) -> 23 | K8: =STDEV(B8:G8) -> #DIV/0! | L8: =MIN(B8:G8) -> 23 | M8: =MEDIAN(B8:G8) -> 23 | N8: =MAX(B8:G8) -> 23
A9: Net Gain/loss on Changes in Investments in Affiliates | F9: -368 | G9: -3446 | J9: =AVERAGE(B9:G9) -> -1907 | K9: =STDEV(B9:G9) -> 2176.4747 | L9: =MIN(B9:G9) -> -3446 | M9: =MEDIAN(B9:G9) -> -1907 | N9: =MAX(B9:G9) -> -368
A10: EV asset impairment/program Cancellation asset write-downs | B10: 9435 | J10: =AVERAGE(B10:G10) -> 9435 | K10: =STDEV(B10:G10) -> #DIV/0! | L10: =MIN(B10:G10) -> 9435 | M10: =MEDIAN(B10:G10) -> 9435 | N10: =MAX(B10:G10) -> 9435
A11: Brazil Manufacturing Exit Non-cash Charges (excluding Accelerated Depreciation | G11: 1159 | J11: =AVERAGE(B11:G11) -> 1159 | K11: =STDEV(B11:G11) -> #DIV/0! | L11: =MIN(B11:G11) -> 1159 | M11: =MEDIAN(B11:G11) -> 1159 | N11: =MAX(B11:G11) -> 1159
A12: Net Losses/(Earnings) from Equity Investments in Excess of Dividends Remitted | F12: 116 | G12: 130 | J12: =AVERAGE(B12:G12) -> 123 | K12: =STDEV(B12:G12) -> 9.8994949 | L12: =MIN(B12:G12) -> 116 | M12: =MEDIAN(B12:G12) -> 123 | N12: =MAX(B12:G12) -> 130
A13: Equity Method Investment (Earnings)/Losses and Impairments in Excess of Dividends Received | B13: 3572 | C13: -287 | D13: -33 | E13: 3324 | J13: =AVERAGE(B13:G13) -> 1644 | K13: =STDEV(B13:G13) -> 2088.1151 | L13: =MIN(B13:G13) -> -287 | M13: =MEDIAN(B13:G13) -> 1645.5 | N13: =MAX(B13:G13) -> 3572
A14: Stock Compensation | B14: 510 | C14: 511 | D14: 460 | E14: 336 | F14: 305 | G14: 199 | J14: =AVERAGE(B14:G14) -> 386.83333 | K14: =STDEV(B14:G14) -> 126.88801 | L14: =MIN(B14:G14) -> 199 | M14: =MEDIAN(B14:G14) -> 398 | N14: =MAX(B14:G14) -> 511
A15: Provision for Credit/insurance Losses | B15: 616 | C15: 575 | D15: 438 | E15: 46 | J15: =AVERAGE(B15:G15) -> 418.75 | K15: =STDEV(B15:G15) -> 259.89405 | L15: =MIN(B15:G15) -> 46 | M15: =MEDIAN(B15:G15) -> 506.5 | N15: =MAX(B15:G15) -> 616
A16: Provision For/(benefit From) Credit and Insurance Losses | F16: -298 | G16: 929 | J16: =AVERAGE(B16:G16) -> 315.5 | K16: =STDEV(B16:G16) -> 867.62002 | L16: =MIN(B16:G16) -> -298 | M16: =MEDIAN(B16:G16) -> 315.5 | N16: =MAX(B16:G16) -> 929
A17: Foreign Currency Adjustments | B17: -87 | C17: 227 | D17: -234 | E17: -27 | F17: 532 | G17: -420 | J17: =AVERAGE(B17:G17) -> -1.5 | K17: =STDEV(B17:G17) -> 338.81957 | L17: =MIN(B17:G17) -> -420 | M17: =MEDIAN(B17:G17) -> -57 | N17: =MAX(B17:G17) -> 532
A18: Others | B18: 380 | C18: 439 | D18: 664 | E18: 654 | F18: -186 | G18: 72 | J18: =AVERAGE(B18:G18) -> 337.16667 | K18: =STDEV(B18:G18) -> 335.68582 | L18: =MIN(B18:G18) -> -186 | M18: =MEDIAN(B18:G18) -> 409.5 | N18: =MAX(B18:G18) -> 664
A19: Gain/loss on Extinguishment of Debt | F19: 1702 | G19: 1 | J19: =AVERAGE(B19:G19) -> 851.5 | K19: =STDEV(B19:G19) -> 1202.7886 | L19: =MIN(B19:G19) -> 1 | M19: =MEDIAN(B19:G19) -> 851.5 | N19: =MAX(B19:G19) -> 1702
A20: Pension and Other Postretirement Employee Benefits (opeb) Income/expense | B20: 1062 | C20: 149 | D20: 3052 | E20: -378 | F20: -4865 | G20: 1027 | J20: =AVERAGE(B20:G20) -> 7.8333333 | K20: =STDEV(B20:G20) -> 2658.2031 | L20: =MIN(B20:G20) -> -4865 | M20: =MEDIAN(B20:G20) -> 588 | N20: =MAX(B20:G20) -> 3052
A21: Net Realized and Unrealized Gain/loss on Cash Equivalents, Marketable Securities, and Other Investments | B21: -346 | C21: 42 | D21: 205 | E21: 7518 | F21: -9159 | G21: -315 | J21: =AVERAGE(B21:G21) -> -342.5 | K21: =STDEV(B21:G21) -> 5290.8694 | L21: =MIN(B21:G21) -> -9159 | M21: =MEDIAN(B21:G21) -> -136.5 | N21: =MAX(B21:G21) -> 7518
A22: Accounts Receivable and Other Current Assets | B22: -2791 | C22: -2497 | D22: -2620 | E22: -1183 | F22: -1141 | G22: -63 | J22: =AVERAGE(B22:G22) -> -1715.8333 | K22: =STDEV(B22:G22) -> 1089.0294 | L22: =MIN(B22:G22) -> -2791 | M22: =MEDIAN(B22:G22) -> -1840 | N22: =MAX(B22:G22) -> -63
A23: Changes in Finance Receivables (wholesale and Other) | B23: 4992 | C23: -4299 | D23: -4827 | E23: -10560 | F23: 7656 | G23: 12104 | J23: =AVERAGE(B23:G23) -> 844.33333 | K23: =STDEV(B23:G23) -> 8706.9944 | L23: =MIN(B23:G23) -> -10560 | M23: =MEDIAN(B23:G23) -> 346.5 | N23: =MAX(B23:G23) -> 12104
A24: Changes in Inventory | B24: 539 | C24: 27 | D24: -1219 | E24: -2576 | F24: -1778 | G24: 148 | J24: =AVERAGE(B24:G24) -> -809.83333 | K24: =STDEV(B24:G24) -> 1237.8364 | L24: =MIN(B24:G24) -> -2576 | M24: =MEDIAN(B24:G24) -> -596 | N24: =MAX(B24:G24) -> 539
A25: Accounts Payable and Other Liabilities | B25: 10103 | C25: 8425 | D25: 9829 | E25: 7268 | F25: -36 | G25: 6809 | J25: =AVERAGE(B25:G25) -> 7066.3333 | K25: =STDEV(B25:G25) -> 3721.5501 | L25: =MIN(B25:G25) -> -36 | M25: =MEDIAN(B25:G25) -> 7846.5 | N25: =MAX(B25:G25) -> 10103
A26: (Credit) Provision for Deferred Income Taxes | B26: -4536 | C26: 350 | D26: -1649 | E26: -1910 | F26: -563 | G26: -269 | J26: =AVERAGE(B26:G26) -> -1429.5 | K26: =STDEV(B26:G26) -> 1743.1928 | L26: =MIN(B26:G26) -> -4536 | M26: =MEDIAN(B26:G26) -> -1106 | N26: =MAX(B26:G26) -> 350
A27: Cash Flow from Operating Activities | B27: 21282 | C27: 15423 | D27: 14918 | E27: 6853 | F27: 15787 | G27: 24269 | J27: =AVERAGE(B27:G27) -> 16422 | K27: =STDEV(B27:G27) -> 6007.0627 | L27: =MIN(B27:G27) -> 6853 | M27: =MEDIAN(B27:G27) -> 15605 | N27: =MAX(B27:G27) -> 24269
A28: Investing Activities
A29: Capital Spending | B29: -8815 | C29: -8684 | D29: -8236 | E29: -6866 | F29: -6227 | G29: -5742 | J29: =AVERAGE(B29:G29) -> -7428.3333 | K29: =STDEV(B29:G29) -> 1323.2543 | L29: =MIN(B29:G29) -> -8815 | M29: =MEDIAN(B29:G29) -> -7551 | N29: =MAX(B29:G29) -> -5742
A30: Proceeds from Sale of Businesses | E30: 449 | F30: 145 | G30: 1340 | J30: =AVERAGE(B30:G30) -> 644.66667 | K30: =STDEV(B30:G30) -> 621.06387 | L30: =MIN(B30:G30) -> 145 | M30: =MEDIAN(B30:G30) -> 449 | N30: =MAX(B30:G30) -> 1340
A31: Return of Capital from Equity Method Investment | B31: 1702 | C31: 1465 | D31: 1 | J31: =AVERAGE(B31:G31) -> 1056 | K31: =STDEV(B31:G31) -> 921.30939 | L31: =MIN(B31:G31) -> 1 | M31: =MEDIAN(B31:G31) -> 1465 | N31: =MAX(B31:G31) -> 1702
A32: Capital Contributions to Equity Method Investments | B32: -1172 | C32: -2323 | D32: -2733 | E32: -738 | F32: -57 | G32: -4 | J32: =AVERAGE(B32:G32) -> -1171.1667 | K32: =STDEV(B32:G32) -> 1145.1919 | L32: =MIN(B32:G32) -> -2733 | M32: =MEDIAN(B32:G32) -> -955 | N32: =MAX(B32:G32) -> -4
A33: Purchase of Marketable Securities and Other Investments | B33: -9457 | C33: -12300 | D33: -8590 | E33: -17458 | F33: -27491 | G33: -39624 | J33: =AVERAGE(B33:G33) -> -19153.333 | K33: =STDEV(B33:G33) -> 12198.443 | L33: =MIN(B33:G33) -> -39624 | M33: =MEDIAN(B33:G33) -> -14879 | N33: =MAX(B33:G33) -> -8590
A34: Sales and Maturities of Marketable Securities and Other Investments | B34: 10063 | C34: 12346 | D34: 12700 | E34: 19117 | F34: 33229 | G34: 32395 | J34: =AVERAGE(B34:G34) -> 19975 | K34: =STDEV(B34:G34) -> 10392.652 | L34: =MIN(B34:G34) -> 10063 | M34: =MEDIAN(B34:G34) -> 15908.5 | N34: =MAX(B34:G34) -> 33229
A35: Acquisitions of Finance Receivables and Operating Leases | B35: -55747 | C35: -59720 | D35: -54505 | E35: -45533 | F35: -48379 | G35: -55901 | J35: =AVERAGE(B35:G35) -> -53297.5 | K35: =STDEV(B35:G35) -> 5290.8209 | L35: =MIN(B35:G35) -> -59720 | M35: =MEDIAN(B35:G35) -> -55126 | N35: =MAX(B35:G35) -> -45533
A36: Collections of Finance Receivables and Operating Leases | B36: 45710 | C36: 45159 | D36: 44561 | E36: 46276 | F36: 52094 | G36: 48746 | J36: =AVERAGE(B36:G36) -> 47091 | K36: =STDEV(B36:G36) -> 2845.1342 | L36: =MIN(B36:G36) -> 44561 | M36: =MEDIAN(B36:G36) -> 45993 | N36: =MAX(B36:G36) -> 52094
A37: Others | B37: 110 | C37: -45 | D37: -688 | E37: 312 | F37: -297 | G37: 498 | J37: =AVERAGE(B37:G37) -> -18.333333 | K37: =STDEV(B37:G37) -> 428.7212 | L37: =MIN(B37:G37) -> -688 | M37: =MEDIAN(B37:G37) -> 32.5 | N37: =MAX(B37:G37) -> 498
A38: Settlement of Derivative | B38: -443 | C38: -268 | D38: -138 | E38: 94 | F38: -272 | G38: -323 | J38: =AVERAGE(B38:G38) -> -225 | K38: =STDEV(B38:G38) -> 184.67052 | L38: =MIN(B38:G38) -> -443 | M38: =MEDIAN(B38:G38) -> -270 | N38: =MAX(B38:G38) -> 94
A39: Cash Flow from Investing Activities | B39: -18049 | C39: -24370 | D39: -17628 | E39: -4347 | F39: 2745 | G39: -18615 | J39: =AVERAGE(B39:G39) -> -13377.333 | K39: =STDEV(B39:G39) -> 10292.143 | L39: =MIN(B39:G39) -> -24370 | M39: =MEDIAN(B39:G39) -> -17838.5 | N39: =MAX(B39:G39) -> 2745
A40: Financing Activities
A41: Principal Payments on Long-term Debt | B41: -50303 | C41: -45680 | D41: -41965 | E41: -45655 | F41: -54164 | G41: -60514 | J41: =AVERAGE(B41:G41) -> -49713.5 | K41: =STDEV(B41:G41) -> 6776.2092 | L41: =MIN(B41:G41) -> -60514 | M41: =MEDIAN(B41:G41) -> -47991.5 | N41: =MAX(B41:G41) -> -41965
A42: Proceeds from Issuance of Long-term Debt | B42: 49688 | C42: 57312 | D42: 51659 | E42: 45470 | F42: 27901 | G42: 65900 | J42: =AVERAGE(B42:G42) -> 49655 | K42: =STDEV(B42:G42) -> 12785.128 | L42: =MIN(B42:G42) -> 27901 | M42: =MEDIAN(B42:G42) -> 50673.5 | N42: =MAX(B42:G42) -> 65900
A43: Net Change in Short-term Debt | B43: 654 | C43: -276 | D43: -1539 | E43: 5460 | F43: 3273 | G43: -2291 | J43: =AVERAGE(B43:G43) -> 880.16667 | K43: =STDEV(B43:G43) -> 2966.3804 | L43: =MIN(B43:G43) -> -2291 | M43: =MEDIAN(B43:G43) -> 189 | N43: =MAX(B43:G43) -> 5460
A44: Purchase of Treasury Stock | C44: -426 | D44: -335 | E44: -484 | J44: =AVERAGE(B44:G44) -> -415 | K44: =STDEV(B44:G44) -> 75.106591 | L44: =MIN(B44:G44) -> -484 | M44: =MEDIAN(B44:G44) -> -426 | N44: =MAX(B44:G44) -> -335
A45: Cash Dividends | B45: -2989 | C45: -3118 | D45: -4995 | E45: -2009 | F45: -403 | G45: -596 | J45: =AVERAGE(B45:G45) -> -2351.6667 | K45: =STDEV(B45:G45) -> 1730.7663 | L45: =MIN(B45:G45) -> -4995 | M45: =MEDIAN(B45:G45) -> -2499 | N45: =MAX(B45:G45) -> -403
A46: Others | B46: -255 | C46: -327 | D46: -241 | E46: -271 | F46: -105 | G46: -184 | J46: =AVERAGE(B46:G46) -> -230.5 | K46: =STDEV(B46:G46) -> 76.909687 | L46: =MIN(B46:G46) -> -327 | M46: =MEDIAN(B46:G46) -> -248 | N46: =MAX(B46:G46) -> -105
A47: Cash Flow from Financing Activities | B47: -3205 | C47: 7485 | D47: 2584 | E47: 2511 | F47: -23498 | G47: 2315 | J47: =AVERAGE(B47:G47) -> -1968 | K47: =STDEV(B47:G47) -> 11077.513 | L47: =MIN(B47:G47) -> -23498 | M47: =MEDIAN(B47:G47) -> 2413 | N47: =MAX(B47:G47) -> 7485
A48: Other Adjustments
A49: Foreign Exchange Rate Effect on Cash and Cash Equivalents | B49: 532 | C49: -458 | D49: -104 | E49: -414 | F49: -232 | G49: 225 | J49: =AVERAGE(B49:G49) -> -75.166667 | K49: =STDEV(B49:G49) -> 386.14734 | L49: =MIN(B49:G49) -> -458 | M49: =MEDIAN(B49:G49) -> -168 | N49: =MAX(B49:G49) -> 532
A50: Cash Flow Net Changes in Cash | B50: 560 | C50: -1920 | D50: -230 | E50: 4603 | F50: -5198 | G50: 8194 | J50: =AVERAGE(B50:G50) -> 1001.5 | K50: =STDEV(B50:G50) -> 4762.0024 | L50: =MIN(B50:G50) -> -5198 | M50: =MEDIAN(B50:G50) -> 165 | N50: =MAX(B50:G50) -> 8194

Sheet D2_Fig_OpCFs_FinCFs_InvCFs
A1: Insert any figures requested in the deliverable instructions here:

Sheet D2_StatmentofCFsCommonSize
A1: Line Items | B1: Year(t=0) | C1: Year(t=-1) | D1: Year(t=-2) | E1: Year(t=-3) | F1: Year(t=-4) | G1: Year(t=-5)
B2: 2025 | C2: 2024 | D2: 2023 | E2: 2022 | F2: 2021 | G2: 2020
A3: Operating Activities
A4: Net Income (Loss) from Continuing Operations | B4: =D1_StatmentofCFs!B4/D1_IncomeStatment!B$9 -> -0.043584828 | C4: =D1_StatmentofCFs!C4/D1_IncomeStatment!C$9 -> 0.031860837 | D4: =D1_StatmentofCFs!D4/D1_IncomeStatment!D$9 -> 0.024569927 | E4: =D1_StatmentofCFs!E4/D1_IncomeStatment!E$9 -> -0.013615341 | F4: =D1_StatmentofCFs!F4/D1_IncomeStatment!F$9 -> 0.13136181 | G4: =D1_StatmentofCFs!G4/D1_IncomeStatment!G$9 -> -0.010035865
A5: Depreciation and Amortization | B5: =D1_StatmentofCFs!B5/D1_IncomeStatment!B$9 -> 0.041833318 | C5: =D1_StatmentofCFs!C5/D1_IncomeStatment!C$9 -> 0.040904472 | D5: =D1_StatmentofCFs!D5/D1_IncomeStatment!D$9 -> 0.043645816 | E5: =D1_StatmentofCFs!E5/D1_IncomeStatment!E$9 -> 0.048349646 | F5: =D1_StatmentofCFs!F5/D1_IncomeStatment!F$9 -> 0.053674243 | G5: =D1_StatmentofCFs!G5/D1_IncomeStatment!G$9 -> 0.068827471
A6: Depreciation and Tooling Amortization | B6: =D1_StatmentofCFs!B6/D1_IncomeStatment!B$9 -> 0 | C6: =D1_StatmentofCFs!C6/D1_IncomeStatment!C$9 -> 0 | D6: =D1_StatmentofCFs!D6/D1_IncomeStatment!D$9 -> 0 | E6: =D1_StatmentofCFs!E6/D1_IncomeStatment!E$9 -> 0.048349646 | F6: =D1_StatmentofCFs!F6/D1_IncomeStatment!F$9 -> 0 | G6: =D1_StatmentofCFs!G6/D1_IncomeStatment!G$9 -> 0
A7: Other Amortization | B7: =D1_StatmentofCFs!B7/D1_IncomeStatment!B$9 -> -0.0098202032 | C7: =D1_StatmentofCFs!C7/D1_IncomeStatment!C$9 -> -0.0091895866 | D7: =D1_StatmentofCFs!D7/D1_IncomeStatment!D$9 -> -0.0066234938 | E7: =D1_StatmentofCFs!E7/D1_IncomeStatment!E$9 -> -0.0072695293 | F7: =D1_StatmentofCFs!F7/D1_IncomeStatment!F$9 -> -0.0099603201 | G7: =D1_StatmentofCFs!G7/D1_IncomeStatment!G$9 -> -0.010177437
A8: Held-for-sale Impairment Charges | B8: =D1_StatmentofCFs!B8/D1_IncomeStatment!B$9 -> 0 | C8: =D1_StatmentofCFs!C8/D1_IncomeStatment!C$9 -> 0 | D8: =D1_StatmentofCFs!D8/D1_IncomeStatment!D$9 -> 0 | E8: =D1_StatmentofCFs!E8/D1_IncomeStatment!E$9 -> 0 | F8: =D1_StatmentofCFs!F8/D1_IncomeStatment!F$9 -> 0 | G8: =D1_StatmentofCFs!G8/D1_IncomeStatment!G$9 -> 0.00018089725
A9: Net Gain/loss on Changes in Investments in Affiliates | B9: =D1_StatmentofCFs!B9/D1_IncomeStatment!B$9 -> 0 | C9: =D1_StatmentofCFs!C9/D1_IncomeStatment!C$9 -> 0 | D9: =D1_StatmentofCFs!D9/D1_IncomeStatment!D$9 -> 0 | E9: =D1_StatmentofCFs!E9/D1_IncomeStatment!E$9 -> 0 | F9: =D1_StatmentofCFs!F9/D1_IncomeStatment!F$9 -> -0.0026991147 | G9: =D1_StatmentofCFs!G9/D1_IncomeStatment!G$9 -> -0.027103127
A10: EV asset impairment/program Cancellation asset write-downs | B10: =D1_StatmentofCFs!B10/D1_IncomeStatment!B$9 -> 0.050382609 | C10: =D1_StatmentofCFs!C10/D1_IncomeStatment!C$9 -> 0 | D10: =D1_StatmentofCFs!D10/D1_IncomeStatment!D$9 -> 0 | E10: =D1_StatmentofCFs!E10/D1_IncomeStatment!E$9 -> 0 | F10: =D1_StatmentofCFs!F10/D1_IncomeStatment!F$9 -> 0 | G10: =D1_StatmentofCFs!G10/D1_IncomeStatment!G$9 -> 0
A11: Brazil Manufacturing Exit Non-cash Charges (excluding Accelerated Depreciation | B11: =D1_StatmentofCFs!B11/D1_IncomeStatment!B$9 -> 0 | C11: =D1_StatmentofCFs!C11/D1_IncomeStatment!C$9 -> 0 | D11: =D1_StatmentofCFs!D11/D1_IncomeStatment!D$9 -> 0 | E11: =D1_StatmentofCFs!E11/D1_IncomeStatment!E$9 -> 0 | F11: =D1_StatmentofCFs!F11/D1_IncomeStatment!F$9 -> 0 | G11: =D1_StatmentofCFs!G11/D1_IncomeStatment!G$9 -> 0.0091156484
A12: Net Losses/(Earnings) from Equity Investments in Excess of Dividends Remitted | B12: =D1_StatmentofCFs!B12/D1_IncomeStatment!B$9 -> 0 | C12: =D1_StatmentofCFs!C12/D1_IncomeStatment!C$9 -> 0 | D12: =D1_StatmentofCFs!D12/D1_IncomeStatment!D$9 -> 0 | E12: =D1_StatmentofCFs!E12/D1_IncomeStatment!E$9 -> 0 | F12: =D1_StatmentofCFs!F12/D1_IncomeStatment!F$9 -> 0.0008508079 | G12: =D1_StatmentofCFs!G12/D1_IncomeStatment!G$9 -> 0.0010224627
A13: Equity Method Investment (Earnings)/Losses and Impairments in Excess of Dividends Received | B13: =D1_StatmentofCFs!B13/D1_IncomeStatment!B$9 -> 0.01907437 | C13: =D1_StatmentofCFs!C13/D1_IncomeStatment!C$9 -> -0.0015514184 | D13: =D1_StatmentofCFs!D13/D1_IncomeStatment!D$9 -> -0.00018729674 | E13: =D1_StatmentofCFs!E13/D1_IncomeStatment!E$9 -> 0.021030388 | F13: =D1_StatmentofCFs!F13/D1_IncomeStatment!F$9 -> 0 | G13: =D1_StatmentofCFs!G13/D1_IncomeStatment!G$9 -> 0
A14: Stock Compensation | B14: =D1_StatmentofCFs!B14/D1_IncomeStatment!B$9 -> 0.0027233843 | C14: =D1_StatmentofCFs!C14/D1_IncomeStatment!C$9 -> 0.0027622816 | D14: =D1_StatmentofCFs!D14/D1_IncomeStatment!D$9 -> 0.002610803 | E14: =D1_StatmentofCFs!E14/D1_IncomeStatment!E$9 -> 0.0021258154 | F14: =D1_StatmentofCFs!F14/D1_IncomeStatment!F$9 -> 0.002237038 | G14: =D1_StatmentofCFs!G14/D1_IncomeStatment!G$9 -> 0.0015651545
A15: Provision for Credit/insurance Losses | B15: =D1_StatmentofCFs!B15/D1_IncomeStatment!B$9 -> 0.003289421 | C15: =D1_StatmentofCFs!C15/D1_IncomeStatment!C$9 -> 0.0031082425 | D15: =D1_StatmentofCFs!D15/D1_IncomeStatment!D$9 -> 0.0024859386 | E15: =D1_StatmentofCFs!E15/D1_IncomeStatment!E$9 -> 0.00029103425 | F15: =D1_StatmentofCFs!F15/D1_IncomeStatment!F$9 -> 0 | G15: =D1_StatmentofCFs!G15/D1_IncomeStatment!G$9 -> 0
... A50: Cash Flow Net Changes in Cash | B50: =D1_StatmentofCFs!B50/D1_IncomeStatment!B$9 -> 0.0029903827 | C50: =D1_StatmentofCFs!C50/D1_IncomeStatment!C$9 -> -0.010378827 | D50: =D1_StatmentofCFs!D50/D1_IncomeStatment!D$9 -> -0.0013054015 | E50: =D1_StatmentofCFs!E50/D1_IncomeStatment!E$9 -> 0.029122405 | F50: =D1_StatmentofCFs!F50/D1_IncomeStatment!F$9 -> -0.038124995 | G50: =D1_StatmentofCFs!G50/D1_IncomeStatment!G$9 -> 0.064446612

Sheet D3_Analysis of CF Statement
A1: *Please use calculations as shown in the slides and/or textbook (please do not use the internet)
A3: CF Ratios | B3: 2025 | C3: 2024 | D3: 2023 | E3: 2022 | F3: 2021 | G3: 2020
A4: Cash Flow to Revenue | B4: =D1_StatmentofCFs!B27/D1_IncomeStatment!B9 -> 0.11364522 | C4: =D1_StatmentofCFs!C27/D1_IncomeStatment!C9 -> 0.083371173 | D4: =D1_StatmentofCFs!D27/D1_IncomeStatment!D9 -> 0.084669478 | E4: =D1_StatmentofCFs!E27/D1_IncomeStatment!E9 -> 0.043357776 | F4: =D1_StatmentofCFs!F27/D1_IncomeStatment!F9 -> 0.11579055 | G4: =D1_StatmentofCFs!G27/D1_IncomeStatment!G9 -> 0.19087806
A5: Cash Return on Assets | B5: =D1_StatmentofCFs!B27/(SUM('D1_Balance Sheet'!$B$19:$G$19)/6) -> 0.07844231 | C5: =D1_StatmentofCFs!C27/(SUM('D1_Balance Sheet'!$B$19:$G$19)/6) -> 0.056846901 | D5: =D1_StatmentofCFs!D27/(SUM('D1_Balance Sheet'!$B$19:$G$19)/6) -> 0.054985545 | E5: =D1_StatmentofCFs!E27/(SUM('D1_Balance Sheet'!$B$19:$G$19)/6) -> 0.025259146 | F5: =D1_StatmentofCFs!F27/(SUM('D1_Balance Sheet'!$B$19:$G$19)/6) -> 0.058188551 | G5: =D1_StatmentofCFs!G27/(SUM('D1_Balance Sheet'!$B$19:$G$19)/6) -> 0.089451951
A6: Cash Return on Equity | B6: =D1_StatmentofCFs!B27/(SUM('D1_Balance Sheet'!$B$42:$G$42)/6) -> 0.51904996 | C6: =D1_StatmentofCFs!C27/(SUM('D1_Balance Sheet'!$B$42:$G$42)/6) -> 0.37615391 | D6: =D1_StatmentofCFs!D27/(SUM('D1_Balance Sheet'!$B$42:$G$42)/6) -> 0.36383739 | E6: =D1_StatmentofCFs!E27/(SUM('D1_Balance Sheet'!$B$42:$G$42)/6) -> 0.16713887 | F6: =D1_StatmentofCFs!F27/(SUM('D1_Balance Sheet'!$B$42:$G$42)/6) -> 0.38503156 | G6: =D1_StatmentofCFs!G27/(SUM('D1_Balance Sheet'!$B$42:$G$42)/6) -> 0.59190036
A7: Cash to Income | B7: =D1_StatmentofCFs!B27/D1_IncomeStatment!B28 -> -2.3210819 | C7: =D1_StatmentofCFs!C27/D1_IncomeStatment!C28 -> 2.9551638 | D7: =D1_StatmentofCFs!D27/D1_IncomeStatment!D28 -> 2.7332356 | E7: =D1_StatmentofCFs!E27/D1_IncomeStatment!E28 -> 1.0919375 | F7: =D1_StatmentofCFs!F27/D1_IncomeStatment!F28 -> 3.4903825 | G7: =D1_StatmentofCFs!G27/D1_IncomeStatment!G28 -> -5.5056715
A8: Cash Flow per Share | B8: =D1_StatmentofCFs!$B$27/3979 -> 5.34858 | C8: =D1_StatmentofCFs!$B$27/3978 -> 5.3499246 | D8: =D1_StatmentofCFs!$B$27/3998 -> 5.3231616 | E8: =D1_StatmentofCFs!$B$27/4014 -> 5.3019432 | F8: =D1_StatmentofCFs!$B$27/3991 -> 5.3324981 | G8: =D1_StatmentofCFs!$B$27/3973 -> 5.3566574
A9: Debt Coverage | B9: =D1_StatmentofCFs!B27/('D1_Balance Sheet'!B23+'D1_Balance Sheet'!B21+'D1_Balance Sheet'!B28+'D1_Balance Sheet'!B32) -> 0.13029583 | C9: =D1_StatmentofCFs!C27/('D1_Balance Sheet'!C23+'D1_Balance Sheet'!C21+'D1_Balance Sheet'!C28+'D1_Balance Sheet'!C32) -> 0.097292489 | D9: =D1_StatmentofCFs!D27/('D1_Balance Sheet'!D23+'D1_Balance Sheet'!D21+'D1_Balance Sheet'!D28+'D1_Balance Sheet'!D32) -> 0.099965825 | E9: =D1_StatmentofCFs!E27/('D1_Balance Sheet'!E23+'D1_Balance Sheet'!E21+'D1_Balance Sheet'!E28+'D1_Balance Sheet'!E32) -> 0.049313156 | F9: =D1_StatmentofCFs!F27/('D1_Balance Sheet'!F23+'D1_Balance Sheet'!F21+'D1_Balance Sheet'!F28+'D1_Balance Sheet'!F32) -> 0.11432234 | G9: =D1_StatmentofCFs!G27/('D1_Balance Sheet'!G23+'D1_Balance Sheet'!G21+'D1_Balance Sheet'!G28+'D1_Balance Sheet'!G32) -> 0.15010143
A10: Interest Coverage | B10: =(D1_StatmentofCFs!B27+ABS(D3_StatementofCFsDirectMethod!C7)+ABS(D3_StatementofCFsDirectMethod!C8)/ABS(D3_StatementofCFsDirectMethod!C7)) -> 22582.478 | C10: =(D1_StatmentofCFs!C27+ABS(D3_StatementofCFsDirectMethod!D7)+ABS(D3_StatementofCFsDirectMethod!D8)/ABS(D3_StatementofCFsDirectMethod!D7)) -> 16524.107 | D10: =(D1_StatmentofCFs!D27+ABS(D3_StatementofCFsDirectMethod!E7)+ABS(D3_StatementofCFsDirectMethod!E8)/ABS(D3_StatementofCFsDirectMethod!E7)) -> 16218.79 | E10: =(D1_StatmentofCFs!E27+ABS(D3_StatementofCFsDirectMethod!F7)+ABS(D3_StatementofCFsDirectMethod!F8)/ABS(D3_StatementofCFsDirectMethod!F7)) -> 8053.6675 | F10: =(D1_StatmentofCFs!F27+ABS(D3_StatementofCFsDirectMethod!G7)+ABS(D3_StatementofCFsDirectMethod!G8)/ABS(D3_StatementofCFsDirectMethod!G7)) -> 17687.299 | G10: =(D1_StatmentofCFs!G27+ABS(D3_StatementofCFsDirectMethod!H7)+ABS(D3_StatementofCFsDirectMethod!H8)/ABS(D3_StatementofCFsDirectMethod!H7)) -> 25669.301
A11: Reinvestment | B11: =D1_StatmentofCFs!B27/ABS((D1_StatmentofCFs!B29+D1_StatmentofCFs!B35)) -> 0.32963663 | C11: =D1_StatmentofCFs!C27/ABS((D1_StatmentofCFs!C29+D1_StatmentofCFs!C35)) -> 0.22546927 | D11: =D1_StatmentofCFs!D27/ABS((D1_StatmentofCFs!D29+D1_StatmentofCFs!D35)) -> 0.23777115 | E11: =D1_StatmentofCFs!E27/ABS((D1_StatmentofCFs!E29+D1_StatmentofCFs!E35)) -> 0.13078494 | F11: =D1_StatmentofCFs!F27/ABS((D1_StatmentofCFs!F29+D1_StatmentofCFs!F35)) -> 0.28910742 | G11: =D1_StatmentofCFs!G27/ABS((D1_StatmentofCFs!G29+D1_StatmentofCFs!G35)) -> 0.39370245
A12: Debt Payment | B12: =D1_StatmentofCFs!B27/ABS(D1_StatmentofCFs!B41) -> 0.42307616 | C12: =D1_StatmentofCFs!C27/ABS(D1_StatmentofCFs!C41) -> 0.33763135 | D12: =D1_StatmentofCFs!D27/ABS(D1_StatmentofCFs!D41) -> 0.35548672 | E12: =D1_StatmentofCFs!E27/ABS(D1_StatmentofCFs!E41) -> 0.15010404 | F12: =D1_StatmentofCFs!F27/ABS(D1_StatmentofCFs!F41) -> 0.29146666 | G12: =D1_StatmentofCFs!G27/ABS(D1_StatmentofCFs!G41) -> 0.40104769
A13: Dividend Payment | B13: =D1_StatmentofCFs!B27/ABS(D1_StatmentofCFs!B45) -> 7.1201071 | C13: =D1_StatmentofCFs!C27/ABS(D1_StatmentofCFs!C45) -> 4.94644 | D13: =D1_StatmentofCFs!D27/ABS(D1_StatmentofCFs!D45) -> 2.9865866 | E13: =D1_StatmentofCFs!E27/ABS(D1_StatmentofCFs!E45) -> 3.4111498 | F13: =D1_StatmentofCFs!F27/ABS(D1_StatmentofCFs!F45) -> 39.173697 | G13: =D1_StatmentofCFs!G27/ABS(D1_StatmentofCFs!G45) -> 40.719799
A14: Investing and financing | B14: =D1_StatmentofCFs!B27/ABS(SUM(D1_StatmentofCFs!B29,D1_StatmentofCFs!B32:B33,D1_StatmentofCFs!B35,D1_StatmentofCFs!B38,D1_StatmentofCFs!B41,D1_StatmentofCFs!B45:B46)) -> 0.16474559 | C14: =D1_StatmentofCFs!C27/ABS(SUM(D1_StatmentofCFs!C29,D1_StatmentofCFs!C32:C33,D1_StatmentofCFs!C35,D1_StatmentofCFs!C38,D1_StatmentofCFs!C41,D1_StatmentofCFs!C45:C46)) -> 0.11647032 | D14: =D1_StatmentofCFs!D27/ABS(SUM(D1_StatmentofCFs!D29,D1_StatmentofCFs!D32:D33,D1_StatmentofCFs!D35,D1_StatmentofCFs!D38,D1_StatmentofCFs!D41,D1_StatmentofCFs!D45:D46)) -> 0.12287999 | E14: =D1_StatmentofCFs!E27/ABS(SUM(D1_StatmentofCFs!E29,D1_StatmentofCFs!E32:E33,D1_StatmentofCFs!E35,D1_StatmentofCFs!E38,D1_StatmentofCFs!E41,D1_StatmentofCFs!E45:E46)) -> 0.057862474 | F14: =D1_StatmentofCFs!F27/ABS(SUM(D1_StatmentofCFs!F29,D1_StatmentofCFs!F32:F33,D1_StatmentofCFs!F35,D1_StatmentofCFs!F38,D1_StatmentofCFs!F41,D1_StatmentofCFs!F45:F46)) -> 0.11515121 | G14: =D1_StatmentofCFs!G27/ABS(SUM(D1_StatmentofCFs!G29,D1_StatmentofCFs!G32:G33,D1_StatmentofCFs!G35,D1_StatmentofCFs!G38,D1_StatmentofCFs!G41,D1_StatmentofCFs!G45:G46)) -> 0.14899195

Sheet D3_StatementofCFsHorizontal
A1: Line Items | B1: 2025 | C1: 2024 | D1: 2023 | E1: 2022 | F1: 2021 | G1: 2020
J2: Year | K2: 2020 | L2: 2021 | M2: 2022 | N2: 2023 | O2: 2024 | P2: 2025
A3: Cash Flow from Operating Activities | B3: =(D1_StatmentofCFs!B27-D1_StatmentofCFs!C27)/ABS(D1_StatmentofCFs!C27) -> 0.37988718 | C3: =(D1_StatmentofCFs!C27-D1_StatmentofCFs!D27)/ABS(D1_StatmentofCFs!D27) -> 0.033851723 | D3: =(D1_StatmentofCFs!D27-D1_StatmentofCFs!E27)/ABS(D1_StatmentofCFs!E27) -> 1.1768569 | E3: =(D1_StatmentofCFs!E27-D1_StatmentofCFs!F27)/ABS(D1_StatmentofCFs!F27) -> -0.56590866 | F3: =(D1_StatmentofCFs!F27-D1_StatmentofCFs!G27)/ABS(D1_StatmentofCFs!G27) -> -0.34949936 | G3: - | J3: CF - Operating | K3: =D1_StatmentofCFs!G27 -> 24269 | L3: =D1_StatmentofCFs!F27 -> 15787 | M3: =D1_StatmentofCFs!E27 -> 6853 | N3: =D1_StatmentofCFs!D27 -> 14918 | O3: =D1_StatmentofCFs!C27 -> 15423 | P3: =D1_StatmentofCFs!B27 -> 21282
A4: Cash Flow from Investing Activities | B4: =(D1_StatmentofCFs!B39-D1_StatmentofCFs!C39)/ABS(D1_StatmentofCFs!C39) -> 0.25937628 | C4: =(D1_StatmentofCFs!C39-D1_StatmentofCFs!D39)/ABS(D1_StatmentofCFs!D39) -> -0.38245972 | D4: =(D1_StatmentofCFs!D39-D1_StatmentofCFs!E39)/ABS(D1_StatmentofCFs!E39) -> -3.0552105 | E4: =(D1_StatmentofCFs!E39-D1_StatmentofCFs!F39)/ABS(D1_StatmentofCFs!F39) -> -2.5836066 | F4: =(D1_StatmentofCFs!F39-D1_StatmentofCFs!G39)/ABS(D1_StatmentofCFs!G39) -> 1.1474617 | G4: - | J4: % Change - Operating | K4: 0 | L4: =F3 -> -0.34949936 | M4: =E3 -> -0.56590866 | N4: =D3 -> 1.1768569 | O4: =C3 -> 0.033851723 | P4: =B3 -> 0.37988718
A5: Cash Flow from Financing Activities | B5: =(D1_StatmentofCFs!B47-D1_StatmentofCFs!C47)/ABS(D1_StatmentofCFs!C47) -> -1.4281897 | C5: =(D1_StatmentofCFs!C47-D1_StatmentofCFs!D47)/ABS(D1_StatmentofCFs!D47) -> 1.8966718 | D5: =(D1_StatmentofCFs!D47-D1_StatmentofCFs!E47)/ABS(D1_StatmentofCFs!E47) -> 0.029072083 | E5: =(D1_StatmentofCFs!E47-D1_StatmentofCFs!F47)/ABS(D1_StatmentofCFs!F47) -> 1.1068602 | F5: =(D1_StatmentofCFs!F47-D1_StatmentofCFs!G47)/ABS(D1_StatmentofCFs!G47) -> -11.150324 | G5: -
J6: Year | K6: 2020 | L6: 2021 | M6: 2022 | N6: 2023 | O6: 2024 | P6: 2025
J7: CF - Investing | K7: =D1_StatmentofCFs!G39 -> -18615 | L7: =D1_StatmentofCFs!F39 -> 2745 | M7: =D1_StatmentofCFs!E39 -> -4347 | N7: =D1_StatmentofCFs!D39 -> -17628 | O7: =D1_StatmentofCFs!C39 -> -24370 | P7: =D1_StatmentofCFs!B39 -> -18049
J8: % Change - Investing | K8: 0 | L8: =F4 -> 1.1474617 | M8: =E4 -> -2.5836066 | N8: =D4 -> -3.0552105 | O8: =C4 -> -0.38245972 | P8: =B4 -> 0.25937628
J10: Year | K10: 2020 | L10: 2021 | M10: 2022 | N10: 2023 | O10: 2024 | P10: 2025
J11: CF - Financing | K11: =D1_StatmentofCFs!G47 -> 2315 | L11: =D1_StatmentofCFs!F47 -> -23498 | M11: =D1_StatmentofCFs!E47 -> 2511 | N11: =D1_StatmentofCFs!D47 -> 2584 | O11: =D1_StatmentofCFs!C47 -> 7485 | P11: =D1_StatmentofCFs!B47 -> -3205
J12: % Change - Financing | K12: 0 | L12: =F5 -> -11.150324 | M12: =E5 -> 1.1068602 | N12: =D5 -> 0.029072083 | O12: =C5 -> 1.8966718 | P12: =B5 -> -1.4281897

Sheet D3_StatementofCFsDirectMethod
C1: 2025 | D1: 2024 | E1: 2023 | F1: 2022 | G1: 2021 | H1: 2020 | I1: 2019
A2: Cash Flow from Operating Activities:
B3: Cash received from customers | C3: =C19 -> 184476 | D3: =D19 -> 182495 | E3: =E19 -> 173571 | F3: =F19 -> 156874 | G3: =G19 -> 135200 | H3: =H19 -> 127081 | I3: =I19 -> 155084
B4: Cash paid to suppliers | C4: =C26 -> -139908 | D4: =D26 -> -149982 | E4: =E26 -> -141940 | F4: =F26 -> -128312 | G4: =G26 -> -115828 | H4: =H26 -> -106006 | I4: =I26 -> -129227
B5: Cash paid to employees | C5: N/A | D5: N/A | E5: N/A | F5: N/A | G5: N/A | H5: N/A | I5: N/A
B6: Cash paid for other operating expenses | C6: N/A | D6: N/A | E6: N/A | F6: N/A | G6: N/A | H6: N/A | I6: N/A
B7: Cash paid for interest | C7: =C42 -> -1300 | D7: =D42 -> -1100 | E7: =E42 -> -1300 | F7: =F42 -> -1200 | G7: =G42 -> -1900 | H7: =H42 -> -1400 | I7: =I42 -> -1000
B8: Cash paid for income tax | C8: =C48 -> -622 | D8: =D48 -> -1218 | E8: =E48 -> -1027 | F8: =F48 -> -801 | G8: =G48 -> -568 | H8: =H48 -> -421 | I8: =I48 -> -599
A9: Net Cash provided from operating activities | C9: =SUM(C3:C8) -> 42646 | D9: =SUM(D3:D8) -> 30195 | E9: =SUM(E3:E8) -> 29304 | F9: =SUM(F3:F8) -> 26561 | G9: =SUM(G3:G8) -> 16904 | H9: =SUM(H3:H8) -> 19254 | I9: =SUM(I3:I8) -> 24258
A14: Operating Activities
A15: Cash Received from Customers
B16: Beginning Accounts Receivable
B17: Plus: Revenue | C17: =D1_IncomeStatment!B9 -> 187267 | D17: =D1_IncomeStatment!C9 -> 184992 | E17: =D1_IncomeStatment!D9 -> 176191 | F17: =D1_IncomeStatment!E9 -> 158057 | G17: =D1_IncomeStatment!F9 -> 136341 | H17: =D1_IncomeStatment!G9 -> 127144 | I17: 155900
B18: Subtract: Ending Accounts Receivable* | C18: =D1_StatmentofCFs!B22 -> -2791 | D18: =D1_StatmentofCFs!C22 -> -2497 | E18: =D1_StatmentofCFs!D22 -> -2620 | F18: =D1_StatmentofCFs!E22 -> -1183 | G18: =D1_StatmentofCFs!F22 -> -1141 | H18: =D1_StatmentofCFs!G22 -> -63 | I18: -816 | J18: *Decrease(Increase) in AR found in Statement of Cash Flow
B19: Cash Received from Customers | C19: =C16+C17+C18 -> 184476 | D19: =D16+D17+D18 -> 182495 | E19: =E16+E17+E18 -> 173571 | F19: =F16+F17+F18 -> 156874 | G19: =G16+G17+G18 -> 135200 | H19: =H16+H17+H18 -> 127081 | I19: =I16+I17+I18 -> 155084
A21: Cash Paid to Suppliers
B22: Cost of Goods Sold | C22: =D1_IncomeStatment!B11 -> -150550 | D22: =D1_IncomeStatment!C11 -> -158434 | E22: =D1_IncomeStatment!D11 -> -150550 | F22: =D1_IncomeStatment!E11 -> -134397 | G22: =D1_IncomeStatment!F11 -> -114651 | H22: =D1_IncomeStatment!G11 -> -112752 | I22: -134693
B23: Add (Subtract): Increase (Decrease) in Inventory | C23: 539 | D23: 27 | E23: -1219 | F23: -1183 | G23: -1141 | H23: -63 | I23: 206
B24: Equals purchases from Suppliers | C24: =C22+C23 -> -150011 | D24: =D22+D23 -> -158407 | E24: =E22+E23 -> -151769 | F24: =F22+F23 -> -135580 | G24: =G22+G23 -> -115792 | H24: =H22+H23 -> -112815 | I24: =I22+I23 -> -134487
B25: Subtract (Add): Increases (Decreases) in Accounts Payable | C25: =D1_StatmentofCFs!B25 -> 10103 | D25: =D1_StatmentofCFs!C25 -> 8425 | E25: =D1_StatmentofCFs!D25 -> 9829 | F25: =D1_StatmentofCFs!E25 -> 7268 | G25: =D1_StatmentofCFs!F25 -> -36 | H25: =D1_StatmentofCFs!G25 -> 6809 | I25: 5260
B26: Cash Paid to Suppliers | C26: =C24+C25 -> -139908 | D26: =D24+D25 -> -149982 | E26: =E24+E25 -> -141940 | F26: =F24+F25 -> -128312 | G26: =G24+G25 -> -115828 | H26: =H24+H25 -> -106006 | I26: =I24+I25 -> -129227
A28: Cash Paid to Employees
B29: Salary and Wage Expense
B30: Subtract (Add): Increases (Decreases) in Salary and Wages Payable
B31: Cash Paid to Employees | C31: N/A | D31: N/A | E31: N/A | F31: N/A | G31: N/A | H31: N/A | I31: N/A
A33: Cash Paid for Other Operating Expenses
B34: Other Operating Expenses
B35: Subtract (Add): Decreases (Increases) in Prepaid Expenses
B36: Subtract (Add): Increases in Accrued Liabilities
B37: Cash Paid for other operating expenses | C37: N/A | D37: N/A | E37: N/A | F37: N/A | G37: N/A | H37: N/A | I37: N/A
A39: Cash Paid for Interest
B40: Interest Expense
B41: Add (Subtract): Decreases (Increases) in Interest payables
B42: Cash Paid for Interest | C42: -1300 | D42: -1100 | E42: -1300 | F42: -1200 | G42: -1900 | H42: -1400 | I42: -1000 | J42: *Cash paid for interest found in Notes to the Financial Statements - Debt and Commitments
J43: (Note 18 on 2025 10-K, Note 19 on 2022 10-K, Note 20 on 2019 10-K)
A45: Cash paid for Income Taxes
B46: Income tax expens
B47: Subtract (Add): Increases (decreases) in income tax payables
B48: Cash paid for income taxes | C48: -622 | D48: -1218 | E48: -1027 | F48: -801 | G48: -568 | H48: -421 | I48: -599 | J48: *Cash paid for income taxes found in Notes to the Financial Statements - Note 7 - Income Taxes on 10-K

Sheet D1_StockholdersEq t=0
B1: Total | C1: Total (excl NCI) | D1: Capital Stock | E1: Cap. in Excess of Par Value | F1: Retained Earnings/(Accum Deficit) | G1: Accum Other Comprehensive Income/(Loss) | H1: Treasury Stock | I1: Equity Attr to Noncontrolling Interests
A2: Consolidated Statement of Equity - Year Ended Dec. 31, 2025 ($ in Millions)
A3: Beginning Balance at Dec. 31, 2024 | B3: 44858 | C3: 44835 | D3: 42 | E3: 23502 | F3: 33740 | G3: -9639 | H3: -2810 | I3: 23
A4: Net income/(loss) | B4: -8162 | C4: -8182 | F4: -8182 | I4: 20
A5: Other comprehensive income/(loss), net of tax | B5: 1928 | C5: 1929 | G5: 1929 | I5: -1
A6: Common stock issued | B6: 420 | C6: 420 | E6: 420
A7: Dividend and dividend equivalents declared | B7: -3064 | C7: -3050 | F7: -3050 | I7: -14
A8: Ending Balance at Dec. 31, 2025 | B8: 35980 | C8: 35952 | D8: 42 | E8: 23922 | F8: 22508 | G8: -7710 | H8: -2810 | I8: 28

Sheet D1_StockholderEq t=-1
B1: Total | C1: Total (excl NCI) | D1: Capital Stock | E1: Cap. in Excess of Par Value | F1: Retained Earnings/(Accum Deficit) | G1: Accum Other Comprehensive Income/(Loss) | H1: Treasury Stock | I1: Equity Attr to Noncontrolling Interests
A2: Consolidated Statement of Equity - Year Ended Dec. 31, 2024 ($ in Millions)
A3: Beginning Balance at Dec. 31, 2023 | B3: 42798 | C3: 42773 | D3: 42 | E3: 23128 | F3: 31029 | G3: -9042 | H3: -2384 | I3: 25
A4: Net income/(loss) | B4: 5894 | C4: 5879 | F4: 5879 | I4: 15
A5: Other comprehensive income/(loss), net of tax | B5: -598 | C5: -597 | G5: -597 | I5: -1
A6: Common stock issued | B6: 374 | C6: 374 | E6: 374
A7: Treasury stock/other | B7: -426 | C7: -426 | H7: -426
A8: Dividend and dividend equivalents declared | B8: -3184 | C8: -3168 | F8: -3168 | I8: -16
A9: Ending Balance at Dec. 31, 2024 | B9: 44858 | C9: 44835 | D9: 42 | E9: 23502 | F9: 33740 | G9: -9639 | H9: -2810 | I9: 23

Sheet D1_StockholderEq t= -2
B1: Total | C1: Total (excl NCI) | D1: Capital Stock | E1: Cap. in Excess of Par Value | F1: Retained Earnings/(Accum Deficit) | G1: Accum Other Comprehensive Income/(Loss) | H1: Treasury Stock | I1: Equity Attr to Noncontrolling Interests
A2: Consolidated Statement of Equity - Year Ended Dec. 31, 2023 ($ in Millions)
A3: Beginning Balance at Dec. 31, 2022 | B3: 43167 | C3: 43242 | D3: 42 | E3: 22832 | F3: 31754 | G3: -9339 | H3: -2047 | I3: -75
A4: Net income/(loss) | B4: 4329 | C4: 4347 | F4: 4347 | I4: -18
A5: Other comprehensive income/(loss), net of tax | B5: 298 | C5: 297 | G5: 297 | I5: 1
A6: Common stock issued | B6: 425 | C6: 425 | E6: 425
A7: Treasury stock/other | B7: -337 | C7: -466 | E7: -129 | H7: -337 | I7: 129
A8: Dividend and dividend equivalents declared | B8: -5084 | C8: -5072 | F8: -5072 | I8: -12
A9: Ending Balance at Dec. 31, 2023 | B9: 42798 | C9: 42773 | D9: 42 | E9: 23128 | F9: 31029 | G9: -9042 | H9: -2384 | I9: 25

Sheet D1_StockholderEq t=-3
B1: Total | C1: Total (excl NCI) | D1: Capital Stock | E1: Cap. in Excess of Par Value | F1: Retained Earnings/(Accum Deficit) | G1: Accum Other Comprehensive Income/(Loss) | H1: Treasury Stock | I1: Equity Attr to Noncontrolling Interests
A2: Consolidated Statement of Equity - Year Ended Dec. 31, 2022 ($ in Millions)
A3: Beginning Balance at Dec. 31, 2021 | B3: 48622 | C3: 48519 | D3: 41 | E3: 22611 | F3: 35769 | G3: -8339 | H3: -1563 | I3: 103
A4: Net income/(loss) | B4: -2152 | C4: -1981 | F4: -1981 | I4: -171
A5: Other comprehensive income/(loss), net of tax | B5: -1004 | C5: -1000 | G5: -1000 | I5: -4
A6: Common stock issued | B6: 222 | C6: 222 | D6: 1 | E6: 221
A7: Treasury stock/other | B7: -477 | C7: -484 | H7: -484 | I7: 7
A8: Dividend and dividend equivalents declared | B8: -2044 | C8: -2034 | F8: -2034 | I8: -10
A9: Ending Balance at Dec. 31, 2022 | B9: 43167 | C9: 43242 | D9: 42 | E9: 22832 | F9: 31754 | G9: -9339 | H9: -2047 | I9: -75

Sheet D1_StockholderEq t=-4
B1: Total | C1: Total (excl NCI) | D1: Capital Stock | E1: Cap. in Excess of Par Value | F1: Retained Earnings/(Accum Deficit) | G1: Accum Other Comprehensive Income/(Loss) | H1: Treasury Stock | I1: Equity Attr to Noncontrolling Interests
A2: Consolidated Statement of Equity - Year Ended Dec. 31, 2021 ($ in Millions)
A3: Beginning Balance at Dec. 31, 2020 | B3: 30811 | C3: 30690 | D3: 41 | E3: 22290 | F3: 18243 | G3: -8294 | H3: -1590 | I3: 121
A4: Cumulative effect adjustment (ASU 2016-02) | B4: -202 | C4: -202 | F4: -202
A5: Net income/(loss) | B5: 17910 | C5: 17937 | F5: 17937 | I5: -27
A6: Other comprehensive income/(loss), net of tax | B6: -41 | C6: -45 | G6: -45 | I6: 4
A7: Common stock issued | B7: 321 | C7: 321 | E7: 321
A8: Treasury stock/other | B8: 32 | C8: 27 | H8: 27 | I8: 5
A9: Dividend and dividend equivalents declared | B9: -411 | C9: -411 | F9: -411
A10: Ending Balance at Dec. 31, 2021 | B10: 48622 | C10: 48519 | D10: 41 | E10: 22611 | F10: 35769 | G10: -8339 | H10: -1563 | I10: 103

Sheet D1_StockholderEq t=-5
B1: Total | C1: Total (excl NCI) | D1: Capital Stock | E1: Cap. in Excess of Par Value | F1: Retained Earnings/(Accum Deficit) | G1: Accum Other Comprehensive Income/(Loss) | H1: Treasury Stock | I1: Equity Attr to Noncontrolling Interests
A2: Consolidated Statement of Equity - Year Ended Dec. 31, 2020 ($ in Millions)
A3: Beginning Balance at Dec. 31, 2019 | B3: 33230 | C3: 33185 | D3: 41 | E3: 22165 | F3: 20320 | G3: -7728 | H3: -1613 | I3: 45
A4: Net income/(loss) | B4: -1276 | C4: -1279 | F4: -1279 | I4: 3
A5: Other comprehensive income/(loss), net of tax | B5: -567 | C5: -566 | G5: -566 | I5: -1
A6: Common stock issued | B6: 125 | C6: 125 | E6: 125
A7: Treasury stock/other | B7: 109 | C7: 23 | H7: 23 | I7: 86
A8: Dividend and dividend equivalents declared | B8: -608 | C8: -596 | F8: -596 | I8: -12
A9: Ending Balance at Dec. 31, 2020 | B9: 30811 | C9: 30690 | D9: 41 | E9: 22290 | F9: 18243 | G9: -8294 | H9: -1590 | I9: 121

Sheet D4_ProfitabilityAnalysis
A1: *Please use calculations as shown in the slides and/or textbook (please do not use the internet)
B2: Year(t=0) | C2: Year(t=-1) | D2: Year(t=-2) | E2: Year(t=-3) | F2: Year(t=-4) | G2: Year(t=-5)
A3: Line Items | B3: 2025 | C3: 2024 | D3: 2023 | E3: 2022 | F3: 2021 | G3: 2020
A4: Revenue ($ Amt) | B4: ='D3_Analysis of Income Statment'!B4 -> 187267 | C4: ='D3_Analysis of Income Statment'!C4 -> 184992 | D4: ='D3_Analysis of Income Statment'!D4 -> 176191 | E4: ='D3_Analysis of Income Statment'!E4 -> 158057 | F4: ='D3_Analysis of Income Statment'!F4 -> 136341 | G4: ='D3_Analysis of Income Statment'!G4 -> 127144
A5: Revenue (%change from Horizontal Analysis) | B5: =D3_ISHorizontalAnalysis!B3 -> 0.012297829 | C5: =D3_ISHorizontalAnalysis!C3 -> 0.049951473 | D5: =D3_ISHorizontalAnalysis!D3 -> 0.11473076 | E5: =D3_ISHorizontalAnalysis!E3 -> 0.15927711 | F5: =D3_ISHorizontalAnalysis!F3 -> 0.072335305 | G5: =D3_ISHorizontalAnalysis!G3 -> -
A7: GrossProfit [EBITDA] ($ Amt) | B7: ='D3_Analysis of Income Statment'!B7 -> -21423 | C7: ='D3_Analysis of Income Statment'!C7 -> -2879 | D7: ='D3_Analysis of Income Statment'!D7 -> -4933 | E7: ='D3_Analysis of Income Statment'!E7 -> -8631 | F7: ='D3_Analysis of Income Statment'!F7 -> 13324 | G7: ='D3_Analysis of Income Statment'!G7 -> -7787
A8: Gross Profit [EBITDA] (%change from Horizontal Analysis) | B8: ='D3_Analysis of Income Statment'!B8 -> -6.4411254 | C8: ='D3_Analysis of Income Statment'!C8 -> 0.41637949 | D8: ='D3_Analysis of Income Statment'!D8 -> 0.42845557 | E8: ='D3_Analysis of Income Statment'!E8 -> -1.6477784 | F8: ='D3_Analysis of Income Statment'!F8 -> 2.7110569 | G8: ='D3_Analysis of Income Statment'!G8 -> -
A10: Operating Income ($ Amt) | B10: ='D3_Analysis of Income Statment'!B10 -> -9169 | C10: ='D3_Analysis of Income Statment'!C10 -> 5219 | D10: ='D3_Analysis of Income Statment'!D10 -> 5458 | E10: ='D3_Analysis of Income Statment'!E10 -> 6276 | F10: ='D3_Analysis of Income Statment'!F10 -> 4523 | G10: ='D3_Analysis of Income Statment'!G10 -> -4408
A11: Operating Income (%change from Horizontal Analysis) | B11: ='D3_Analysis of Income Statment'!B11 -> -2.75685 | C11: ='D3_Analysis of Income Statment'!C11 -> -0.043788934 | D11: ='D3_Analysis of Income Statment'!D11 -> -0.13033779 | E11: ='D3_Analysis of Income Statment'!E11 -> 0.38757462 | F11: ='D3_Analysis of Income Statment'!F11 -> 2.0260889 | G11: ='D3_Analysis of Income Statment'!G11 -> -
A13: Income ($Amt) | B13: ='D3_Analysis of Income Statment'!B13 -> -8182 | C13: ='D3_Analysis of Income Statment'!C13 -> 5879 | D13: ='D3_Analysis of Income Statment'!D13 -> 4347 | E13: ='D3_Analysis of Income Statment'!E13 -> -1981 | F13: ='D3_Analysis of Income Statment'!F13 -> 17937 | G13: ='D3_Analysis of Income Statment'!G13 -> -1279
A14: Income (%change from Horizontal Analysis) | B14: =D3_ISHorizontalAnalysis!B5 -> -2.3917333 | C14: =D3_ISHorizontalAnalysis!C5 -> 0.35242696 | D14: =D3_ISHorizontalAnalysis!D5 -> 3.1943463 | E14: =D3_ISHorizontalAnalysis!E5 -> -1.1104421 | F14: =D3_ISHorizontalAnalysis!F5 -> 15.024238 | G14: =D3_ISHorizontalAnalysis!G5 -> -
B17: Year(t=0) | C17: Year(t=-1) | D17: Year(t=-2) | E17: Year(t=-3) | F17: Year(t=-4) | G17: Year(t=-5)
A18: Profitability Ratios | B18: 2025 | C18: 2024 | D18: 2023 | E18: 2022 | F18: 2021 | G18: 2020
A19: ROE | B19: =D1_IncomeStatment!B26/(SUM('D1_Balance Sheet'!B42:C42)/2) -> -0.20255734 | C19: =D1_IncomeStatment!C26/(SUM('D1_Balance Sheet'!C42:D42)/2) -> 0.13421149 | D19: =D1_IncomeStatment!D26/(SUM('D1_Balance Sheet'!D42:E42)/2) -> 0.10107539 | E19: =D1_IncomeStatment!E26/(SUM('D1_Balance Sheet'!E42:F42)/2) -> -0.043177385 | F19: =D1_IncomeStatment!F26/(SUM('D1_Balance Sheet'!F42:G42)/2) -> 0.45290308 | G19: =D1_IncomeStatment!G26/(('D1_Balance Sheet'!G42+33230)/2) -> -0.040018773
A21: Two factor Disaggregation of ROE
A22: ROA | B22: =D1_IncomeStatment!B26/(SUM('D1_Balance Sheet'!B19:C19)/2) -> -0.02849104 | C22: =D1_IncomeStatment!C26/(SUM('D1_Balance Sheet'!C19:D19)/2) -> 0.021052594 | D22: =D1_IncomeStatment!D26/(SUM('D1_Balance Sheet'!D19:E19)/2) -> 0.016428758 | E22: =D1_IncomeStatment!E26/(SUM('D1_Balance Sheet'!E19:F19)/2) -> -0.0077244165 | F22: =D1_IncomeStatment!F26/(SUM('D1_Balance Sheet'!F19:G19)/2) -> 0.068423181 | G22: =D1_IncomeStatment!G26/(SUM('D1_Balance Sheet'!G19,114047)/2) -> -0.0067084876
A23: Leverage | B23: =(SUM('D1_Balance Sheet'!B19:C19)/2)/(SUM('D1_Balance Sheet'!B42:C42)/2) -> 7.1095102 | C23: =(SUM('D1_Balance Sheet'!C19:D19)/2)/(SUM('D1_Balance Sheet'!C42:D42)/2) -> 6.3750571 | D23: =(SUM('D1_Balance Sheet'!D19:E19)/2)/(SUM('D1_Balance Sheet'!D42:E42)/2) -> 6.1523455 | E23: =(SUM('D1_Balance Sheet'!E19:F19)/2)/(SUM('D1_Balance Sheet'!E42:F42)/2) -> 5.5897277 | F23: =(SUM('D1_Balance Sheet'!F19:G19)/2)/(SUM('D1_Balance Sheet'!F42:G42)/2) -> 6.6191468 | G23: =(SUM('D1_Balance Sheet'!G19,114047)/2)/(SUM('D1_Balance Sheet'!G42,33230)/2) -> 5.9653942
A25: Three factor Disaggregation of ROE
A26: Profit Margin | B26: =D1_IncomeStatment!B26/D1_IncomeStatment!B9 -> -0.043691627 | C26: =D1_IncomeStatment!C26/D1_IncomeStatment!C9 -> 0.031779753 | D26: =D1_IncomeStatment!D26/D1_IncomeStatment!D9 -> 0.024672089 | E26: =D1_IncomeStatment!E26/D1_IncomeStatment!E9 -> -0.012533453 | F26: =D1_IncomeStatment!F26/D1_IncomeStatment!F9 -> 0.13155984 | G26: =D1_IncomeStatment!G26/D1_IncomeStatment!G9 -> -0.01005946
A27: Asset Turnover | B27: =D1_IncomeStatment!B9/(SUM('D1_Balance Sheet'!B19:C19)/2) -> 0.65209382 | C27: =D1_IncomeStatment!C9/(SUM('D1_Balance Sheet'!C19:D19)/2) -> 0.66245304 | D27: =D1_IncomeStatment!D9/(SUM('D1_Balance Sheet'!D19:E19)/2) -> 0.66588434 | E27: =D1_IncomeStatment!E9/(SUM('D1_Balance Sheet'!E19:F19)/2) -> 0.61630394 | F27: =D1_IncomeStatment!F9/(SUM('D1_Balance Sheet'!F19:G19)/2) -> 0.5200917 | G27: =D1_IncomeStatment!G9/(SUM('D1_Balance Sheet'!G19,114047)/2) -> 0.66688346
A28: Leverage | B28: =(SUM('D1_Balance Sheet'!B19:C19)/2)/(SUM('D1_Balance Sheet'!B42:C42)/2) -> 7.1095102 | C28: =(SUM('D1_Balance Sheet'!C19:D19)/2)/(SUM('D1_Balance Sheet'!C42:D42)/2) -> 6.3750571 | D28: =(SUM('D1_Balance Sheet'!D19:E19)/2)/(SUM('D1_Balance Sheet'!D42:E42)/2) -> 6.1523455 | E28: =(SUM('D1_Balance Sheet'!E19:F19)/2)/(SUM('D1_Balance Sheet'!E42:F42)/2) -> 5.5897277 | F28: =(SUM('D1_Balance Sheet'!F19:G19)/2)/(SUM('D1_Balance Sheet'!F42:G42)/2) -> 6.6191468 | G28: =(SUM('D1_Balance Sheet'!G19,114047)/2)/(SUM('D1_Balance Sheet'!G42,33230)/2) -> 5.9653942
A30: Five factor Disaggregation of ROE
A31: Tax Burden | B31: =D1_IncomeStatment!B26/D1_IncomeStatment!B22 -> 0.69163145 | C31: =D1_IncomeStatment!C26/D1_IncomeStatment!C22 -> 0.81280243 | D31: =D1_IncomeStatment!D26/D1_IncomeStatment!D22 -> 1.0957903 | E31: =D1_IncomeStatment!E26/D1_IncomeStatment!E22 -> 0.65683024 | F31: =D1_IncomeStatment!F26/D1_IncomeStatment!F22 -> 1.0088301 | G31: =D1_IncomeStatment!G26/D1_IncomeStatment!G22 -> 1.1460573
A32: Interest Burden | B32: =D1_IncomeStatment!B22/D1_IncomeStatment!B28 -> 1.290217 | C32: =D1_IncomeStatment!C22/D1_IncomeStatment!C28 -> 1.3858977 | D32: =D1_IncomeStatment!D22/D1_IncomeStatment!D28 -> 0.72682301 | E32: =D1_IncomeStatment!E22/D1_IncomeStatment!E28 -> -0.48056087 | F32: =D1_IncomeStatment!F22/D1_IncomeStatment!F28 -> 3.9310192 | G32: =D1_IncomeStatment!G22/D1_IncomeStatment!G28 -> 0.25317604
A33: EBIT Margin | B33: =D1_IncomeStatment!B28/D1_IncomeStatment!B9 -> -0.048962177 | C33: =D1_IncomeStatment!C28/D1_IncomeStatment!C9 -> 0.028212031 | D33: =D1_IncomeStatment!D28/D1_IncomeStatment!D9 -> 0.030977746 | E33: =D1_IncomeStatment!E28/D1_IncomeStatment!E9 -> 0.039707194 | F33: =D1_IncomeStatment!F28/D1_IncomeStatment!F9 -> 0.033174174 | G33: =D1_IncomeStatment!G28/D1_IncomeStatment!G9 -> -0.034669351
A34: Asset Turnover | B34: =D1_IncomeStatment!B9/(SUM('D1_Balance Sheet'!B19:C19)/2) -> 0.65209382 | C34: =D1_IncomeStatment!C9/(SUM('D1_Balance Sheet'!C19:D19)/2) -> 0.66245304 | D34: =D1_IncomeStatment!D9/(SUM('D1_Balance Sheet'!D19:E19)/2) -> 0.66588434 | E34: =D1_IncomeStatment!E9/(SUM('D1_Balance Sheet'!E19:F19)/2) -> 0.61630394 | F34: =D1_IncomeStatment!F9/(SUM('D1_Balance Sheet'!F19:G19)/2) -> 0.5200917 | G34: =D1_IncomeStatment!G9/(SUM('D1_Balance Sheet'!G19,114047)/2) -> 0.66688346
A35: Leverage | B35: =(SUM('D1_Balance Sheet'!B19:C19)/2)/(SUM('D1_Balance Sheet'!B42:C42)/2) -> 7.1095102 | C35: =(SUM('D1_Balance Sheet'!C19:D19)/2)/(SUM('D1_Balance Sheet'!C42:D42)/2) -> 6.3750571 | D35: =(SUM('D1_Balance Sheet'!D19:E19)/2)/(SUM('D1_Balance Sheet'!D42:E42)/2) -> 6.1523455 | E35: =(SUM('D1_Balance Sheet'!E19:F19)/2)/(SUM('D1_Balance Sheet'!E42:F42)/2) -> 5.5897277 | F35: =(SUM('D1_Balance Sheet'!F19:G19)/2)/(SUM('D1_Balance Sheet'!F42:G42)/2) -> 6.6191468 | G35: =(SUM('D1_Balance Sheet'!G19,114047)/2)/(SUM('D1_Balance Sheet'!G42,33230)/2) -> 5.9653942
B38: Year(t=0) | C38: Year(t=-1) | D38: Year(t=-2) | E38: Year(t=-3) | F38: Year(t=-4) | G38: Year(t=-5)
A39: Profit Measures | B39: 2025 | C39: 2024 | D39: 2023 | E39: 2022 | F39: 2021 | G39: 2020
A40: Gross Margin | B40: ='D3_Analysis of Income Statment'!B19 -> 0.19606765 | C40: ='D3_Analysis of Income Statment'!C19 -> 0.14356296 | D40: ='D3_Analysis of Income Statment'!D19 -> 0.14552957 | E40: ='D3_Analysis of Income Statment'!E19 -> 0.14969283 | F40: ='D3_Analysis of Income Statment'!F19 -> 0.15908641 | G40: ='D3_Analysis of Income Statment'!G19 -> 0.11319449
A41: Operating Margin | B41: ='D3_Analysis of Income Statment'!B20 -> -0.048962177 | C41: ='D3_Analysis of Income Statment'!C20 -> 0.028212031 | D41: ='D3_Analysis of Income Statment'!D20 -> 0.030977746 | E41: ='D3_Analysis of Income Statment'!E20 -> 0.039707194 | F41: ='D3_Analysis of Income Statment'!F20 -> 0.033174174 | G41: ='D3_Analysis of Income Statment'!G20 -> -0.034669351
A42: Pre-tax Margin | B42: ='D3_Analysis of Income Statment'!B21 -> -0.063171835 | C42: ='D3_Analysis of Income Statment'!C21 -> 0.039098988 | D42: ='D3_Analysis of Income Statment'!D21 -> 0.022515338 | E42: ='D3_Analysis of Income Statment'!E21 -> -0.019081724 | F42: ='D3_Analysis of Income Statment'!F21 -> 0.13040831 | G42: ='D3_Analysis of Income Statment'!G21 -> -0.0087774492
A43: Profit Margin | B43: ='D3_Analysis of Income Statment'!B22 -> -0.043691627 | C43: ='D3_Analysis of Income Statment'!C22 -> 0.031779753 | D43: ='D3_Analysis of Income Statment'!D22 -> 0.024672089 | E43: ='D3_Analysis of Income Statment'!E22 -> -0.012533453 | F43: ='D3_Analysis of Income Statment'!F22 -> 0.13155984 | G43: ='D3_Analysis of Income Statment'!G22 -> -0.01005946

Sheet D4_Activity Ratios
A1: *Please use calculations as shown in the slides and/or textbook (please do not use the internet)
B2: Year(t=0) | C2: Year(t=-1) | D2: Year(t=-2) | E2: Year(t=-3) | F2: Year(t=-4) | G2: Year(t=-5)
A3: Activity Ratios | B3: 2025 | C3: 2024 | D3: 2023 | E3: 2022 | F3: 2021 | G3: 2020
A4: Working Capital Turnover | B4: =D1_IncomeStatment!B9 / (('D1_Balance Sheet'!B11 - 'D1_Balance Sheet'!B26 + 'D1_Balance Sheet'!C11 - 'D1_Balance Sheet'!C26) / 2) -> 14.288646 | C4: =D1_IncomeStatment!C9 / (('D1_Balance Sheet'!C11 - 'D1_Balance Sheet'!C26 + 'D1_Balance Sheet'!D11 - 'D1_Balance Sheet'!D26) / 2) -> 9.8491681 | D4: =D1_IncomeStatment!D9 / (('D1_Balance Sheet'!D11 - 'D1_Balance Sheet'!D26 + 'D1_Balance Sheet'!E11 - 'D1_Balance Sheet'!E26) / 2) -> 8.9075329 | E4: =D1_IncomeStatment!E9 / (('D1_Balance Sheet'!E11 - 'D1_Balance Sheet'!E26 + 'D1_Balance Sheet'!F11 - 'D1_Balance Sheet'!F26) / 2) -> 8.3453629 | F4: =D1_IncomeStatment!F9 / (('D1_Balance Sheet'!F11 - 'D1_Balance Sheet'!F26 + 'D1_Balance Sheet'!G11 - 'D1_Balance Sheet'!G26) / 2) -> 7.2098041 | I4: Revenue / Average Working Capital
A5: Fixed Asset Turnover | B5: =D1_IncomeStatment!B9 / AVERAGE('D1_Balance Sheet'!B13, 'D1_Balance Sheet'!C13) -> 4.7280095 | C5: =D1_IncomeStatment!C9 / AVERAGE('D1_Balance Sheet'!C13, 'D1_Balance Sheet'!D13) -> 4.4711598 | D5: =D1_IncomeStatment!D9 / AVERAGE('D1_Balance Sheet'!D13, 'D1_Balance Sheet'!E13) -> 4.5127424 | E5: =D1_IncomeStatment!E9 / AVERAGE('D1_Balance Sheet'!E13, 'D1_Balance Sheet'!F13) -> 4.2486157 | F5: =D1_IncomeStatment!F9 / AVERAGE('D1_Balance Sheet'!F13, 'D1_Balance Sheet'!G13) -> 3.6738703 | I5: Revenue / Average Net Fixed Assets
A6: Total Asset Turnover | B6: =D1_IncomeStatment!B9 / AVERAGE('D1_Balance Sheet'!B19, 'D1_Balance Sheet'!C19) -> 0.65209382 | C6: =D1_IncomeStatment!C9 / AVERAGE('D1_Balance Sheet'!C19, 'D1_Balance Sheet'!D19) -> 0.66245304 | D6: =D1_IncomeStatment!D9 / AVERAGE('D1_Balance Sheet'!D19, 'D1_Balance Sheet'!E19) -> 0.66588434 | E6: =D1_IncomeStatment!E9 / AVERAGE('D1_Balance Sheet'!E19, 'D1_Balance Sheet'!F19) -> 0.61630394 | F6: =D1_IncomeStatment!F9 / AVERAGE('D1_Balance Sheet'!F19, 'D1_Balance Sheet'!G19) -> 0.5200917 | I6: Revenue / Average Total Assets
A8: Cash Conversion Cycle:
A9: Inventory Turnover | B9: =ABS(D1_IncomeStatment!B11) / AVERAGE('D1_Balance Sheet'!B7, 'D1_Balance Sheet'!C7) -> 9.9583278 | C9: =ABS(D1_IncomeStatment!C11) / AVERAGE('D1_Balance Sheet'!C7, 'D1_Balance Sheet'!D7) -> 10.354487 | D9: =ABS(D1_IncomeStatment!D11) / AVERAGE('D1_Balance Sheet'!D7, 'D1_Balance Sheet'!E7) -> 10.127476 | E9: =ABS(D1_IncomeStatment!E11) / AVERAGE('D1_Balance Sheet'!E7, 'D1_Balance Sheet'!F7) -> 10.280895 | F9: =ABS(D1_IncomeStatment!F11) / AVERAGE('D1_Balance Sheet'!F7, 'D1_Balance Sheet'!G7) -> 10.025008 | I9: Cost of sales / Average Inventory
A10: Days of Inventory on Hand (DOH) | B10: =365 / B9 -> 36.65274 | C10: =365 / C9 -> 35.25042 | D10: =365 / D9 -> 36.040568 | E10: =365 / E9 -> 35.502746 | F10: =365 / F9 -> 36.40895 | I10: 365 / Inventory Turnover
A12: Receivables Turnover | B12: =D1_IncomeStatment!B9 / AVERAGE('D1_Balance Sheet'!B6, 'D1_Balance Sheet'!C6) -> 12.434315 | C12: =D1_IncomeStatment!C9 / AVERAGE('D1_Balance Sheet'!C6, 'D1_Balance Sheet'!D6) -> 12.201029 | D12: =D1_IncomeStatment!D9 / AVERAGE('D1_Balance Sheet'!D6, 'D1_Balance Sheet'!E6) -> 11.247431 | E12: =D1_IncomeStatment!E9 / AVERAGE('D1_Balance Sheet'!E6, 'D1_Balance Sheet'!F6) -> 11.665154 | F12: =D1_IncomeStatment!F9 / AVERAGE('D1_Balance Sheet'!F6, 'D1_Balance Sheet'!G6) -> 12.764219 | I12: Revenue/ Average Receivables
A13: Days Sales Outstanding (DSO) | B13: =365 / B12 -> 29.354251 | C13: =365 / C12 -> 29.91551 | D13: =365 / D12 -> 32.451856 | E13: =365 / E12 -> 31.289772 | F13: =365 / F12 -> 28.595562 | I13: 365 / Receivables Turnover
A15: Payables Turnover | B15: =(ABS(D1_IncomeStatment!B11) + 'D1_Balance Sheet'!B7 - 'D1_Balance Sheet'!C7) / AVERAGE('D1_Balance Sheet'!B24, 'D1_Balance Sheet'!C24) -> 6.0429741 | C15: =(ABS(D1_IncomeStatment!C11) + 'D1_Balance Sheet'!C7 - 'D1_Balance Sheet'!D7) / AVERAGE('D1_Balance Sheet'!C24, 'D1_Balance Sheet'!D24) -> 6.2942538 | D15: =(ABS(D1_IncomeStatment!D11) + 'D1_Balance Sheet'!D7 - 'D1_Balance Sheet'!E7) / AVERAGE('D1_Balance Sheet'!D24, 'D1_Balance Sheet'!E24) -> 5.8965056 | E15: =(ABS(D1_IncomeStatment!E11) + 'D1_Balance Sheet'!E7 - 'D1_Balance Sheet'!F7) / AVERAGE('D1_Balance Sheet'!E24, 'D1_Balance Sheet'!F24) -> 5.6892856 | F15: =(ABS(D1_IncomeStatment!F11) + 'D1_Balance Sheet'!F7 - 'D1_Balance Sheet'!G7) / AVERAGE('D1_Balance Sheet'!F24, 'D1_Balance Sheet'!G24) -> 5.2031513 | I15: Purchases / Average Trade Payables
A16: Number Days in Payables (DPO) | B16: =365 / B15 -> 60.400722 | C16: =365 / C15 -> 57.9894 | D16: =365 / D15 -> 61.901069 | E16: =365 / E15 -> 64.155683 | F16: =365 / F15 -> 70.149796 | I16: 365 / Payables Turnover
A18: Cash Conversion Cycle | B18: =B10 + B13 - B16 -> 5.6062691 | C18: =C10 + C13 - C16 -> 7.1765297 | D18: =D10 + D13 - D16 -> 6.5913553 | E18: =E10 + E13 - E16 -> 2.6368349 | F18: =F10 + F13 - F16 -> -5.1452839

Sheet D4_CreditRiskAnalysis
A1: *Please use calculations as shown in the slides and/or textbook (please do not use the internet)
B2: Year(t=0) | C2: Year(t=-1) | D2: Year(t=-2) | E2: Year(t=-3) | F2: Year(t=-4) | G2: Year(t=-5)
A3: Liquidity Ratios | B3: 2025 | C3: 2024 | D3: 2023 | E3: 2022 | F3: 2021 | G3: 2020
A4: Current Ratio | B4: ='D1_Balance Sheet'!B11/'D1_Balance Sheet'!B26 -> 1.0748281 | C4: ='D1_Balance Sheet'!C11/'D1_Balance Sheet'!C26 -> 1.1648434 | D4: ='D1_Balance Sheet'!D11/'D1_Balance Sheet'!D26 -> 1.1964917 | E4: ='D1_Balance Sheet'!E11/'D1_Balance Sheet'!E26 -> 1.2024446 | F4: ='D1_Balance Sheet'!F11/'D1_Balance Sheet'!F26 -> 1.2013623 | G4: ='D1_Balance Sheet'!G11/'D1_Balance Sheet'!G26 -> 1.2011688
A5: Quick Ratio | B5: =('D1_Balance Sheet'!B11-'D1_Balance Sheet'!B7)/'D1_Balance Sheet'!B26 -> 0.9417878 | C5: =('D1_Balance Sheet'!C11-'D1_Balance Sheet'!C7)/'D1_Balance Sheet'!C26 -> 1.02493 | D5: =('D1_Balance Sheet'!D11-'D1_Balance Sheet'!D7)/'D1_Balance Sheet'!D26 -> 1.0423417 | E5: =('D1_Balance Sheet'!E11-'D1_Balance Sheet'!E7)/'D1_Balance Sheet'!E26 -> 1.0570892 | F5: =('D1_Balance Sheet'!F11-'D1_Balance Sheet'!F7)/'D1_Balance Sheet'!F26 -> 1.068381 | G5: =('D1_Balance Sheet'!G11-'D1_Balance Sheet'!G7)/'D1_Balance Sheet'!G26 -> 1.0899663
A6: Cash Ratio | B6: ='D1_Balance Sheet'!B4/'D1_Balance Sheet'!B26 -> 0.2032901 | C6: ='D1_Balance Sheet'!C4/'D1_Balance Sheet'!C26 -> 0.21462862 | D6: ='D1_Balance Sheet'!D4/'D1_Balance Sheet'!D26 -> 0.24487102 | E6: ='D1_Balance Sheet'!E4/'D1_Balance Sheet'!E26 -> 0.25947185 | F6: ='D1_Balance Sheet'!F4/'D1_Balance Sheet'!F26 -> 0.22639347 | G6: ='D1_Balance Sheet'!G4/'D1_Balance Sheet'!G26 -> 0.25972302
B9: Year(t=0) | C9: Year(t=-1) | D9: Year(t=-2) | E9: Year(t=-3) | F9: Year(t=-4) | G9: Year(t=-5)
A10: Solvency Ratios | B10: 2025 | C10: 2024 | D10: 2023 | E10: 2022 | F10: 2021 | G10: 2020
A11: Debt Ratios:
A12: Debt to Total Assets | B12: =('D1_Balance Sheet'!B43-'D1_Balance Sheet'!B42)/'D1_Balance Sheet'!B19 -> 0.87566745 | C12: =('D1_Balance Sheet'!C43-'D1_Balance Sheet'!C42)/'D1_Balance Sheet'!C19 -> 0.84279233 | D12: =('D1_Balance Sheet'!D43-'D1_Balance Sheet'!D42)/'D1_Balance Sheet'!D19 -> 0.84350005 | E12: =('D1_Balance Sheet'!E43-'D1_Balance Sheet'!E42)/'D1_Balance Sheet'!E19 -> 0.83100936 | F12: =('D1_Balance Sheet'!F43-'D1_Balance Sheet'!F42)/'D1_Balance Sheet'!F19 -> 0.81123582 | G12: =('D1_Balance Sheet'!G43-'D1_Balance Sheet'!G42)/'D1_Balance Sheet'!G19 -> 0.88516843
A13: Debt to Equity | B13: =('D1_Balance Sheet'!B43-'D1_Balance Sheet'!B42)/'D1_Balance Sheet'!B42 -> 7.0429462 | C13: =('D1_Balance Sheet'!C43-'D1_Balance Sheet'!C42)/'D1_Balance Sheet'!C42 -> 5.3610126 | D13: =('D1_Balance Sheet'!D43-'D1_Balance Sheet'!D42)/'D1_Balance Sheet'!D42 -> 5.3897786 | E13: =('D1_Balance Sheet'!E43-'D1_Balance Sheet'!E42)/'D1_Balance Sheet'!E42 -> 4.9174876 | F13: =('D1_Balance Sheet'!F43-'D1_Balance Sheet'!F42)/'D1_Balance Sheet'!F42 -> 4.2976154 | G13: =('D1_Balance Sheet'!G43-'D1_Balance Sheet'!G42)/'D1_Balance Sheet'!G42 -> 7.7084066
A14: Debt to Total Capital | B14: =('D1_Balance Sheet'!B43-'D1_Balance Sheet'!B42)/'D1_Balance Sheet'!B43 -> 0.87566745 | C14: =('D1_Balance Sheet'!C43-'D1_Balance Sheet'!C42)/'D1_Balance Sheet'!C43 -> 0.84279233 | D14: =('D1_Balance Sheet'!D43-'D1_Balance Sheet'!D42)/'D1_Balance Sheet'!D43 -> 0.84350005 | E14: =('D1_Balance Sheet'!E43-'D1_Balance Sheet'!E42)/'D1_Balance Sheet'!E43 -> 0.83100936 | F14: =('D1_Balance Sheet'!F43-'D1_Balance Sheet'!F42)/'D1_Balance Sheet'!F43 -> 0.81123582 | G14: =('D1_Balance Sheet'!G43-'D1_Balance Sheet'!G42)/'D1_Balance Sheet'!G43 -> 0.88516843
A15: Financial Leverage | B15: ='D1_Balance Sheet'!B19/'D1_Balance Sheet'!B42 -> 8.0429462 | C15: ='D1_Balance Sheet'!C19/'D1_Balance Sheet'!C42 -> 6.3610126 | D15: ='D1_Balance Sheet'!D19/'D1_Balance Sheet'!D42 -> 6.3897786 | E15: ='D1_Balance Sheet'!E19/'D1_Balance Sheet'!E42 -> 5.9174876 | F15: ='D1_Balance Sheet'!F19/'D1_Balance Sheet'!F42 -> 5.2976154 | G15: ='D1_Balance Sheet'!G19/'D1_Balance Sheet'!G42 -> 8.7084066
A17: Coverage Interest Ratios:
A18: EBIT Interest Coverage | B18: =(D1_IncomeStatment!B22+D1_IncomeStatment!B17)/D1_IncomeStatment!B17 -> 2.6584887 | C18: =(D1_IncomeStatment!C22+D1_IncomeStatment!C17)/D1_IncomeStatment!C17 -> 0.046155875 | D18: =(D1_IncomeStatment!D22+D1_IncomeStatment!D17)/D1_IncomeStatment!D17 -> 0.37141499 | E18: =(D1_IncomeStatment!E22+D1_IncomeStatment!E17)/D1_IncomeStatment!E17 -> 1.9046191 | F18: =(D1_IncomeStatment!F22+D1_IncomeStatment!F17)/D1_IncomeStatment!F17 -> -5.3727599 | G18: =(D1_IncomeStatment!G22+D1_IncomeStatment!G17)/D1_IncomeStatment!G17 -> 1.3280423
A19: Fixed Charge Coverage
C23: Year(t=0) | D23: Year(t=-1) | E23: Year(t=-2) | F23: Year(t=-3) | G23: Year(t=-4) | H23: Year(t=-5)
A24: Z-Score Calculation | B24: Weighting Factor | C24: 2025 | D24: 2024 | E24: 2023 | F24: 2022 | G24: 2021 | H24: 2020
A25: Working Capital to Total Asset | B25: 1.2 | C25: =(('D1_Balance Sheet'!B11-'D1_Balance Sheet'!B26)/'D1_Balance Sheet'!B19)*1.2 -> 0.035677134 | D25: =(('D1_Balance Sheet'!C11-'D1_Balance Sheet'!C26)/'D1_Balance Sheet'!C19)*1.2 -> 0.074117449 | E25: =(('D1_Balance Sheet'!D11-'D1_Balance Sheet'!D26)/'D1_Balance Sheet'!D19)*1.2 -> 0.087592843 | F25: =(('D1_Balance Sheet'!E11-'D1_Balance Sheet'!E26)/'D1_Balance Sheet'!E19)*1.2 -> 0.091963546 | G25: =(('D1_Balance Sheet'!F11-'D1_Balance Sheet'!F26)/'D1_Balance Sheet'!F19)*1.2 -> 0.085291108 | H25: =(('D1_Balance Sheet'!G11-'D1_Balance Sheet'!G26)/'D1_Balance Sheet'!G19)*1.2 -> 0.087788342
A26: Retained Earnings to Total Capital | B26: 1.4 | C26: =('D1_Balance Sheet'!B40/'D1_Balance Sheet'!B43)*1.4 -> 0.10897496 | D26: =('D1_Balance Sheet'!C40/'D1_Balance Sheet'!C43)*1.4 -> 0.16562645 | E26: =('D1_Balance Sheet'!D40/'D1_Balance Sheet'!D43)*1.4 -> 0.15894259 | F26: =('D1_Balance Sheet'!E40/'D1_Balance Sheet'!E43)*1.4 -> 0.17373341 | G26: =('D1_Balance Sheet'!F40/'D1_Balance Sheet'!F43)*1.4 -> 0.19482405 | H26: =('D1_Balance Sheet'!G40/'D1_Balance Sheet'!G43)*1.4 -> 0.095562764
A27: EBIT to Total Assets | B27: 3.3 | C27: =((D1_IncomeStatment!B22+D1_IncomeStatment!B17)/'D1_Balance Sheet'!B19)*3.3 -> -0.21641271 | D27: =((D1_IncomeStatment!C22+D1_IncomeStatment!C17)/'D1_Balance Sheet'!C19)*3.3 -> -0.0040498464 | E27: =((D1_IncomeStatment!D22+D1_IncomeStatment!D17)/'D1_Balance Sheet'!D19)*3.3 -> -0.028301928 | F27: =((D1_IncomeStatment!E22+D1_IncomeStatment!E17)/'D1_Balance Sheet'!E19)*3.3 -> -0.081892576 | G27: =((D1_IncomeStatment!F22+D1_IncomeStatment!F17)/'D1_Balance Sheet'!F19)*3.3 -> 0.19245239 | H27: =((D1_IncomeStatment!G22+D1_IncomeStatment!G17)/'D1_Balance Sheet'!G19)*3.3 -> -0.055785917
A28: Market Value of Equity to Book Value of Liabilities | B28: 0.6 | C28: =(55000/('D1_Balance Sheet'!B43-'D1_Balance Sheet'!B42))*0.6 -> 0.13032764 | D28: =(55000/('D1_Balance Sheet'!C43-'D1_Balance Sheet'!C42))*0.6 -> 0.13729349 | E28: =(55000/('D1_Balance Sheet'!D43-'D1_Balance Sheet'!D42))*0.6 -> 0.14314405 | F28: =(55000/('D1_Balance Sheet'!E43-'D1_Balance Sheet'!E42))*0.6 -> 0.15519041 | G28: =(55000/('D1_Balance Sheet'!F43-'D1_Balance Sheet'!F42))*0.6 -> 0.15826124 | H28: =(55000/('D1_Balance Sheet'!G43-'D1_Balance Sheet'!G42))*0.6 -> 0.13949301
A29: Sales to Total Assets | B29: 1 | C29: =D1_IncomeStatment!B9/'D1_Balance Sheet'!B19 -> 0.64762415 | D29: =D1_IncomeStatment!C9/'D1_Balance Sheet'!C19 -> 0.64864865 | E29: =D1_IncomeStatment!D9/'D1_Balance Sheet'!D19 -> 0.64465625 | F29: =D1_IncomeStatment!E9/'D1_Balance Sheet'!E19 -> 0.61769005 | G29: =D1_IncomeStatment!F9/'D1_Balance Sheet'!F19 -> 0.53043749 | H29: =D1_IncomeStatment!G9/'D1_Balance Sheet'!G19 -> 0.47572972
A31: Z-Score | C31: =SUM(C25:C29) -> 0.70619117 | D31: =SUM(D25:D29) -> 1.0216362 | E31: =SUM(E25:E29) -> 1.0060338 | F31: =SUM(F25:F29) -> 0.95668484 | G31: =SUM(G25:G29) -> 1.1612663 | H31: =SUM(H25:H29) -> 0.74278791
A34: *Please note the formulas and the historical estimated credit ratings are found in the Deliverable Instructions.
B35: Year(t=0) | C35: Year(t=-1) | D35: Year(t=-2) | E35: Year(t=-3) | F35: Year(t=-4) | G35: Year(t=-5)
A36: Line Items | B36: 2025 | C36: 2024 | D36: 2023 | E36: 2022 | F36: 2021 | G36: 2020
A37: EBITA to average assets = EBIT/Avg Assets | B37: =(D1_IncomeStatment!B22+D1_IncomeStatment!B17)/(('D1_Balance Sheet'!B19+'D1_Balance Sheet'!C19)/2) -> -0.066032217 | C37: =(D1_IncomeStatment!C22+D1_IncomeStatment!C17)/(('D1_Balance Sheet'!C19+'D1_Balance Sheet'!D19)/2) -> -0.0012533437 | D37: =(D1_IncomeStatment!D22+D1_IncomeStatment!D17)/(('D1_Balance Sheet'!D19+'D1_Balance Sheet'!E19)/2) -> -0.008858755 | E37: =(D1_IncomeStatment!E22+D1_IncomeStatment!E17)/(('D1_Balance Sheet'!E19+'D1_Balance Sheet'!F19)/2) -> -0.024760245 | F37: =(D1_IncomeStatment!F22+D1_IncomeStatment!F17)/(('D1_Balance Sheet'!F19+'D1_Balance Sheet'!G19)/2) -> 0.057181439 | G37: =(D1_IncomeStatment!G22+D1_IncomeStatment!G17)/(('D1_Balance Sheet'!G19+'D1_Balance Sheet'!H19)/2) -> -0.033809647
A38: Estimated Credit Rating | B38: C | C38: C | D38: C | E38: C | F38: C | G38: C
A40: Operating Income Margin = EBT/Sales | B40: =D1_IncomeStatment!B22/D1_IncomeStatment!B9 -> -0.063171835 | C40: =D1_IncomeStatment!C22/D1_IncomeStatment!C9 -> 0.039098988 | D40: =D1_IncomeStatment!D22/D1_IncomeStatment!D9 -> 0.022515338 | E40: =D1_IncomeStatment!E22/D1_IncomeStatment!E9 -> -0.019081724 | F40: =D1_IncomeStatment!F22/D1_IncomeStatment!F9 -> 0.13040831 | G40: =D1_IncomeStatment!G22/D1_IncomeStatment!G9 -> -0.0087774492
A41: Estimated Credit Rating | B41: C | C41: C | D41: C | E41: C | F41: Baa | G41: C
A43: EBITA margin = EBIT/Sales | B43: =(D1_IncomeStatment!B22+D1_IncomeStatment!B17)/D1_IncomeStatment!B9 -> -0.10126183 | C43: =(D1_IncomeStatment!C22+D1_IncomeStatment!C17)/D1_IncomeStatment!C9 -> -0.0018919737 | D43: =(D1_IncomeStatment!D22+D1_IncomeStatment!D17)/D1_IncomeStatment!D9 -> -0.013303744 | E43: =(D1_IncomeStatment!E22+D1_IncomeStatment!E17)/D1_IncomeStatment!E9 -> -0.04017538 | F43: =(D1_IncomeStatment!F22+D1_IncomeStatment!F17)/D1_IncomeStatment!F9 -> 0.10994492 | G43: =(D1_IncomeStatment!G22+D1_IncomeStatment!G17)/D1_IncomeStatment!G9 -> -0.035534512
A44: Estimated Credit Rating | B44: C | C44: C | D44: C | E44: C | F44: B | G44: C
A46: EBITA interest coverage = EBIT/Interest Expense | B46: =(D1_IncomeStatment!B22+D1_IncomeStatment!B17)/D1_IncomeStatment!B17 -> 2.6584887 | C46: =(D1_IncomeStatment!C22+D1_IncomeStatment!C17)/D1_IncomeStatment!C17 -> 0.046155875 | D46: =(D1_IncomeStatment!D22+D1_IncomeStatment!D17)/D1_IncomeStatment!D17 -> 0.37141499 | E46: =(D1_IncomeStatment!E22+D1_IncomeStatment!E17)/D1_IncomeStatment!E17 -> 1.9046191 | F46: =(D1_IncomeStatment!F22+D1_IncomeStatment!F17)/D1_IncomeStatment!F17 -> -5.3727599 | G46: =(D1_IncomeStatment!G22+D1_IncomeStatment!G17)/D1_IncomeStatment!G17 -> 1.3280423
A47: Estimated Credit Rating | B47: B | C47: C | D47: C | E47: C | F47: C | G47: C
A49: (FFO + Interest Expense)/Interest Expense | B49: =(D1_IncomeStatment!B26+D1_StatmentofCFs!B7+D1_IncomeStatment!B17)/D1_IncomeStatment!B17 -> 2.4048787 | C49: =(D1_IncomeStatment!C26+D1_StatmentofCFs!C7+D1_IncomeStatment!C17)/D1_IncomeStatment!C17 -> 0.44889885 | D49: =(D1_IncomeStatment!D26+D1_StatmentofCFs!D7+D1_IncomeStatment!D17)/D1_IncomeStatment!D17 -> 0.49611789 | E49: =(D1_IncomeStatment!E26+D1_StatmentofCFs!E7+D1_IncomeStatment!E17)/D1_IncomeStatment!E17 -> 1.9388122 | F49: =(D1_IncomeStatment!F26+D1_StatmentofCFs!F7+D1_IncomeStatment!F17)/D1_IncomeStatment!F17 -> -4.9422939 | G49: =(D1_IncomeStatment!G26+D1_StatmentofCFs!G7+D1_IncomeStatment!G17)/D1_IncomeStatment!G17 -> 1.7563198
A50: Estimated Credit Rating | B50: C | C50: C | D50: C | E50: C | F50: C | G50: C
A52: Debt to EBITDA = (Short term Debt + Long Term Debt)/EBITDA | B52: =('D1_Balance Sheet'!B43-'D1_Balance Sheet'!B42)/(D1_IncomeStatment!B22+D1_IncomeStatment!B17) -> -13.35274 | C52: =('D1_Balance Sheet'!C43-'D1_Balance Sheet'!C42)/(D1_IncomeStatment!C22+D1_IncomeStatment!C17) -> -686.74571 | D52: =('D1_Balance Sheet'!D43-'D1_Balance Sheet'!D42)/(D1_IncomeStatment!D22+D1_IncomeStatment!D17) -> -98.351962 | E52: =('D1_Balance Sheet'!E43-'D1_Balance Sheet'!E42)/(D1_IncomeStatment!E22+D1_IncomeStatment!E17) -> -33.486929 | F52: =('D1_Balance Sheet'!F43-'D1_Balance Sheet'!F42)/(D1_IncomeStatment!F22+D1_IncomeStatment!F17) -> 13.91034 | G52: =('D1_Balance Sheet'!G43-'D1_Balance Sheet'!G42)/(D1_IncomeStatment!G22+D1_IncomeStatment!G17) -> -52.361886
A53: Estimated Credit Rating | B53: C | C53: C | D53: C | E53: C | F53: C | G53: C
A55: Debt to Book Capitalization = (Short term Debt + Long Term Debt)/ (Short term Debt + Long Term Debt+Deferred Taxes+Minority Interest+ Book Equity) | B55: ='D1_Balance Sheet'!B44/('D1_Balance Sheet'!B29+'D1_Balance Sheet'!B44+'D1_Balance Sheet'!B30+'D1_Balance Sheet'!B42) -> 0.87150223 | C55: ='D1_Balance Sheet'!C44/('D1_Balance Sheet'!C29+'D1_Balance Sheet'!C44+'D1_Balance Sheet'!C30+'D1_Balance Sheet'!C42) -> 0.83956297 | D55: ='D1_Balance Sheet'!D44/('D1_Balance Sheet'!D29+'D1_Balance Sheet'!D44+'D1_Balance Sheet'!D30+'D1_Balance Sheet'!D42) -> 0.84033316 | E55: ='D1_Balance Sheet'!E44/('D1_Balance Sheet'!E29+'D1_Balance Sheet'!E44+'D1_Balance Sheet'!E30+'D1_Balance Sheet'!E42) -> 0.82624982 | F55: ='D1_Balance Sheet'!F44/('D1_Balance Sheet'!F29+'D1_Balance Sheet'!F44+'D1_Balance Sheet'!F30+'D1_Balance Sheet'!F42) -> 0.8059555 | G55: ='D1_Balance Sheet'!G44/('D1_Balance Sheet'!G29+'D1_Balance Sheet'!G44+'D1_Balance Sheet'!G30+'D1_Balance Sheet'!G42) -> 0.88299119
A56: Estimated Credit Rating | B56: B | C56: B | D56: B | E56: B | F56: B | G56: B
A58: FFO to Debt | B58: =(D1_StatmentofCFs!B4+D1_StatmentofCFs!B5)/('D1_Balance Sheet'!B43-'D1_Balance Sheet'!B42) -> -0.0012953777 | C58: =(D1_StatmentofCFs!C4+D1_StatmentofCFs!C5)/('D1_Balance Sheet'!C43-'D1_Balance Sheet'!C42) -> 0.056003262 | D58: =(D1_StatmentofCFs!D4+D1_StatmentofCFs!D5)/('D1_Balance Sheet'!D43-'D1_Balance Sheet'!D42) -> 0.052134798 | E58: =(D1_StatmentofCFs!E4+D1_StatmentofCFs!E5)/('D1_Balance Sheet'!E43-'D1_Balance Sheet'!E42) -> 0.025818042 | F58: =(D1_StatmentofCFs!F4+D1_StatmentofCFs!F5)/('D1_Balance Sheet'!F43-'D1_Balance Sheet'!F42) -> 0.12098832 | G58: =(D1_StatmentofCFs!G4+D1_StatmentofCFs!G5)/('D1_Balance Sheet'!G43-'D1_Balance Sheet'!G42) -> 0.031597279
A59: Estimated Credit Rating | B59: C | C59: C | D59: C | E59: C | F59: B | G59: C
A61: RCF to Debt = Retained Cash Flow/Debt | B61: =D1_StatmentofCFs!B27/('D1_Balance Sheet'!B43-'D1_Balance Sheet'!B42) -> 0.084049477 | C61: =D1_StatmentofCFs!C27/('D1_Balance Sheet'!C43-'D1_Balance Sheet'!C42) -> 0.064165984 | D61: =D1_StatmentofCFs!D27/('D1_Balance Sheet'!D43-'D1_Balance Sheet'!D42) -> 0.064709786 | E61: =D1_StatmentofCFs!E27/('D1_Balance Sheet'!E43-'D1_Balance Sheet'!E42) -> 0.032227876 | F61: =D1_StatmentofCFs!F27/('D1_Balance Sheet'!F43-'D1_Balance Sheet'!F42) -> 0.075711216 | G61: =D1_StatmentofCFs!G27/('D1_Balance Sheet'!G43-'D1_Balance Sheet'!G42) -> 0.10258654
A62: Estimated Credit Rating | B62: C | C62: C | D62: C | E62: C | F62: C | G62: C
A64: Capex to Depreciation = CapEx/Depreciation | B64: =(D1_StatmentofCFs!B29/D1_StatmentofCFs!B5) -> -1.1252234 | C64: =(D1_StatmentofCFs!C29/D1_StatmentofCFs!C5) -> -1.1476146 | D64: =(D1_StatmentofCFs!D29/D1_StatmentofCFs!D5) -> -1.0710013 | E64: =(D1_StatmentofCFs!E29/D1_StatmentofCFs!E5) -> -0.8984559 | F64: =(D1_StatmentofCFs!F29/D1_StatmentofCFs!F5) -> -0.85091555 | G64: =(D1_StatmentofCFs!G29/D1_StatmentofCFs!G5) -> -0.65615358
A65: Estimated Credit Rating | B65: C | C65: C | D65: C | E65: C | F65: C | G65: C
A68: Estimated Long Term Debt Rating

Sheet D4_Valuation Ratios
A1: *Please use calculations as shown in the slides and/or textbook (please do not use the internet)
B2: Year(t=0) | C2: Year(t=-1) | D2: Year(t=-2) | E2: Year(t=-3) | F2: Year(t=-4) | G2: Year(t=-5)
A3: Trailing Price Multiples | B3: 2025 | C3: 2024 | D3: 2023 | E3: 2022 | F3: 2021 | G3: 2020
A4: P/E | B4: =B9/B10 -> -6.461165 | C4: =C9/C10 -> 6.869863 | D4: =D9/D10 -> 11.435185 | E4: =E9/E10 -> -23.183673 | F4: =F9/F10 -> 3.647191 | G4: =G9/G10 -> -27.46875
A5: P/CF | B5: =B9/B11 -> 2.4840359 | C5: =C9/C11 -> 2.6186815 | D5: =D9/D11 -> 3.3321323 | E5: =E9/E11 -> 6.7017156 | F5: =F9/F11 -> 4.1438947 | G5: =G9/G11 -> 1.4476299
A6: P/S | B6: =B9/B43 -> 0.28229882 | C6: =C9/C43 -> 0.21832255 | D6: =D9/D43 -> 0.2821299 | E6: =E9/E43 -> 0.29057148 | F6: =F9/F43 -> 0.47982386 | G6: =G9/G43 -> 0.2763208
A7: P/BV | B7: =B9/B12 -> 1.4704398 | C7: =C9/C12 -> 0.90081242 | D7: =D9/D12 -> 1.1621525 | E7: =E9/E12 -> 1.0620891 | F7: =F9/F12 -> 1.3483309 | G7: =G9/G12 -> 1.144755
A9: Mkt Price | B9: 13.31 | C9: 10.03 | D9: 12.35 | E9: 11.36 | F9: 16.23 | G9: 8.79
A10: EPS | B10: =D1_IncomeStatment!B30 -> -2.06 | C10: =D1_IncomeStatment!C30 -> 1.46 | D10: =D1_IncomeStatment!D30 -> 1.08 | E10: =D1_IncomeStatment!E30 -> -0.49 | F10: =D1_IncomeStatment!F30 -> 4.45 | G10: =D1_IncomeStatment!G30 -> -0.32
A11: Cash Flow | B11: =D1_StatmentofCFs!B27/D1_IncomeStatment!B31 -> 5.3582156 | C11: =D1_StatmentofCFs!C27/D1_IncomeStatment!C31 -> 3.8301718 | D11: =D1_StatmentofCFs!D27/D1_IncomeStatment!D31 -> 3.7063354 | E11: =D1_StatmentofCFs!E27/D1_IncomeStatment!E31 -> 1.6950883 | F11: =D1_StatmentofCFs!F27/D1_IncomeStatment!F31 -> 3.9166053 | G11: =D1_StatmentofCFs!G27/D1_IncomeStatment!G31 -> 6.0719937
A12: Book Value | B12: ='D1_Balance Sheet'!B42/D1_IncomeStatment!B31 -> 9.0517135 | C12: ='D1_Balance Sheet'!C42/D1_IncomeStatment!C31 -> 11.134394 | D12: ='D1_Balance Sheet'!D42/D1_IncomeStatment!D31 -> 10.626832 | E12: ='D1_Balance Sheet'!E42/D1_IncomeStatment!E31 -> 10.695901 | F12: ='D1_Balance Sheet'!F42/D1_IncomeStatment!F31 -> 12.037105 | G12: ='D1_Balance Sheet'!G42/D1_IncomeStatment!G31 -> 7.6784988
A13: Note:Use the market price that is closest to the end of the reporting year as possible. Thus if you Balance sheet says "As of June 30, 2017." Find the stock price that is closest to that date. You can find price history on Yahoo Finance.
A16: Leading Price Multiples
B17: Year (t=+1)
A18: Forecasted EPS | B18: 1.52 | C18: *yahoo, analyst estimates page
A19: Leading P/E (Leading P/E = P0/EPS1) | B19: =B9/B18 -> 8.7565789
B22: Year(t=0) | C22: Year(t=-1) | D22: Year(t=-2) | E22: Year(t=-3) | F22: Year(t=-4) | G22: Year(t=-5)
A23: Enterprise Value and Residual Income
A24: Market Value of Debt (Use Book Value as proxy) | B24: ='D1_Balance Sheet'!B21+'D1_Balance Sheet'!B23+'D1_Balance Sheet'!B28+'D1_Balance Sheet'!B32 -> 163336 | C24: ='D1_Balance Sheet'!C21+'D1_Balance Sheet'!C23+'D1_Balance Sheet'!C28+'D1_Balance Sheet'!C32 -> 158522 | D24: ='D1_Balance Sheet'!D21+'D1_Balance Sheet'!D23+'D1_Balance Sheet'!D28+'D1_Balance Sheet'!D32 -> 149231 | E24: ='D1_Balance Sheet'!E21+'D1_Balance Sheet'!E23+'D1_Balance Sheet'!E28+'D1_Balance Sheet'!E32 -> 138969 | F24: ='D1_Balance Sheet'!F21+'D1_Balance Sheet'!F23+'D1_Balance Sheet'!F28+'D1_Balance Sheet'!F32 -> 138092 | G24: ='D1_Balance Sheet'!G21+'D1_Balance Sheet'!G23+'D1_Balance Sheet'!G28+'D1_Balance Sheet'!G32 -> 161684
A25: Market Value of Preferred Stock (if applicable…use Book Value as proxy) | B25: 0 | C25: 0 | D25: 0 | E25: 0 | F25: 0 | G25: 0
A26: Market Value of Equity (Market Capitalization) | B26: =D1_IncomeStatment!B31*B9 -> 52865.252 | C26: =D1_IncomeStatment!C31*C9 -> 40387.925 | D26: =D1_IncomeStatment!D31*D9 -> 49708.75 | E26: =D1_IncomeStatment!E31*E9 -> 45926.857 | F26: =D1_IncomeStatment!F31*F9 -> 65419.665 | G26: =D1_IncomeStatment!G31*G9 -> 35132.531
A27: Cash and Short-term investments | B27: ='D1_Balance Sheet'!B4+'D1_Balance Sheet'!B5 -> 38487 | C27: ='D1_Balance Sheet'!C4+'D1_Balance Sheet'!C5 -> 38348 | D27: ='D1_Balance Sheet'!D4+'D1_Balance Sheet'!D5 -> 40171 | E27: ='D1_Balance Sheet'!E4+'D1_Balance Sheet'!E5 -> 44070 | F27: ='D1_Balance Sheet'!F4+'D1_Balance Sheet'!F5 -> 49593 | G27: ='D1_Balance Sheet'!G4+'D1_Balance Sheet'!G5 -> 49961
A28: Minority Interest (aka Non-controlling Interest) | B28: ='D1_Balance Sheet'!B30 -> 28 | C28: ='D1_Balance Sheet'!C30 -> 23 | D28: ='D1_Balance Sheet'!D30 -> 25 | E28: ='D1_Balance Sheet'!E30 -> -75 | F28: ='D1_Balance Sheet'!F30 -> 103 | G28: ='D1_Balance Sheet'!G30 -> 121
A29: Enterprise Value (Enterprise value = Market value of common equity + Market value of preferred stock + Market value of debt + Minority Interest – Value of cash and short-term investments) | B29: =B24+B25+B26+B28-B27 -> 177742.25 | C29: =C24+C25+C26+C28-C27 -> 160584.92 | D29: =D24+D25+D26+D28-D27 -> 158793.75 | E29: =E24+E25+E26+E28-E27 -> 140750.86 | F29: =F24+F25+F26+F28-F27 -> 154021.67 | G29: =G24+G25+G26+G28-G27 -> 146976.53
A30: EBITDA | B30: =D1_IncomeStatment!B28+D1_StatmentofCFs!B5 -> -1335 | C30: =D1_IncomeStatment!C28+D1_StatmentofCFs!C5 -> 12786 | D30: =D1_IncomeStatment!D28+D1_StatmentofCFs!D5 -> 13148 | E30: =D1_IncomeStatment!E28+D1_StatmentofCFs!E5 -> 13918 | F30: =D1_IncomeStatment!F28+D1_StatmentofCFs!F5 -> 11841 | G30: =D1_IncomeStatment!G28+D1_StatmentofCFs!G5 -> 4343
A31: Enterprise Value to EBITDA (EV/EBITDA = Enterprise Value/EBITDA) | B31: =B29/B30 -> -133.14026 | C31: =C29/C30 -> 12.559434 | D31: =D29/D30 -> 12.077407 | E31: =E29/E30 -> 10.112865 | F31: =F29/F30 -> 13.007488 | G31: =G29/G30 -> 33.842167
A34: Cost of Equity Capital | B34: =4.3%+1.37*5% -> 0.1115 | C34: =4.3%+1.37*5% -> 0.1115 | D34: =4.3%+1.37*5% -> 0.1115 | E34: =4.3%+1.37*5% -> 0.1115 | F34: =4.3%+1.37*5% -> 0.1115 | G34: =4.3%+1.37*5% -> 0.1115
A35: Equity Capital | B35: ='D1_Balance Sheet'!B42 -> 35952 | C35: ='D1_Balance Sheet'!C42 -> 44835 | D35: ='D1_Balance Sheet'!D42 -> 42773 | E35: ='D1_Balance Sheet'!E42 -> 43242 | F35: ='D1_Balance Sheet'!F42 -> 48519 | G35: ='D1_Balance Sheet'!G42 -> 30690
A36: Equity charge = Cost of equity capital × Equity capital | B36: =B34*B35 -> 4008.648 | C36: =C34*C35 -> 4999.1025 | D36: =D34*D35 -> 4769.1895 | E36: =E34*E35 -> 4821.483 | F36: =F34*F35 -> 5409.8685 | G36: =G34*G35 -> 3421.935
A37: Net Income | B37: =D1_IncomeStatment!B26 -> -8182 | C37: =D1_IncomeStatment!C26 -> 5879 | D37: =D1_IncomeStatment!D26 -> 4347 | E37: =D1_IncomeStatment!E26 -> -1981 | F37: =D1_IncomeStatment!F26 -> 17937 | G37: =D1_IncomeStatment!G26 -> -1279
A38: Residual Income | B38: =B37-B36 -> -12190.648 | C38: =C37-C36 -> 879.8975 | D38: =D37-D36 -> -422.1895 | E38: =E37-E36 -> -6802.483 | F38: =F37-F36 -> 12527.131 | G38: =G37-G36 -> -4700.935
A43: Revenue per share | B43: =D1_IncomeStatment!B9/D1_IncomeStatment!B31 -> 47.148621 | C43: =D1_IncomeStatment!C9/D1_IncomeStatment!C31 -> 45.941201 | D43: =D1_IncomeStatment!D9/D1_IncomeStatment!D31 -> 43.774161 | E43: =D1_IncomeStatment!E9/D1_IncomeStatment!E31 -> 39.095371 | F43: =D1_IncomeStatment!F9/D1_IncomeStatment!F31 -> 33.824912 | G43: =D1_IncomeStatment!G9/D1_IncomeStatment!G31 -> 31.810852 | I43: *need rev per share to calculate P/S

Sheet D5_Long Term Liab
A1: *Note the future years are represented with t=+1, t=+2, etc.
B3: Year(t=0) | C3: Year(t=+1) | D3: Year(t=+2) | E3: Year(t=+3) | F3: Year(t=+4) | G3: Year(t=+5) | H3: Thereafter
A5: Principal Coming Due

Sheet D5_Income Shifting
A1: This tab walks you through several places where managers have flexibility and can shift income (the stuff that we have hit throughout the term), and hopefully gets you to think about it holistically.
A2: Income shifting is hard to prove, but like a lawyer you look for mounting evidence. Thus if you see multiple places where it appears suspect, then you can build a case for it.
B4: Year(t=0) | C4: Year(t=-1) | D4: Year(t=-2) | E4: Year(t=-3) | F4: Year(t=-4) | G4: Year(t=-5)
A5: Revenue Recognition:
A6: Did Revenue Recognition Policy Change?
A7: Was change Aggressive, Conservative, or Nuetral?
A8: Are there long-term contracts?
A9: Barter transactions?
A10: Bill and Hold transactions?
A11: Installment Sales?
A12: Were there Sales Allowances?
A14: Revenue Amt ($)
A15: Revenue Growth (%Growth)
A17: Potential for Income Shifting?
B20: Year(t=0) | C20: Year(t=-1) | D20: Year(t=-2) | E20: Year(t=-3) | F20: Year(t=-4) | G20: Year(t=-5)
A21: Restructuring Expense
A22: Restructuring Expense
A23: Further Accruals Made?
A24: Reversals Made?
B27: Year(t=0) | C27: Year(t=-1) | D27: Year(t=-2) | E27: Year(t=-3) | F27: Year(t=-4) | G27: Year(t=-5)
A28: Accounts Receivable:
A29: Review Footnotes related to AR. Were there any changes?
A31: AR Amounts Reported on Bal Sheet (Net of Allowances)
A32: Allowance Amounts
A33: Gross AR (AR + Allowances)
A34: Allowance to Gross AR Ratio (i.e. what percentage the firm thinks is uncollectible) = Allowance Amt/Gross AR
A36: Bad Debt Expense
A37: Bad Debt to Sales Ratio
A38: AR to Sales Ratio (note that it's the inverse of AR turnover)
A40: Accounts Receivable Turnover
A41: DSO
A43: Potential for Income Shifting?
B46: Year(t=0) | C46: Year(t=-1) | D46: Year(t=-2) | E46: Year(t=-3) | F46: Year(t=-4) | G46: Year(t=-5)
A47: Inventory:
A48: Inventory Costing Method Used
A49: Any Changes to Inventory Costing methods in Significant Accounting Policies?
A51: Inventory Growth
A52: Sales Growth
A54: Gross Profit Margin
A55: Inventory Turnover
A56: Days of Inventory on Hand
A58: Inventory Write-downs (Yes/No)?
A59: LIFO Liquidations (if applicable)
A60: Potential For Income Shifting?
B63: Year(t=0) | C63: Year(t=-1) | D63: Year(t=-2) | E63: Year(t=-3) | F63: Year(t=-4) | G63: Year(t=-5)
A64: PP&E:
A65: Review Significant Accounting Policies for PP&E (and any other applicable footnotes). Were there any changes over the years? Eg. Did they make any changes to Useful Lives in how they depreciate different asset classes (buildings, office equipment, etc.).
A66: Was the change Aggressive, Conservative or Nuetral?
A67: Were there any write-downs with regards to their PP&E?
A69: PPE Turnover
A71: Average Useful Life = depreciable Asset Costs/Depreciation Expense
A73: Percent Used Up = Accumulated Depreciation / Depreciable Asset Costs
A75: Potential For Income Shifting?
B80: Year(t=0) | C80: Year(t=-1) | D80: Year(t=-2) | E80: Year(t=-3) | F80: Year(t=-4) | G80: Year(t=-5)
A81: Intangible Assets
A82: Review Significant Accounting Policies and any applicable footnotes for Intangibles (Goodwill and/or Other Intangibles). Were there any changes over the years?
A83: Was the change Aggressive, Conservative or Nuetral?
A84: Were there any write-downs of Intangible Assets (Goodwill or Other Intangible Assets)?
A86: Potential For Income Shifting?
B90: Year(t=0) | C90: Year(t=-1) | D90: Year(t=-2) | E90: Year(t=-3) | F90: Year(t=-4) | G90: Year(t=-5)
A91: CFO to Income
A92: CFO to Op. Income = CFO/Operating Income
A93: %Change = (new-old)/abs(old)
A95: CFO to Income = CFO/Net Income
A96: %Change = (new-old)/abs(old)
