Workbook

Sheet Income Statement
A1: SELLAS LIFE SCIENCES GROUP, INC. (SLS)
A2: Consolidated Statement of Operations (USD $000s)
A3: Source: 10-K (FY2024), 10-Q (Q3 2025)
B5: FY 2022 | C5: FY 2023 | D5: FY 2024 | E5: Q3 2025 (9M) | F5: Notes
A6: Revenue
A7: License & Collaboration Revenue | B7: 12400 | C7: 9700 | D7: 0 | E7: 0
A8: Total Revenue | B8: =B7 -> 12400 | C8: =C7 -> 9700 | D8: =D7 -> 0 | E8: =E7 -> 0 | F8: No product revenue; licensing ended 2023
A10: Operating Expenses
A11: Research & Development | B11: 18500 | C11: 24000 | D11: 19100 | E11: 11300 | F11: GPS Phase 3 REGAL trial costs
A12: General & Administrative | B12: 14200 | C12: 13900 | D12: 12400 | E12: 9500 | F12: Includes SBC
A13: Total Operating Expenses | B13: =SUM(B11:B12) -> 32700 | C13: =SUM(C11:C12) -> 37900 | D13: =SUM(D11:D12) -> 31500 | E13: =SUM(E11:E12) -> 20800
A15: Operating Income (Loss) | B15: =B8-B13 -> -20300 | C15: =C8-C13 -> -28200 | D15: =D8-D13 -> -31500 | E15: =E8-E13 -> -20800
A17: Other Income (Expense)
A18: Interest Income | B18: 200 | C18: 350 | D18: 500 | E18: 800
A19: Interest Expense | B19: -1200 | C19: -800 | D19: -500 | E19: -300
A20: Change in FV of Warrant Liabilities | B20: -5000 | C20: 2500 | D20: -1800 | E20: -3200
A21: Other Income / (Expense) | B21: 100 | C21: -200 | D21: 300 | E21: -100
A22: Total Other Income (Expense) | B22: =SUM(B18:B21) -> -5900 | C22: =SUM(C18:C21) -> 1850 | D22: =SUM(D18:D21) -> -1500 | E22: =SUM(E18:E21) -> -2800
A24: Income Tax Expense | B24: 0 | C24: 0 | D24: 0 | E24: 0
A26: NET LOSS | B26: =B15+B22-B24 -> -26200 | C26: =C15+C22-C24 -> -26350 | D26: =D15+D22-D24 -> -33000 | E26: =E15+E22-E24 -> -23600
A28: Shares Outstanding - Basic (M) | B28: 45 | C28: 35 | D28: 74 | E28: 108.4 | F28: Significant dilution from warrant exercises
A29: EPS (Basic) | B29: =B26/(B28*1000) -> -0.58222222 | C29: =C26/(C28*1000) -> -0.75285714 | D29: =D26/(D28*1000) -> -0.44594595 | E29: =E26/(E28*1000) -> -0.21771218
A31: Key Metrics
A32: R&D as % of OpEx | B32: =B11/B13 -> 0.56574924 | C32: =C11/C13 -> 0.63324538 | D32: =D11/D13 -> 0.60634921 | E32: =E11/E13 -> 0.54326923
A33: Cash Burn per Quarter ($000s) | B33: =B13/4 -> 8175 | C33: =C13/4 -> 9475 | D33: =D13/4 -> 7875 | E33: =E13/3 -> 6933.3333

Sheet Balance Sheet
A1: SELLAS LIFE SCIENCES GROUP, INC. (SLS)
A2: Consolidated Balance Sheet (USD $000s)
B4: Dec 31, 2023 | C4: Dec 31, 2024 | D4: Sep 30, 2025
A5: ASSETS
A6: Cash & Cash Equivalents | B6: 18500 | C6: 13900 | D6: 44300 | E6: $71.8M by Dec 31, 2025 per 10-K
A7: Prepaid Expenses & Other Current | B7: 3200 | C7: 2800 | D7: 3500
A8: Other Receivables | B8: 1500 | C8: 1200 | D8: 800
A9: Total Current Assets | B9: =SUM(B6:B8) -> 23200 | C9: =SUM(C6:C8) -> 17900 | D9: =SUM(D6:D8) -> 48600
A10: Non-Current Assets
A11: Operating Lease ROU Assets | B11: 2500 | C11: 1800 | D11: 1500
A12: Intangible Assets (Licenses) | B12: 3500 | C12: 3200 | D12: 3000
A13: Other Non-Current Assets | B13: 800 | C13: 500 | D13: 400
A14: Total Non-Current Assets | B14: =SUM(B11:B13) -> 6800 | C14: =SUM(C11:C13) -> 5500 | D14: =SUM(D11:D13) -> 4900
A16: TOTAL ASSETS | B16: =B9+B14 -> 30000 | C16: =C9+C14 -> 23400 | D16: =D9+D14 -> 53500
A18: LIABILITIES & EQUITY
A19: Accounts Payable & Accrued Expenses | B19: 8500 | C19: 6200 | D19: 7800
A20: Accrued Clinical Trial Costs | B20: 4500 | C20: 3800 | D20: 4200
A21: Operating Lease Liability - Current | B21: 800 | C21: 700 | D21: 600
A22: Warrant Liabilities | B22: 3200 | C22: 5000 | D22: 8200
A23: Other Current Liabilities | B23: 1200 | C23: 800 | D23: 600
A24: Total Current Liabilities | B24: =SUM(B19:B23) -> 18200 | C24: =SUM(C19:C23) -> 16500 | D24: =SUM(D19:D23) -> 21400
A25: Operating Lease Liability - Non-Current | B25: 1800 | C25: 1200 | D25: 1000
A26: Other Non-Current Liabilities | B26: 500 | C26: 300 | D26: 200
A27: Total Non-Current Liabilities | B27: =SUM(B25:B26) -> 2300 | C27: =SUM(C25:C26) -> 1500 | D27: =SUM(D25:D26) -> 1200
A29: Total Liabilities | B29: =B24+B27 -> 20500 | C29: =C24+C27 -> 18000 | D29: =D24+D27 -> 22600
A30: Shareholders' Equity
A31: Common Stock & APIC | B31: 285000 | C31: 340000 | D31: 410000
A32: Accumulated Deficit | B32: -265000 | C32: -295900 | D32: -326800
A33: AOCI | B33: -500 | C33: -300 | D33: -200
A34: Total Shareholders' Equity | B34: =SUM(B31:B33) -> 19500 | C34: =SUM(C31:C33) -> 43800 | D34: =SUM(D31:D33) -> 83000
A36: TOTAL LIABILITIES & EQUITY | B36: =B29+B34 -> 40000 | C36: =C29+C34 -> 61800 | D36: =D29+D34 -> 105600
A38: Balance Check (= 0) | B38: =B16-B36 -> -10000 | C38: =C16-C36 -> -38400 | D38: =D16-D36 -> -52100
A40: Key Ratios
A41: Current Ratio | B41: =B9/B24 -> 1.2747253 | C41: =C9/C24 -> 1.0848485 | D41: =D9/D24 -> 2.271028
A42: Cash as % of Total Assets | B42: =B6/B16 -> 0.61666667 | C42: =C6/C16 -> 0.59401709 | D42: =D6/D16 -> 0.82803738
A43: Cash Runway (Quarters) | B43: =B6/('Income Statement'!B13/4) -> 2.2629969 | C43: =C6/('Income Statement'!D13/4) -> 1.7650794 | D43: =D6/('Income Statement'!E13/3) -> 6.3894231 | E43: Formula: Cash / Quarterly Burn

Sheet Cash Flow Statement
A1: SELLAS LIFE SCIENCES GROUP, INC. (SLS)
A2: Consolidated Cash Flow Statement (USD $000s)
B4: FY 2022 | C4: FY 2023 | D4: FY 2024
A5: OPERATING ACTIVITIES
A6: Net Loss | B6: ='Income Statement'!B26 -> -26200 | C6: ='Income Statement'!C26 -> -26350 | D6: ='Income Statement'!D26 -> -33000
A7: Adjustments:
A8: Stock-Based Compensation | B8: 4500 | C8: 3800 | D8: 3200
A9: Change in FV of Warrants | B9: 5000 | C9: -2500 | D9: 1800
A10: Depreciation & Amortization | B10: 800 | C10: 900 | D10: 750
A11: Non-Cash Lease Expense | B11: 600 | C11: 500 | D11: 400
A12: Changes in Working Capital:
A13: Receivables & Prepaids | B13: -1200 | C13: 800 | D13: 700
A14: Accounts Payable & Accrued | B14: 3500 | C14: -2800 | D14: -2300
A15: Accrued Clinical Trial Costs | B15: 2000 | C15: 1500 | D15: -700
A16: Other Working Capital | B16: -500 | C16: -300 | D16: -200
A17: Net Cash Used in Operations | B17: =SUM(B6,B8:B11,B13:B16) -> -11500 | C17: =SUM(C6,C8:C11,C13:C16) -> -24450 | D17: =SUM(D6,D8:D11,D13:D16) -> -29350
A19: INVESTING ACTIVITIES
A20: Purchase of Equipment | B20: -100 | C20: -50 | D20: -30
A21: Other Investing | B21: 0 | C21: 0 | D21: 0
A22: Net Cash from Investing | B22: =SUM(B20:B21) -> -100 | C22: =SUM(C20:C21) -> -50 | D22: =SUM(D20:D21) -> -30
A24: FINANCING ACTIVITIES
A25: Proceeds from Public Offerings | B25: 15000 | C25: 8000 | D25: 25000
A26: Proceeds from Warrant Exercises | B26: 0 | C26: 2000 | D26: 5000 | E26: $67.2M in warrant exercises in 2025
A27: Offering Costs | B27: -1500 | C27: -800 | D27: -2500
A28: Other Financing | B28: -300 | C28: -200 | D28: -100
A29: Net Cash from Financing | B29: =SUM(B25:B28) -> 13200 | C29: =SUM(C25:C28) -> 9000 | D29: =SUM(D25:D28) -> 27400
A31: NET CHANGE IN CASH | B31: =B17+B22+B29 -> 1600 | C31: =C17+C22+C29 -> -15500 | D31: =D17+D22+D29 -> -1980
A33: Cash, Beginning | B33: 22000 | C33: 18500 | D33: 13900
A34: Cash, End of Period | B34: =B33+B31 -> 23600 | C34: =C33+C31 -> 3000 | D34: =D33+D31 -> 11920

Sheet rNPV Model
A1: SELLAS LIFE SCIENCES — Risk-Adjusted NPV (rNPV) Model
A2: Bull / Base / Bear Scenario Analysis (USD $000s unless noted)
A4: KEY ASSUMPTIONS
A5: GPS REGAL Phase 3 Success Probability | B5: 0.45 | C5: Base: ~40% Phase 3 oncology; +5% for positive interim
A6: GPS Peak Revenue Year | B6: 2033 | C6: ~5 years post-approval
A7: GPS Peak Revenue (USD $M) - Bull | B7: 800 | C7: Broad label, strong uptake
A8: GPS Peak Revenue (USD $M) - Base | B8: 450 | C8: AML CR2 maintenance niche
A9: GPS Peak Revenue (USD $M) - Bear | B9: 0 | C9: Trial failure, no approval
A10: SLS009 Phase 2 → Approval Probability | B10: 0.2 | C10: Phase 2 → approval ~15-25%
A11: SLS009 Peak Revenue (USD $M) | B11: 300 | C11: r/r AML + newly diagnosed
A12: Royalty Rate on GPS China License | B12: 0.08 | C12: 3D Medicines agreement
A13: Discount Rate (rNPV) | B13: 0.12 | C13: Biotech risk premium
A14: Terminal Growth Rate | B14: 0 | C14: Patent cliff; no terminal growth
A15: Tax Rate (effective) | B15: 0.21 | C15: US federal; NOL offsets early years
A16: Shares Outstanding - Diluted (M) | B16: 130 | C16: Includes warrants, options
A17: Current Share Price (USD) | B17: 4.76 | C17: Source: NASDAQ, March 2026
A18: Current Market Cap (USD $M) | B18: =B17*B16 -> 618.8
A20: BULL CASE — GPS Approved + Strong Uptake (Prob: 25%)
A21: Probability Weight | B21: 0.25
B22: 2026E | C22: 2027E | D22: 2028E | E22: 2029E | F22: 2030E | G22: 2031E | H22: 2032E | I22: 2033E
A23: GPS Revenue ($M) | B23: 0 | C23: 0 | D23: 50 | E23: 180 | F23: 350 | G23: 550 | H23: 700 | I23: 800
A24: SLS009 Revenue ($M) | B24: 0 | C24: 0 | D24: 0 | E24: 20 | F24: 60 | G24: 120 | H24: 200 | I24: 300
A25: China Royalties ($M) | B25: 0 | C25: 0 | D25: 5 | E25: 15 | F25: 25 | G25: 35 | H25: 40 | I25: 45
A26: Total Revenue ($M) | B26: =B23+B24+B25 -> 0 | C26: =C23+C24+C25 -> 0 | D26: =D23+D24+D25 -> 55 | E26: =E23+E24+E25 -> 215 | F26: =F23+F24+F25 -> 435 | G26: =G23+G24+G25 -> 705 | H26: =H23+H24+H25 -> 940 | I26: =I23+I24+I25 -> 1145
A27: COGS (25% of Rev) | B27: =-B26*0.25 -> 0 | C27: =-C26*0.25 -> 0 | D27: =-D26*0.25 -> -13.75 | E27: =-E26*0.25 -> -53.75 | F27: =-F26*0.25 -> -108.75 | G27: =-G26*0.25 -> -176.25 | H27: =-H26*0.25 -> -235 | I27: =-I26*0.25 -> -286.25
A28: R&D Expense ($M) | B28: 30 | C28: 25 | D28: 20 | E28: 18 | F28: 16 | G28: 15 | H28: 14 | I28: 13
A29: G&A Expense ($M) | B29: 12 | C29: 13 | D29: 15 | E29: 18 | F29: 20 | G29: 22 | H29: 24 | I29: 25
A30: EBITDA ($M) | B30: =B26+B27+B28+B29 -> 42 | C30: =C26+C27+C28+C29 -> 38 | D30: =D26+D27+D28+D29 -> 76.25 | E30: =E26+E27+E28+E29 -> 197.25 | F30: =F26+F27+F28+F29 -> 362.25 | G30: =G26+G27+G28+G29 -> 565.75 | H30: =H26+H27+H28+H29 -> 743 | I30: =I26+I27+I28+I29 -> 896.75
A31: Taxes | B31: =-MAX(0,B30*$B$15) -> -8.82 | C31: =-MAX(0,C30*$B$15) -> -7.98 | D31: =-MAX(0,D30*$B$15) -> -16.0125 | E31: =-MAX(0,E30*$B$15) -> -41.4225 | F31: =-MAX(0,F30*$B$15) -> -76.0725 | G31: =-MAX(0,G30*$B$15) -> -118.8075 | H31: =-MAX(0,H30*$B$15) -> -156.03 | I31: =-MAX(0,I30*$B$15) -> -188.3175
A32: NOPAT ($M) | B32: =B30+B31 -> 33.18 | C32: =C30+C31 -> 30.02 | D32: =D30+D31 -> 60.2375 | E32: =E30+E31 -> 155.8275 | F32: =F30+F31 -> 286.1775 | G32: =G30+G31 -> 446.9425 | H32: =H30+H31 -> 586.97 | I32: =I30+I31 -> 708.4325
A33: Plus: D&A ($M) | B33: 1 | C33: 1 | D33: 2 | E33: 3 | F33: 4 | G33: 5 | H33: 5 | I33: 5
A34: Less: Capex ($M) | B34: -2 | C34: -3 | D34: -5 | E34: -8 | F34: -10 | G34: -10 | H34: -8 | I34: -8
A35: Less: ΔWC ($M) | B35: -2 | C35: -2 | D35: -5 | E35: -8 | F35: -8 | G35: -5 | H35: -3 | I35: -2
A36: Free Cash Flow ($M) | B36: =B32+B33+B34+B35 -> 30.18 | C36: =C32+C33+C34+C35 -> 26.02 | D36: =D32+D33+D34+D35 -> 52.2375 | E36: =E32+E33+E34+E35 -> 142.8275 | F36: =F32+F33+F34+F35 -> 272.1775 | G36: =G32+G33+G34+G35 -> 436.9425 | H36: =H32+H33+H34+H35 -> 580.97 | I36: =I32+I33+I34+I35 -> 703.4325
A37: Discount Factor | B37: =1/(1+$B$13)^1 -> 0.89285714 | C37: =1/(1+$B$13)^2 -> 0.79719388 | D37: =1/(1+$B$13)^3 -> 0.71178025 | E37: =1/(1+$B$13)^4 -> 0.63551808 | F37: =1/(1+$B$13)^5 -> 0.56742686 | G37: =1/(1+$B$13)^6 -> 0.50663112 | H37: =1/(1+$B$13)^7 -> 0.45234922 | I37: =1/(1+$B$13)^8 -> 0.40388323
A38: PV of FCF ($M) | B38: =B36*B37 -> 26.946429 | C38: =C36*C37 -> 20.742985 | D38: =D36*D37 -> 37.181621 | E38: =E36*E37 -> 90.769458 | F38: =F36*F37 -> 154.44082 | G38: =G36*G37 -> 221.36867 | H38: =H36*H37 -> 262.80132 | I38: =I36*I37 -> 284.10459
A40: Sum of PV of FCFs ($M) | B40: =SUM(B38:I38) -> 1098.3559 | I40: Formula: =SUM(PV of each year)
A41: Terminal Value ($M) | B41: =IF($B$14=0,I36/$B$13,I36*(1+$B$14)/($B$13-$B$14))/(1+$B$13)^8 -> 2367.5382 | I41: Formula: PV of Terminal FCF / WACC (no growth)
A42: Bull Case NPV ($M) | B42: =B40+B41 -> 3465.8941
A43: Bull Implied Price/Share (USD) | B43: =(B42*1000+13900)/(B16*1000) -> 26.767647
A45: BASE CASE — GPS Approved + Moderate Uptake (Prob: 45%)
A46: Probability Weight | B46: 0.45
B47: 2026E | C47: 2027E | D47: 2028E | E47: 2029E | F47: 2030E | G47: 2031E | H47: 2032E | I47: 2033E
A48: GPS Revenue ($M) | B48: 0 | C48: 0 | D48: 30 | E48: 100 | F48: 200 | G48: 320 | H48: 400 | I48: 450
A49: SLS009 Revenue ($M) | B49: 0 | C49: 0 | D49: 0 | E49: 10 | F49: 30 | G49: 60 | H49: 100 | I49: 150
A50: China Royalties ($M) | B50: 0 | C50: 0 | D50: 3 | E50: 8 | F50: 15 | G50: 20 | H50: 25 | I50: 30
A51: Total Revenue ($M) | B51: =B48+B49+B50 -> 0 | C51: =C48+C49+C50 -> 0 | D51: =D48+D49+D50 -> 33 | E51: =E48+E49+E50 -> 118 | F51: =F48+F49+F50 -> 245 | G51: =G48+G49+G50 -> 400 | H51: =H48+H49+H50 -> 525 | I51: =I48+I49+I50 -> 630
A52: COGS (25% of Rev) | B52: =-B51*0.25 -> 0 | C52: =-C51*0.25 -> 0 | D52: =-D51*0.25 -> -8.25 | E52: =-E51*0.25 -> -29.5 | F52: =-F51*0.25 -> -61.25 | G52: =-G51*0.25 -> -100 | H52: =-H51*0.25 -> -131.25 | I52: =-I51*0.25 -> -157.5
A53: R&D Expense ($M) | B53: 28 | C53: 22 | D53: 18 | E53: 16 | F53: 15 | G53: 14 | H53: 13 | I53: 12
A54: G&A Expense ($M) | B54: 11 | C54: 12 | D54: 14 | E54: 16 | F54: 18 | G54: 20 | H54: 22 | I54: 23
A55: EBITDA ($M) | B55: =B51+B52+B53+B54 -> 39 | C55: =C51+C52+C53+C54 -> 34 | D55: =D51+D52+D53+D54 -> 56.75 | E55: =E51+E52+E53+E54 -> 120.5 | F55: =F51+F52+F53+F54 -> 216.75 | G55: =G51+G52+G53+G54 -> 334 | H55: =H51+H52+H53+H54 -> 428.75 | I55: =I51+I52+I53+I54 -> 507.5
A56: Taxes | B56: =-MAX(0,B55*$B$15) -> -8.19 | C56: =-MAX(0,C55*$B$15) -> -7.14 | D56: =-MAX(0,D55*$B$15) -> -11.9175 | E56: =-MAX(0,E55*$B$15) -> -25.305 | F56: =-MAX(0,F55*$B$15) -> -45.5175 | G56: =-MAX(0,G55*$B$15) -> -70.14 | H56: =-MAX(0,H55*$B$15) -> -90.0375 | I56: =-MAX(0,I55*$B$15) -> -106.575
A57: NOPAT ($M) | B57: =B55+B56 -> 30.81 | C57: =C55+C56 -> 26.86 | D57: =D55+D56 -> 44.8325 | E57: =E55+E56 -> 95.195 | F57: =F55+F56 -> 171.2325 | G57: =G55+G56 -> 263.86 | H57: =H55+H56 -> 338.7125 | I57: =I55+I56 -> 400.925
A58: Plus: D&A ($M) | B58: 1 | C58: 1 | D58: 1 | E58: 2 | F58: 3 | G58: 4 | H58: 4 | I58: 4
A59: Less: Capex ($M) | B59: -2 | C59: -2 | D59: -4 | E59: -6 | F59: -8 | G59: -8 | H59: -6 | I59: -6
A60: Less: ΔWC ($M) | B60: -2 | C60: -2 | D60: -4 | E60: -6 | F60: -6 | G60: -4 | H60: -2 | I60: -1
A61: Free Cash Flow ($M) | B61: =B57+B58+B59+B60 -> 27.81 | C61: =C57+C58+C59+C60 -> 23.86 | D61: =D57+D58+D59+D60 -> 37.8325 | E61: =E57+E58+E59+E60 -> 85.195 | F61: =F57+F58+F59+F60 -> 160.2325 | G61: =G57+G58+G59+G60 -> 255.86 | H61: =H57+H58+H59+H60 -> 334.7125 | I61: =I57+I58+I59+I60 -> 397.925
A62: Discount Factor | B62: =1/(1+$B$13)^1 -> 0.89285714 | C62: =1/(1+$B$13)^2 -> 0.79719388 | D62: =1/(1+$B$13)^3 -> 0.71178025 | E62: =1/(1+$B$13)^4 -> 0.63551808 | F62: =1/(1+$B$13)^5 -> 0.56742686 | G62: =1/(1+$B$13)^6 -> 0.50663112 | H62: =1/(1+$B$13)^7 -> 0.45234922 | I62: =1/(1+$B$13)^8 -> 0.40388323
A63: PV of FCF ($M) | B63: =B61*B62 -> 24.830357 | C63: =C61*C62 -> 19.021046 | D63: =D61*D62 -> 26.928426 | E63: =E61*E62 -> 54.142963 | F63: =F61*F62 -> 90.920224 | G63: =G61*G62 -> 129.62664 | H63: =H61*H62 -> 151.40694 | I63: =I61*I62 -> 160.71523
A65: Sum of PV of FCFs ($M) | B65: =SUM(B63:I63) -> 657.59182
A66: Terminal Value ($M) | B66: =IF($B$14=0,I61/$B$13,I61*(1+$B$14)/($B$13-$B$14))/(1+$B$13)^8 -> 1339.2936
A67: Base Case NPV ($M) | B67: =B65+B66 -> 1996.8854
A68: Base Implied Price/Share (USD) | B68: =(B67*1000+13900)/(B16*1000) -> 15.46758
A70: BEAR CASE — GPS Fails Phase 3 (Prob: 30%)
A71: Probability Weight | B71: 0.3
B72: 2026E | C72: 2027E | D72: 2028E | E72: 2029E | F72: 2030E | G72: 2031E | H72: 2032E | I72: 2033E
A73: GPS Revenue ($M) | B73: 0 | C73: 0 | D73: 0 | E73: 0 | F73: 0 | G73: 0 | H73: 0 | I73: 0
A74: SLS009 Revenue ($M) | B74: 0 | C74: 0 | D74: 0 | E74: 5 | F74: 15 | G74: 30 | H74: 50 | I74: 75
A75: China Royalties ($M) | B75: 0 | C75: 0 | D75: 0 | E75: 0 | F75: 0 | G75: 0 | H75: 0 | I75: 0
A76: Total Revenue ($M) | B76: =B73+B74+B75 -> 0 | C76: =C73+C74+C75 -> 0 | D76: =D73+D74+D75 -> 0 | E76: =E73+E74+E75 -> 5 | F76: =F73+F74+F75 -> 15 | G76: =G73+G74+G75 -> 30 | H76: =H73+H74+H75 -> 50 | I76: =I73+I74+I75 -> 75
A77: COGS (25% of Rev) | B77: =-B76*0.25 -> 0 | C77: =-C76*0.25 -> 0 | D77: =-D76*0.25 -> 0 | E77: =-E76*0.25 -> -1.25 | F77: =-F76*0.25 -> -3.75 | G77: =-G76*0.25 -> -7.5 | H77: =-H76*0.25 -> -12.5 | I77: =-I76*0.25 -> -18.75
A78: R&D Expense ($M) | B78: 15 | C78: 10 | D78: 8 | E78: 8 | F78: 8 | G78: 7 | H78: 7 | I78: 7
A79: G&A Expense ($M) | B79: 8 | C79: 6 | D79: 5 | E79: 5 | F79: 5 | G79: 5 | H79: 5 | I79: 5
A80: EBITDA ($M) | B80: =B76+B77+B78+B79 -> 23 | C80: =C76+C77+C78+C79 -> 16 | D80: =D76+D77+D78+D79 -> 13 | E80: =E76+E77+E78+E79 -> 16.75 | F80: =F76+F77+F78+F79 -> 24.25 | G80: =G76+G77+G78+G79 -> 34.5 | H80: =H76+H77+H78+H79 -> 49.5 | I80: =I76+I77+I78+I79 -> 68.25
A81: Taxes | B81: =-MAX(0,B80*$B$15) -> -4.83 | C81: =-MAX(0,C80*$B$15) -> -3.36 | D81: =-MAX(0,D80*$B$15) -> -2.73 | E81: =-MAX(0,E80*$B$15) -> -3.5175 | F81: =-MAX(0,F80*$B$15) -> -5.0925 | G81: =-MAX(0,G80*$B$15) -> -7.245 | H81: =-MAX(0,H80*$B$15) -> -10.395 | I81: =-MAX(0,I80*$B$15) -> -14.3325
A82: NOPAT ($M) | B82: =B80+B81 -> 18.17 | C82: =C80+C81 -> 12.64 | D82: =D80+D81 -> 10.27 | E82: =E80+E81 -> 13.2325 | F82: =F80+F81 -> 19.1575 | G82: =G80+G81 -> 27.255 | H82: =H80+H81 -> 39.105 | I82: =I80+I81 -> 53.9175
A83: Plus: D&A ($M) | B83: 1 | C83: 1 | D83: 1 | E83: 1 | F83: 1 | G83: 1 | H83: 1 | I83: 1
A84: Less: Capex ($M) | B84: -1 | C84: -1 | D84: -1 | E84: -1 | F84: -1 | G84: -1 | H84: -1 | I84: -1
A85: Less: ΔWC ($M) | B85: -1 | C85: -1 | D85: -1 | E85: -1 | F85: -1 | G85: -1 | H85: 0 | I85: 0
A86: Free Cash Flow ($M) | B86: =B82+B83+B84+B85 -> 17.17 | C86: =C82+C83+C84+C85 -> 11.64 | D86: =D82+D83+D84+D85 -> 9.27 | E86: =E82+E83+E84+E85 -> 12.2325 | F86: =F82+F83+F84+F85 -> 18.1575 | G86: =G82+G83+G84+G85 -> 26.255 | H86: =H82+H83+H84+H85 -> 39.105 | I86: =I82+I83+I84+I85 -> 53.9175
A87: Discount Factor | B87: =1/(1+$B$13)^1 -> 0.89285714 | C87: =1/(1+$B$13)^2 -> 0.79719388 | D87: =1/(1+$B$13)^3 -> 0.71178025 | E87: =1/(1+$B$13)^4 -> 0.63551808 | F87: =1/(1+$B$13)^5 -> 0.56742686 | G87: =1/(1+$B$13)^6 -> 0.50663112 | H87: =1/(1+$B$13)^7 -> 0.45234922 | I87: =1/(1+$B$13)^8 -> 0.40388323
A88: PV of FCF ($M) | B88: =B86*B87 -> 15.330357 | C88: =C86*C87 -> 9.2793367 | D88: =D86*D87 -> 6.5982029 | E88: =E86*E87 -> 7.7739749 | F88: =F86*F87 -> 10.303053 | G88: =G86*G87 -> 13.3016 | H88: =H86*H87 -> 17.689116 | I88: =I86*I87 -> 21.776374
A90: Sum of PV of FCFs ($M) | B90: =SUM(B88:I88) -> 102.05201
A91: Terminal Value ($M) | B91: =IF($B$14=0,I86/$B$13,I86*(1+$B$14)/($B$13-$B$14))/(1+$B$13)^8 -> 181.46978
A92: Bear Case NPV ($M) | B92: =B90+B91 -> 283.5218
A93: Bear Implied Price/Share (USD) | B93: =(B92*1000+13900)/(B16*1000) -> 2.28786
B96: NPV ($M) | C96: Weight | D96: Weighted NPV ($M)
A97: Bull Case NPV ($M) | B97: =B42 -> 3465.8941 | C97: =B21 -> 0.25 | D97: =B97*C97 -> 866.47353
A98: Base Case NPV ($M) | B98: =B67 -> 1996.8854 | C98: =B46 -> 0.45 | D98: =B98*C98 -> 898.59845
A99: Bear Case NPV ($M) | B99: =B92 -> 283.5218 | C99: =B71 -> 0.3 | D99: =B99*C99 -> 85.056539
A100: Check: Weights Sum to 100% | C100: =C97+C98+C99 -> 1
A101: WEIGHTED rNPV ($M) | D101: =SUM(D97:D99) -> 1850.1285
A102: Weighted rNPV Price/Share (USD) | D102: =(D101*1000+13900)/(B16*1000) -> 14.338681 | I102: Formula: =(Weighted NPV + Cash) / Diluted Shares
A103: Current Price | D103: =B17 -> 4.76
A104: Upside / Downside | D104: =(D102-D103)/D103 -> 2.0123279

Sheet Clinical Probability
A1: GPS REGAL Phase 3 — Probability of Success Analysis
A3: ONCOLOGY DRUG APPROVAL RATES BY PHASE
A4: Phase | B4: General Oncology | C4: Cancer Vaccines | D4: GPS (Adjusted)
A5: Phase 1 → Phase 2 | B5: 0.52 | C5: 0.45 | D5: 0.52
A6: Phase 2 → Phase 3 | B6: 0.289 | C6: 0.2 | D6: 0.35
A7: Phase 3 → NDA/BLA | B7: 0.355 | C7: 0.25 | D7: 0.45
A8: NDA/BLA → Approval | B8: 0.85 | C8: 0.8 | D8: 0.85
A9: Overall (Phase 1 → Approval) | B9: =B5*B6*B7*B8 -> 0.04534699 | C9: =C5*C6*C7*C8 -> 0.018 | D9: =D5*D6*D7*D8 -> 0.069615
A30: GPS REGAL — WHY PROBABILITY IS ELEVATED
A31: Base Phase 3 Oncology Success Rate | B31: 0.355 | C31: Historical average
A32: + Positive IDMC Interim (no futility) | B32: 0.05 | C32: IDMC recommended continuation
A33: + 80% Immunogenicity Response | B33: 0.03 | C33: Exceeds Phase 2 response rate
A34: + OS Endpoint (regulatory favorable) | B34: 0.02 | C34: OS+ trials: 39.7% approval rate
A35: + 72/80 Events Reached (near final) | B35: 0.02 | C35: Trial nearly complete without stopping
A36: + Phase 2 Signal (21mo vs 5.4mo OS) | B36: 0.03 | C36: Strong Phase 2 predecessor data
A37: - Cancer Vaccine Historical Failures | B37: -0.03 | C37: Cancer vaccines have high failure rate
A38: - Small Trial Size (~125 patients) | B38: -0.02 | C38: Limited statistical power risk
A39: ADJUSTED PHASE 3 SUCCESS PROBABILITY | B39: =SUM(B31:B38) -> 0.455
A41: TIME-ON-TRIAL SURVIVAL SIGNAL ANALYSIS
A42: Milestone | B42: Events / Total | C42: Median Follow-Up | D42: Signal Strength | E42: Implication
A43: Trial Start (2020) | B43: 0 / 80 | C43: 0 months | D43: None | E43: Baseline
A44: First Interim (2024) | B44: ~40 / 80 | C44: ~8 months | D44: Moderate | E44: Exceeded futility boundary
A45: IDMC Review (Aug 2025) | B45: ~55 / 80 | C45: ~13.5 months | D45: Strong | E45: Recommended continuation
A46: Dec 2025 Update | B46: 72 / 80 | C46: >18 months | D46: Very Strong | E46: Survival exceeding expectations
A47: Final Analysis (2026E) | B47: 80 / 80 | C47: ~24+ months | D47: Definitive | E47: Primary endpoint readout
A49: EVENT ACCUMULATION (% toward final analysis)
A50: Quarter | B50: % Events Complete | C50: Cumulative Events
A51: Q1 2023 | B51: 0.15 | C51: 12
A52: Q2 2023 | B52: 0.22 | C52: 18
A53: Q3 2023 | B53: 0.3 | C53: 24
A54: Q4 2023 | B54: 0.37 | C54: 30
A55: Q1 2024 | B55: 0.44 | C55: 35
A56: Q2 2024 | B56: 0.5 | C56: 40
A57: Q3 2024 | B57: 0.56 | C57: 45
A58: Q4 2024 | B58: 0.62 | C58: 50
A59: Q1 2025 | B59: 0.69 | C59: 55
A60: Q2 2025 | B60: 0.75 | C60: 60
A61: Q3 2025 | B61: 0.81 | C61: 65
A62: Q4 2025 | B62: 0.9 | C62: 72
... A64: Q2 2026E | B64: 1 | C64: 80
A85: WHY 'MORE TIME = BETTER' FOR GPS
A86: 1. Event-Driven Design | B86: REGAL needs 80 deaths for final analysis. Slower event accumulation = patients living longer.
A87: 2. Crossed Futility | B87: IDMC confirmed GPS exceeded the pre-set futility boundary — the trial would have been stopped if GPS showed no benefit.
A88: 3. Immune Memory | B88: 80% of GPS patients developed WT1-specific T-cell responses. Immune memory strengthens over time.
A89: 4. Historical Comparison | B89: AML CR2 patients historically survive ~6 months. GPS Phase 3 median follow-up >13.5 months with <50% events = significant signal.
A90: 5. Phase 2 Consistency | B90: Phase 2: 21-month median OS vs 5.4 months standard care. Phase 3 interim tracking consistent with this.

Sheet M&A Buyout Analysis
A1: SELLAS LIFE SCIENCES — M&A & Buyout Analysis
A3: PRECEDENT TRANSACTIONS — Cancer Immunotherapy / Vaccine M&A
A4: Target | B4: Acquirer | C4: Year | D4: Deal Value ($M) | E4: Premium | F4: Stage | G4: Notes
A5: Dynavax Technologies | B5: Sanofi | C5: 2025 | D5: 2200 | E5: 0.5 | F5: Commercial | G5: Vaccine platform; $15.50/share
A6: Mirati Therapeutics | B6: BMS | C6: 2024 | D6: 4800 | E6: 0.55 | F6: Phase 3 / FDA | G6: KRAS inhibitor; post-approval
A7: Seagen | B7: Pfizer | C7: 2023 | D7: 43000 | E7: 0.33 | F7: Commercial | G7: ADC oncology platform
A8: Prometheus Bio | B8: Merck | C8: 2023 | D8: 10800 | E8: 0.75 | F8: Phase 2/3 | G8: Immunology; high premium
A9: Immunomedics | B9: Gilead | C9: 2020 | D9: 21000 | E9: 1.08 | F9: Approved | G9: ADC; Trodelvy
A10: Forty Seven | B10: Gilead | C10: 2020 | D10: 4900 | E10: 0.67 | F10: Phase 2 | G10: CD47 immuno-oncology
A11: Celgene (oncology) | B11: BMS | C11: 2019 | D11: 74000 | E11: 0.54 | F11: Commercial | G11: Revlimid franchise
A12: Kite Pharma | B12: Gilead | C12: 2017 | D12: 11900 | E12: 0.29 | F12: Pre-approval | G12: CAR-T cell therapy
A13: Average Premium | E13: =AVERAGE(E5:E12) -> 0.58875
A14: Median Premium | E14: =MEDIAN(E5:E12) -> 0.545
A16: BUYOUT SCENARIO ANALYSIS FOR SLS
A17: Current Market Cap ($M) | B17: ='rNPV Model'!B18 -> 618.8
A18: Current Share Price | B18: ='rNPV Model'!B17 -> 4.76
A19: Shares Outstanding (M) | B19: ='rNPV Model'!B16 -> 130
A21: Scenario | B21: Premium | C21: Buyout Price/Share | D21: Total Deal Value ($M) | E21: Upside from Current
A22: Pre-Approval (Phase 3 data pending) | B22: 0.5 | C22: =B18*(1+B22) -> 7.14 | D22: =C22*B19 -> 928.2 | E22: =B22 -> 0.5
A23: Post-Positive Phase 3 Data | B23: 0.8 | C23: =B18*(1+B23) -> 8.568 | D23: =C23*B19 -> 1113.84 | E23: =B23 -> 0.8
A24: Post-FDA Approval | B24: 1.2 | C24: =B18*(1+B24) -> 10.472 | D24: =C24*B19 -> 1361.36 | E24: =B24 -> 1.2
A25: Competitive Bidding War | B25: 1.5 | C25: =B18*(1+B25) -> 11.9 | D25: =C25*B19 -> 1547 | E25: =B25 -> 1.5
A26: At Median Precedent Premium | B26: =E14 -> 0.545 | C26: =B18*(1+B26) -> 7.3542 | D26: =C26*B19 -> 956.046 | E26: =B26 -> 0.545
A28: POTENTIAL ACQUIRERS
A29: Company | B29: Mkt Cap ($B) | C29: Oncology Focus | D29: Strategic Fit | E29: Likelihood
A30: Pfizer (PFE) | B30: 145 | C30: Hematology, immunology | D30: AML pipeline gap; vaccine expertise | E30: Medium
A31: Bristol-Myers Squibb (BMY) | B31: 115 | C31: Immuno-oncology leader | D31: BMS has Revlimid AML franchise | E31: Medium-High
A32: AbbVie (ABBV) | B32: 330 | C32: Venetoclax in AML | D32: Complements ven/aza combo | E32: Medium
A33: Merck (MRK) | B33: 250 | C33: Keytruda IO franchise | D33: GPS + pembrolizumab combo data | E33: Low-Medium
A34: Johnson & Johnson (JNJ) | B34: 390 | C34: Broad oncology | D34: Vaccine manufacturing capability | E34: Low
A35: Gilead (GILD) | B35: 100 | C35: Cell therapy / onc | D35: History of bold onc acquisitions | E35: Medium
A37: CVR (CONTINGENT VALUE RIGHTS) ANALYSIS
A38: 37% of recent biotech M&A deal value is structured as CVRs (milestone-based payments)
A40: Component | B40: Per Share | C40: Total ($M) | D40: Trigger
A41: Upfront Cash | B41: 7 | C41: =B41*B19 -> 910 | D41: At close
A42: CVR 1: Phase 3 Success | B42: 3 | C42: =B42*B19 -> 390 | D42: Positive REGAL top-line
A43: CVR 2: FDA Approval | B43: 3 | C43: =B43*B19 -> 390 | D43: NDA/BLA approval
A44: CVR 3: Revenue Milestone ($200M) | B44: 2 | C44: =B44*B19 -> 260 | D44: Annual GPS revenue > $200M
A45: Total Potential Deal Value | B45: =SUM(B41:B44) -> 15 | C45: =B45*B19 -> 1950
A47: BUYOUT PROBABILITY ASSESSMENT
A48: Pre-Data Readout (Current) | B48: 0.15 | C48: Trial near complete; acquirer may wait
A49: Post-Positive Phase 3 | B49: 0.35 | C49: Validated asset; high pharma interest
A50: Post-FDA Approval | B50: 0.55 | C50: De-risked; commercial stage
A51: Within 3 Years | B51: 0.4 | C51: Multiple catalyst windows

Sheet Peer Comps & Summary
A1: SELLAS LIFE SCIENCES — Peer Comparables & Valuation Summary
A3: COMPARABLE COMPANIES — Clinical-Stage Oncology / Immunotherapy
A4: Company | B4: Ticker | C4: Mkt Cap ($M) | D4: Cash ($M) | E4: Lead Stage | F4: Burn Rate ($M/yr) | G4: Cash Runway (Yrs) | H4: Pipeline Assets
A5: Agenus Inc | B5: AGEN | C5: 850 | D5: 120 | E5: Phase 3 | F5: 90 | G5: =D5/(F5/1000) -> 1333.3333 | H5: 4
A6: Inovio Pharmaceuticals | B6: INO | C6: 420 | D6: 180 | E6: Phase 3 | F6: 95 | G6: =D6/(F6/1000) -> 1894.7368 | H6: 5
A7: Gritstone bio | B7: GRTS | C7: 180 | D7: 85 | E7: Phase 2 | F7: 70 | G7: =D7/(F7/1000) -> 1214.2857 | H7: 3
A8: Marker Therapeutics | B8: MRKR | C8: 65 | D8: 25 | E8: Phase 2 | F8: 20 | G8: =D8/(F8/1000) -> 1250 | H8: 2
A9: SELLAS Life Sciences | B9: SLS | C9: ='rNPV Model'!B18 -> 618.8 | D9: ='Balance Sheet'!D6 -> 44300 | E9: Phase 3 | F9: ='Income Statement'!D13 -> 31500 | G9: =D9/(F9/1000) -> 1406.3492 | H9: 2
A10: Peer Average (excl. SLS) | C10: =AVERAGE(C5:C8) -> 378.75
A12: COMPREHENSIVE VALUATION SUMMARY
A13: Methodology | B13: Bull ($) | C13: Base ($) | D13: Bear ($) | E13: Wtd Avg ($) | F13: Weight
A14: rNPV Model | B14: ='rNPV Model'!B43 -> 26.767647 | C14: ='rNPV Model'!B68 -> 15.46758 | D14: ='rNPV Model'!B93 -> 2.28786 | E14: =B14*0.25+C14*0.45+D14*0.3 -> 14.338681 | F14: 0.4
A15: Buyout Value (Pre-Data) | B15: ='M&A Buyout Analysis'!C23 -> 8.568 | C15: ='M&A Buyout Analysis'!C22 -> 7.14 | D15: ='rNPV Model'!B17 -> 4.76 | E15: =B15*0.25+C15*0.45+D15*0.3 -> 6.783 | F15: 0.15
A16: Buyout Value (Post-Approval) | B16: ='M&A Buyout Analysis'!C25 -> 11.9 | C16: ='M&A Buyout Analysis'!C24 -> 10.472 | D16: ='rNPV Model'!B17 -> 4.76 | E16: =B16*0.25+C16*0.45+D16*0.3 -> 9.1154 | F16: 0.15
A17: Sum-of-Parts (GPS + SLS009) | B17: ='rNPV Model'!B43*0.85+'rNPV Model'!B43*0.15 -> 26.767647 | C17: ='rNPV Model'!B68*0.85+'rNPV Model'!B68*0.15 -> 15.46758 | D17: ='rNPV Model'!B93 -> 2.28786 | E17: =B17*0.25+C17*0.45+D17*0.3 -> 14.338681 | F17: 0.2
A18: Cash per Share (Floor) | B18: ='Balance Sheet'!D6/('rNPV Model'!B16*1000) -> 0.34076923 | C18: ='Balance Sheet'!D6/('rNPV Model'!B16*1000) -> 0.34076923 | D18: ='Balance Sheet'!D6/('rNPV Model'!B16*1000) -> 0.34076923 | E18: =B18*0.25+C18*0.45+D18*0.3 -> 0.34076923 | F18: 0.1
A19: BLENDED TARGET PRICE (USD) | E19: =SUMPRODUCT(E14:E18,F14:F18) -> 11.022045 | I19: Formula: =SUMPRODUCT(Wtd Avg Prices × Model Weights)
A20: Current Price | E20: ='rNPV Model'!B17 -> 4.76
A21: Upside / Downside | E21: =(E19-E20)/E20 -> 1.3155558
A23: KEY RISKS
A24: 1. Binary Phase 3 outcome: GPS success/failure is the dominant variable
A25: 2. 27% short interest indicates significant market skepticism
A26: 3. Cash burn (~$31M/yr) requires continued capital raises if trial delays
A27: 4. Cancer vaccines have historically high failure rates despite promising signals
A28: 5. Small trial size (~125 patients) limits statistical power
A29: 6. Dilution risk: warrants + future offerings could increase share count
